Workbook

Sheet 📊 Dashboard Control
A1: PANEL DE CONTROL E INVENTARIOS - POLE DANCE ACADEMY
A3: ⚡ CONSULTA RÁPIDA DE PRODUCTO Y CONSECUTIVO
A4: Escribe el Código de Prenda: | C4: TM
A5: Descripción del Producto: | C5: =IFERROR(VLOOKUP(C4,#REF!, 3, FALSE()), "⚠️ Código no encontrado") -> ⚠️ Código no encontrado
A6: Talla: | C6: =IFERROR(VLOOKUP(C4,#REF!, 4, FALSE()), "-") -> -
A7: Precio de Venta Unitario: | C7: =IFERROR(VLOOKUP(C4,#REF!, 6, FALSE()), 0) -> 0
A8: Existencias Actuales (Stock): | C8: =IFERROR(VLOOKUP(C4,#REF!, 10, FALSE()), 0) -> 0
A9: Total Unidades Vendidas: | C9: =SUMIF('🛒 Ventas'!C:C, C4, '🛒 Ventas'!G:G) -> 0
A10: PRÓXIMO CONSECUTIVO DE VENTA: | C10: =IF(C4="","", C4 & (SUMIF('🛒 Ventas'!C:C, C4, '🛒 Ventas'!G:G) + 1)) -> TM1
A12: RESUMEN GENERAL ACADEMIA
A14: UNIDADES EN STOCK | C14: VALOR INVENTARIO ROPA | E14: VENTAS TOTALES ($) | G14: VALOR ACTIVOS FIJOS ($) | I14: GASTOS TOTALES ($) | K14: BALANCE NETO ($)
A15: =SUM(Marcancia!G:G)-SUM('🛒 Ventas'!G:G) -> 71 | C15: =IFERROR((SUM(Marcancia!J:J)/SUM(Marcancia!G:G))*A15,0) -> 2787150 | E15: =SUM('🛒 Ventas'!I2:I41) -> 0 | G15: =SUM('🏢 Activos Fijos'!H2:H47) -> 20857007 | I15: =SUM('💸 Gastos'!E2:E65) -> 14256280 | K15: =E15-I15 -> -14256280
A19: VENTAS POR TIPO DE PRENDA | E19: VENTAS POR MÉTODO DE PAGO
A21: Tipo Prenda | B21: Unidades Vendidas | C21: Total Recaudado ($) | E21: Método Pago | F21: N° Transacciones | G21: Total ($)
A22: Short (S) | B22: =SUMIF('🛒 Ventas'!C:C, "S*", '🛒 Ventas'!G:G) -> 0 | C22: =SUMIF('🛒 Ventas'!C:C, "S*", '🛒 Ventas'!I:I) -> 0 | E22: Nequi | F22: =COUNTIF('🛒 Ventas'!J:J, "Nequi") -> 1 | G22: =SUMIF('🛒 Ventas'!J:J, "Nequi", '🛒 Ventas'!I:I) -> 0
A23: Pantalón (P) | B23: =SUMIF('🛒 Ventas'!C:C, "P*", '🛒 Ventas'!G:G) -> 0 | C23: =SUMIF('🛒 Ventas'!C:C, "P*", '🛒 Ventas'!I:I) -> 0 | E23: Daviplata | F23: =COUNTIF('🛒 Ventas'!J:J, "Daviplata") -> 0 | G23: =SUMIF('🛒 Ventas'!J:J, "Daviplata", '🛒 Ventas'!I:I) -> 0
A24: Top/Sujetador (T) | B24: =SUMIF('🛒 Ventas'!C:C, "T*", '🛒 Ventas'!G:G) -> 0 | C24: =SUMIF('🛒 Ventas'!C:C, "T*", '🛒 Ventas'!I:I) -> 0 | E24: Efectivo | F24: =COUNTIF('🛒 Ventas'!J:J, "Efectivo") -> 0 | G24: =SUMIF('🛒 Ventas'!J:J, "Efectivo", '🛒 Ventas'!I:I) -> 0
A25: Body (B) | B25: =SUMIF('🛒 Ventas'!C:C, "B*", '🛒 Ventas'!G:G) -> 0 | C25: =SUMIF('🛒 Ventas'!C:C, "B*", '🛒 Ventas'!I:I) -> 0 | E25: Transferencia Bancaria | F25: =COUNTIF('🛒 Ventas'!J:J, "Transferencia Bancaria") -> 0 | G25: =SUMIF('🛒 Ventas'!J:J, "Transferencia Bancaria", '🛒 Ventas'!I:I) -> 0
A26: Accesorio (A) | B26: =SUMIF('🛒 Ventas'!C:C, "A*", '🛒 Ventas'!G:G) -> 0 | C26: =SUMIF('🛒 Ventas'!C:C, "A*", '🛒 Ventas'!I:I) -> 0 | E26: Tarjeta Débito/Crédito | F26: =COUNTIF('🛒 Ventas'!J:J, "Tarjeta Débito/Crédito") -> 0 | G26: =SUMIF('🛒 Ventas'!J:J, "Tarjeta Débito/Crédito", '🛒 Ventas'!I:I) -> 0
A27: TOTALES | B27: =SUM(B22:B26) -> 0 | C27: =SUM(C22:C26) -> 0 | E27: TOTALES | F27: =SUM(F22:F26) -> 1 | G27: =SUM(G22:G26) -> 0

Sheet 📈 Resumen Dinámico
A1: RESUMEN DINÁMICO
A2: Estas tablas se recalculan solas a partir de Gastos y Ventas. No las edites directamente.
A4: GASTOS POR CATEGORÍA | F4: GASTOS POR MÉTODO DE PAGO
A5: Categoría | B5: N° Registros | C5: Total ($) | F5: Método Pago | G5: N° Registros | H5: Total ($)
A6: Arriendo | B6: =COUNTIF('💸 Gastos'!C:C,"Arriendo") -> 2 | C6: =SUMIF('💸 Gastos'!C:C,"Arriendo",'💸 Gastos'!E:E) -> 3950000 | F6: Nequi | G6: =COUNTIF('💸 Gastos'!H:H,"Nequi") -> 0 | H6: =SUMIF('💸 Gastos'!H:H,"Nequi",'💸 Gastos'!E:E) -> 0
A7: Servicios Públicos | B7: =COUNTIF('💸 Gastos'!C:C,"Servicios Públicos") -> 1 | C7: =SUMIF('💸 Gastos'!C:C,"Servicios Públicos",'💸 Gastos'!E:E) -> 35850 | F7: Daviplata | G7: =COUNTIF('💸 Gastos'!H:H,"Daviplata") -> 0 | H7: =SUMIF('💸 Gastos'!H:H,"Daviplata",'💸 Gastos'!E:E) -> 0
A8: Nómina / Personal | B8: =COUNTIF('💸 Gastos'!C:C,"Nómina / Personal") -> 1 | C8: =SUMIF('💸 Gastos'!C:C,"Nómina / Personal",'💸 Gastos'!E:E) -> 906000 | F8: Efectivo | G8: =COUNTIF('💸 Gastos'!H:H,"Efectivo") -> 62 | H8: =SUMIF('💸 Gastos'!H:H,"Efectivo",'💸 Gastos'!E:E) -> 14256280
A9: Insumos y Aseo | B9: =COUNTIF('💸 Gastos'!C:C,"Insumos y Aseo") -> 8 | C9: =SUMIF('💸 Gastos'!C:C,"Insumos y Aseo",'💸 Gastos'!E:E) -> 398403 | F9: Transferencia Bancaria | G9: =COUNTIF('💸 Gastos'!H:H,"Transferencia Bancaria") -> 0 | H9: =SUMIF('💸 Gastos'!H:H,"Transferencia Bancaria",'💸 Gastos'!E:E) -> 0
A10: Mantenimiento Equipos | B10: =COUNTIF('💸 Gastos'!C:C,"Mantenimiento Equipos") -> 0 | C10: =SUMIF('💸 Gastos'!C:C,"Mantenimiento Equipos",'💸 Gastos'!E:E) -> 0 | F10: Tarjeta Débito/Crédito | G10: =COUNTIF('💸 Gastos'!H:H,"Tarjeta Débito/Crédito") -> 0 | H10: =SUMIF('💸 Gastos'!H:H,"Tarjeta Débito/Crédito",'💸 Gastos'!E:E) -> 0
A11: Marketing y Publicidad | B11: =COUNTIF('💸 Gastos'!C:C,"Marketing y Publicidad") -> 8 | C11: =SUMIF('💸 Gastos'!C:C,"Marketing y Publicidad",'💸 Gastos'!E:E) -> 554179 | F11: TOTAL | G11: =SUM(G6:G10) -> 62 | H11: =SUM(H6:H10) -> 14256280
A12: Software / Suscripciones | B12: =COUNTIF('💸 Gastos'!C:C,"Software / Suscripciones") -> 0 | C12: =SUMIF('💸 Gastos'!C:C,"Software / Suscripciones",'💸 Gastos'!E:E) -> 0
A13: Mantenimiento Local/Infraestructura | B13: =COUNTIF('💸 Gastos'!C:C,"Mantenimiento Local/Infraestructura") -> 2 | C13: =SUMIF('💸 Gastos'!C:C,"Mantenimiento Local/Infraestructura",'💸 Gastos'!E:E) -> 6364500
A14: Envíos/Transporte | B14: =COUNTIF('💸 Gastos'!C:C,"Envíos/Transporte") -> 1 | C14: =SUMIF('💸 Gastos'!C:C,"Envíos/Transporte",'💸 Gastos'!E:E) -> 195000
A15: Otros | B15: =COUNTIF('💸 Gastos'!C:C,"Otros") -> 0 | C15: =SUMIF('💸 Gastos'!C:C,"Otros",'💸 Gastos'!E:E) -> 0
A16: TOTAL | B16: =SUM(B6:B15) -> 23 | C16: =SUM(C6:C15) -> 12403932
A18: VENTAS POR COLOR
A19: Color | B19: Unidades Vendidas | C19: Total ($)
A20: Negro | B20: =SUMIF('🛒 Ventas'!F:F,"Negro",'🛒 Ventas'!G:G) -> 0 | C20: =SUMIF('🛒 Ventas'!F:F,"Negro",'🛒 Ventas'!I:I) -> 0
A21: Azul | B21: =SUMIF('🛒 Ventas'!F:F,"Azul",'🛒 Ventas'!G:G) -> 0 | C21: =SUMIF('🛒 Ventas'!F:F,"Azul",'🛒 Ventas'!I:I) -> 0
A22: Rojo | B22: =SUMIF('🛒 Ventas'!F:F,"Rojo",'🛒 Ventas'!G:G) -> 0 | C22: =SUMIF('🛒 Ventas'!F:F,"Rojo",'🛒 Ventas'!I:I) -> 0
A23: Verde | B23: =SUMIF('🛒 Ventas'!F:F,"Verde",'🛒 Ventas'!G:G) -> 0 | C23: =SUMIF('🛒 Ventas'!F:F,"Verde",'🛒 Ventas'!I:I) -> 0
A24: Amarillo | B24: =SUMIF('🛒 Ventas'!F:F,"Amarillo",'🛒 Ventas'!G:G) -> 0 | C24: =SUMIF('🛒 Ventas'!F:F,"Amarillo",'🛒 Ventas'!I:I) -> 0
A25: Blanco | B25: =SUMIF('🛒 Ventas'!F:F,"Blanco",'🛒 Ventas'!G:G) -> 0 | C25: =SUMIF('🛒 Ventas'!F:F,"Blanco",'🛒 Ventas'!I:I) -> 0
A26: TOTAL | B26: =SUM(B20:B25) -> 0 | C26: =SUM(C20:C25) -> 0

Sheet 🎓 Alumnas
A1: ID Alumna | B1: Nombre | C1: Cel | D1: Correo | E1: Dirección | F1: Fecha de nacimiento | G1: Edad | H1: N° de inscripciones (paquetes) | I1: N° de pagos registrados | J1: Total pagado ($) | K1: Primera fecha | L1: Última fecha | M1: Estado
A2: A-001 | B2: Ana Carolina Lopez Galvan | C2: 3229015452 | D2: anacaloga88@gmail.com | E2: carrera 79a#16f | F2: 32232 | G2: =IF(F2="","",DATEDIF(F2,TODAY(),"Y")) -> 38 | H2: =IF(B2="","",COUNTIFS('🤸 Ingresos Pole'!$C$2:$C$1000,B2,'🤸 Ingresos Pole'!$J$2:$J$1000,"Paquete")) -> 1 | I2: =IF(B2="","",COUNTIF('🤸 Ingresos Pole'!$C$2:$C$1000,B2)) -> 1 | J2: =IF(B2="","",SUMIF('🤸 Ingresos Pole'!$C$2:$C$1000,B2,'🤸 Ingresos Pole'!$N$2:$N$1000)) -> 200000 | K2: =IF(OR(B2="",I2=0),"",_xlfn.MINIFS('🤸 Ingresos Pole'!$B$2:$B$1000,'🤸 Ingresos Pole'!$C$2:$C$1000,B2)) -> 46264 | L2: =IF(OR(B2="",I2=0),"",_xlfn.MAXIFS('🤸 Ingresos Pole'!$B$2:$B$1000,'🤸 Ingresos Pole'!$C$2:$C$1000,B2)) -> 46264 | M2: =IF(OR(B2="",I2=0),"",IF(H2=0,"Sin paquete",IF(H2=1,"Nueva","Recurrente"))) -> Nueva
A3: A-002 | B3: Francya Damaris Arias Ospitia | C3: 3142183412 | D3: fraariaspi@hotmail.com | E3: Cra 73# 7f-07 | F3: 27887 | G3: =IF(F3="","",DATEDIF(F3,TODAY(),"Y")) -> 50 | H3: =IF(B3="","",COUNTIFS('🤸 Ingresos Pole'!$C$2:$C$1000,B3,'🤸 Ingresos Pole'!$J$2:$J$1000,"Paquete")) -> 1 | I3: =IF(B3="","",COUNTIF('🤸 Ingresos Pole'!$C$2:$C$1000,B3)) -> 1 | J3: =IF(B3="","",SUMIF('🤸 Ingresos Pole'!$C$2:$C$1000,B3,'🤸 Ingresos Pole'!$N$2:$N$1000)) -> 350000 | K3: =IF(OR(B3="",I3=0),"",_xlfn.MINIFS('🤸 Ingresos Pole'!$B$2:$B$1000,'🤸 Ingresos Pole'!$C$2:$C$1000,B3)) -> 46265 | L3: =IF(OR(B3="",I3=0),"",_xlfn.MAXIFS('🤸 Ingresos Pole'!$B$2:$B$1000,'🤸 Ingresos Pole'!$C$2:$C$1000,B3)) -> 46265 | M3: =IF(OR(B3="",I3=0),"",IF(H3=0,"Sin paquete",IF(H3=1,"Nueva","Recurrente"))) -> Nueva
A4: A-003 | B4: Diana Bermudez Cardona | C4: 3196364084 | D4: diana0.bermudez@gmail.com | E4: Cra 72k # 39a 96 sur | F4: 33374 | G4: =IF(F4="","",DATEDIF(F4,TODAY(),"Y")) -> 35 | H4: =IF(B4="","",COUNTIFS('🤸 Ingresos Pole'!$C$2:$C$1000,B4,'🤸 Ingresos Pole'!$J$2:$J$1000,"Paquete")) -> 2 | I4: =IF(B4="","",COUNTIF('🤸 Ingresos Pole'!$C$2:$C$1000,B4)) -> 2 | J4: =IF(B4="","",SUMIF('🤸 Ingresos Pole'!$C$2:$C$1000,B4,'🤸 Ingresos Pole'!$N$2:$N$1000)) -> 960000 | K4: =IF(OR(B4="",I4=0),"",_xlfn.MINIFS('🤸 Ingresos Pole'!$B$2:$B$1000,'🤸 Ingresos Pole'!$C$2:$C$1000,B4)) -> 46264 | L4: =IF(OR(B4="",I4=0),"",_xlfn.MAXIFS('🤸 Ingresos Pole'!$B$2:$B$1000,'🤸 Ingresos Pole'!$C$2:$C$1000,B4)) -> 46295 | M4: =IF(OR(B4="",I4=0),"",IF(H4=0,"Sin paquete",IF(H4=1,"Nueva","Recurrente"))) -> Recurrente
A5: A-004 | B5: Jessica Torres Olarte | C5: 3104775381 | D5: Jessicatorresolarte@gmail.com | E5: Calle 6b 80b 85 | F5: 31592 | G5: =IF(F5="","",DATEDIF(F5,TODAY(),"Y")) -> 40 | H5: =IF(B5="","",COUNTIFS('🤸 Ingresos Pole'!$C$2:$C$1000,B5,'🤸 Ingresos Pole'!$J$2:$J$1000,"Paquete")) -> 2 | I5: =IF(B5="","",COUNTIF('🤸 Ingresos Pole'!$C$2:$C$1000,B5)) -> 2 | J5: =IF(B5="","",SUMIF('🤸 Ingresos Pole'!$C$2:$C$1000,B5,'🤸 Ingresos Pole'!$N$2:$N$1000)) -> 0 | K5: =IF(OR(B5="",I5=0),"",_xlfn.MINIFS('🤸 Ingresos Pole'!$B$2:$B$1000,'🤸 Ingresos Pole'!$C$2:$C$1000,B5)) -> 46264 | L5: =IF(OR(B5="",I5=0),"",_xlfn.MAXIFS('🤸 Ingresos Pole'!$B$2:$B$1000,'🤸 Ingresos Pole'!$C$2:$C$1000,B5)) -> 46295 | M5: =IF(OR(B5="",I5=0),"",IF(H5=0,"Sin paquete",IF(H5=1,"Nueva","Recurrente"))) -> Recurrente
A6: A-005 | B6: Laura Camila Ramirez Galvis | G6: =IF(F6="","",DATEDIF(F6,TODAY(),"Y")) | H6: =IF(B6="","",COUNTIFS('🤸 Ingresos Pole'!$C$2:$C$1000,B6,'🤸 Ingresos Pole'!$J$2:$J$1000,"Paquete")) -> 1 | I6: =IF(B6="","",COUNTIF('🤸 Ingresos Pole'!$C$2:$C$1000,B6)) -> 1 | J6: =IF(B6="","",SUMIF('🤸 Ingresos Pole'!$C$2:$C$1000,B6,'🤸 Ingresos Pole'!$N$2:$N$1000)) -> 480000 | K6: =IF(OR(B6="",I6=0),"",_xlfn.MINIFS('🤸 Ingresos Pole'!$B$2:$B$1000,'🤸 Ingresos Pole'!$C$2:$C$1000,B6)) -> 46265 | L6: =IF(OR(B6="",I6=0),"",_xlfn.MAXIFS('🤸 Ingresos Pole'!$B$2:$B$1000,'🤸 Ingresos Pole'!$C$2:$C$1000,B6)) -> 46265 | M6: =IF(OR(B6="",I6=0),"",IF(H6=0,"Sin paquete",IF(H6=1,"Nueva","Recurrente"))) -> Nueva
A7: A-006 | B7: Juliana Bossa | C7: 3185937737 | G7: =IF(F7="","",DATEDIF(F7,TODAY(),"Y")) | H7: =IF(B7="","",COUNTIFS('🤸 Ingresos Pole'!$C$2:$C$1000,B7,'🤸 Ingresos Pole'!$J$2:$J$1000,"Paquete")) -> 0 | I7: =IF(B7="","",COUNTIF('🤸 Ingresos Pole'!$C$2:$C$1000,B7)) -> 2 | J7: =IF(B7="","",SUMIF('🤸 Ingresos Pole'!$C$2:$C$1000,B7,'🤸 Ingresos Pole'!$N$2:$N$1000)) -> 44000 | K7: =IF(OR(B7="",I7=0),"",_xlfn.MINIFS('🤸 Ingresos Pole'!$B$2:$B$1000,'🤸 Ingresos Pole'!$C$2:$C$1000,B7)) -> 46267 | L7: =IF(OR(B7="",I7=0),"",_xlfn.MAXIFS('🤸 Ingresos Pole'!$B$2:$B$1000,'🤸 Ingresos Pole'!$C$2:$C$1000,B7)) -> 46283 | M7: =IF(OR(B7="",I7=0),"",IF(H7=0,"Sin paquete",IF(H7=1,"Nueva","Recurrente"))) -> Sin paquete
A8: A-007 | B8: Laura Vanesa Guerra | G8: =IF(F8="","",DATEDIF(F8,TODAY(),"Y")) | H8: =IF(B8="","",COUNTIFS('🤸 Ingresos Pole'!$C$2:$C$1000,B8,'🤸 Ingresos Pole'!$J$2:$J$1000,"Paquete")) -> 2 | I8: =IF(B8="","",COUNTIF('🤸 Ingresos Pole'!$C$2:$C$1000,B8)) -> 2 | J8: =IF(B8="","",SUMIF('🤸 Ingresos Pole'!$C$2:$C$1000,B8,'🤸 Ingresos Pole'!$N$2:$N$1000)) -> 480000 | K8: =IF(OR(B8="",I8=0),"",_xlfn.MINIFS('🤸 Ingresos Pole'!$B$2:$B$1000,'🤸 Ingresos Pole'!$C$2:$C$1000,B8)) -> 46267 | L8: =IF(OR(B8="",I8=0),"",_xlfn.MAXIFS('🤸 Ingresos Pole'!$B$2:$B$1000,'🤸 Ingresos Pole'!$C$2:$C$1000,B8)) -> 46295 | M8: =IF(OR(B8="",I8=0),"",IF(H8=0,"Sin paquete",IF(H8=1,"Nueva","Recurrente"))) -> Recurrente
A9: A-008 | B9: Shirley Dayana Chavarro | C9: 3115269836 | G9: =IF(F9="","",DATEDIF(F9,TODAY(),"Y")) | H9: =IF(B9="","",COUNTIFS('🤸 Ingresos Pole'!$C$2:$C$1000,B9,'🤸 Ingresos Pole'!$J$2:$J$1000,"Paquete")) -> 2 | I9: =IF(B9="","",COUNTIF('🤸 Ingresos Pole'!$C$2:$C$1000,B9)) -> 2 | J9: =IF(B9="","",SUMIF('🤸 Ingresos Pole'!$C$2:$C$1000,B9,'🤸 Ingresos Pole'!$N$2:$N$1000)) -> 480000 | K9: =IF(OR(B9="",I9=0),"",_xlfn.MINIFS('🤸 Ingresos Pole'!$B$2:$B$1000,'🤸 Ingresos Pole'!$C$2:$C$1000,B9)) -> 46267 | L9: =IF(OR(B9="",I9=0),"",_xlfn.MAXIFS('🤸 Ingresos Pole'!$B$2:$B$1000,'🤸 Ingresos Pole'!$C$2:$C$1000,B9)) -> 46295 | M9: =IF(OR(B9="",I9=0),"",IF(H9=0,"Sin paquete",IF(H9=1,"Nueva","Recurrente"))) -> Recurrente
A10: A-009 | B10: Maria Paula Leon | G10: =IF(F10="","",DATEDIF(F10,TODAY(),"Y")) | H10: =IF(B10="","",COUNTIFS('🤸 Ingresos Pole'!$C$2:$C$1000,B10,'🤸 Ingresos Pole'!$J$2:$J$1000,"Paquete")) -> 1 | I10: =IF(B10="","",COUNTIF('🤸 Ingresos Pole'!$C$2:$C$1000,B10)) -> 1 | J10: =IF(B10="","",SUMIF('🤸 Ingresos Pole'!$C$2:$C$1000,B10,'🤸 Ingresos Pole'!$N$2:$N$1000)) -> 240000 | K10: =IF(OR(B10="",I10=0),"",_xlfn.MINIFS('🤸 Ingresos Pole'!$B$2:$B$1000,'🤸 Ingresos Pole'!$C$2:$C$1000,B10)) -> 46267 | L10: =IF(OR(B10="",I10=0),"",_xlfn.MAXIFS('🤸 Ingresos Pole'!$B$2:$B$1000,'🤸 Ingresos Pole'!$C$2:$C$1000,B10)) -> 46267 | M10: =IF(OR(B10="",I10=0),"",IF(H10=0,"Sin paquete",IF(H10=1,"Nueva","Recurrente"))) -> Nueva
A11: A-010 | B11: Ntalia Alejandra Luna | G11: =IF(F11="","",DATEDIF(F11,TODAY(),"Y")) | H11: =IF(B11="","",COUNTIFS('🤸 Ingresos Pole'!$C$2:$C$1000,B11,'🤸 Ingresos Pole'!$J$2:$J$1000,"Paquete")) -> 1 | I11: =IF(B11="","",COUNTIF('🤸 Ingresos Pole'!$C$2:$C$1000,B11)) -> 1 | J11: =IF(B11="","",SUMIF('🤸 Ingresos Pole'!$C$2:$C$1000,B11,'🤸 Ingresos Pole'!$N$2:$N$1000)) -> 240000 | K11: =IF(OR(B11="",I11=0),"",_xlfn.MINIFS('🤸 Ingresos Pole'!$B$2:$B$1000,'🤸 Ingresos Pole'!$C$2:$C$1000,B11)) -> 46272 | L11: =IF(OR(B11="",I11=0),"",_xlfn.MAXIFS('🤸 Ingresos Pole'!$B$2:$B$1000,'🤸 Ingresos Pole'!$C$2:$C$1000,B11)) -> 46272 | M11: =IF(OR(B11="",I11=0),"",IF(H11=0,"Sin paquete",IF(H11=1,"Nueva","Recurrente"))) -> Nueva
A12: A-011 | B12: Marcella Cuellar | G12: =IF(F12="","",DATEDIF(F12,TODAY(),"Y")) | H12: =IF(B12="","",COUNTIFS('🤸 Ingresos Pole'!$C$2:$C$1000,B12,'🤸 Ingresos Pole'!$J$2:$J$1000,"Paquete")) -> 1 | I12: =IF(B12="","",COUNTIF('🤸 Ingresos Pole'!$C$2:$C$1000,B12)) -> 1 | J12: =IF(B12="","",SUMIF('🤸 Ingresos Pole'!$C$2:$C$1000,B12,'🤸 Ingresos Pole'!$N$2:$N$1000)) -> 240000 | K12: =IF(OR(B12="",I12=0),"",_xlfn.MINIFS('🤸 Ingresos Pole'!$B$2:$B$1000,'🤸 Ingresos Pole'!$C$2:$C$1000,B12)) -> 46272 | L12: =IF(OR(B12="",I12=0),"",_xlfn.MAXIFS('🤸 Ingresos Pole'!$B$2:$B$1000,'🤸 Ingresos Pole'!$C$2:$C$1000,B12)) -> 46272 | M12: =IF(OR(B12="",I12=0),"",IF(H12=0,"Sin paquete",IF(H12=1,"Nueva","Recurrente"))) -> Nueva
A13: A-012 | B13: Danial Avila | G13: =IF(F13="","",DATEDIF(F13,TODAY(),"Y")) | H13: =IF(B13="","",COUNTIFS('🤸 Ingresos Pole'!$C$2:$C$1000,B13,'🤸 Ingresos Pole'!$J$2:$J$1000,"Paquete")) -> 0 | I13: =IF(B13="","",COUNTIF('🤸 Ingresos Pole'!$C$2:$C$1000,B13)) -> 2 | J13: =IF(B13="","",SUMIF('🤸 Ingresos Pole'!$C$2:$C$1000,B13,'🤸 Ingresos Pole'!$N$2:$N$1000)) -> 44000 | K13: =IF(OR(B13="",I13=0),"",_xlfn.MINIFS('🤸 Ingresos Pole'!$B$2:$B$1000,'🤸 Ingresos Pole'!$C$2:$C$1000,B13)) -> 46274 | L13: =IF(OR(B13="",I13=0),"",_xlfn.MAXIFS('🤸 Ingresos Pole'!$B$2:$B$1000,'🤸 Ingresos Pole'!$C$2:$C$1000,B13)) -> 46281 | M13: =IF(OR(B13="",I13=0),"",IF(H13=0,"Sin paquete",IF(H13=1,"Nueva","Recurrente"))) -> Sin paquete
A14: A-013 | B14: Karol Sierra | G14: =IF(F14="","",DATEDIF(F14,TODAY(),"Y")) | H14: =IF(B14="","",COUNTIFS('🤸 Ingresos Pole'!$C$2:$C$1000,B14,'🤸 Ingresos Pole'!$J$2:$J$1000,"Paquete")) -> 0 | I14: =IF(B14="","",COUNTIF('🤸 Ingresos Pole'!$C$2:$C$1000,B14)) -> 4 | J14: =IF(B14="","",SUMIF('🤸 Ingresos Pole'!$C$2:$C$1000,B14,'🤸 Ingresos Pole'!$N$2:$N$1000)) -> 132000 | K14: =IF(OR(B14="",I14=0),"",_xlfn.MINIFS('🤸 Ingresos Pole'!$B$2:$B$1000,'🤸 Ingresos Pole'!$C$2:$C$1000,B14)) -> 46274 | L14: =IF(OR(B14="",I14=0),"",_xlfn.MAXIFS('🤸 Ingresos Pole'!$B$2:$B$1000,'🤸 Ingresos Pole'!$C$2:$C$1000,B14)) -> 46295 | M14: =IF(OR(B14="",I14=0),"",IF(H14=0,"Sin paquete",IF(H14=1,"Nueva","Recurrente"))) -> Sin paquete
A15: A-014 | B15: Maira Alejandra Vergara | G15: =IF(F15="","",DATEDIF(F15,TODAY(),"Y")) | H15: =IF(B15="","",COUNTIFS('🤸 Ingresos Pole'!$C$2:$C$1000,B15,'🤸 Ingresos Pole'!$J$2:$J$1000,"Paquete")) -> 2 | I15: =IF(B15="","",COUNTIF('🤸 Ingresos Pole'!$C$2:$C$1000,B15)) -> 2 | J15: =IF(B15="","",SUMIF('🤸 Ingresos Pole'!$C$2:$C$1000,B15,'🤸 Ingresos Pole'!$N$2:$N$1000)) -> 590000 | K15: =IF(OR(B15="",I15=0),"",_xlfn.MINIFS('🤸 Ingresos Pole'!$B$2:$B$1000,'🤸 Ingresos Pole'!$C$2:$C$1000,B15)) -> 46276 | L15: =IF(OR(B15="",I15=0),"",_xlfn.MAXIFS('🤸 Ingresos Pole'!$B$2:$B$1000,'🤸 Ingresos Pole'!$C$2:$C$1000,B15)) -> 46295 | M15: =IF(OR(B15="",I15=0),"",IF(H15=0,"Sin paquete",IF(H15=1,"Nueva","Recurrente"))) -> Recurrente
A16: A-015 | B16: Jose Alberto Rojas Gonzalez | G16: =IF(F16="","",DATEDIF(F16,TODAY(),"Y")) | H16: =IF(B16="","",COUNTIFS('🤸 Ingresos Pole'!$C$2:$C$1000,B16,'🤸 Ingresos Pole'!$J$2:$J$1000,"Paquete")) -> 0 | I16: =IF(B16="","",COUNTIF('🤸 Ingresos Pole'!$C$2:$C$1000,B16)) -> 1 | J16: =IF(B16="","",SUMIF('🤸 Ingresos Pole'!$C$2:$C$1000,B16,'🤸 Ingresos Pole'!$N$2:$N$1000)) -> 44000 | K16: =IF(OR(B16="",I16=0),"",_xlfn.MINIFS('🤸 Ingresos Pole'!$B$2:$B$1000,'🤸 Ingresos Pole'!$C$2:$C$1000,B16)) -> 46280 | L16: =IF(OR(B16="",I16=0),"",_xlfn.MAXIFS('🤸 Ingresos Pole'!$B$2:$B$1000,'🤸 Ingresos Pole'!$C$2:$C$1000,B16)) -> 46280 | M16: =IF(OR(B16="",I16=0),"",IF(H16=0,"Sin paquete",IF(H16=1,"Nueva","Recurrente"))) -> Sin paquete
A17: A-016 | B17: Laura Sofia Hilarion | C17: 3204479014 | G17: =IF(F17="","",DATEDIF(F17,TODAY(),"Y")) | H17: =IF(B17="","",COUNTIFS('🤸 Ingresos Pole'!$C$2:$C$1000,B17,'🤸 Ingresos Pole'!$J$2:$J$1000,"Paquete")) -> 1 | I17: =IF(B17="","",COUNTIF('🤸 Ingresos Pole'!$C$2:$C$1000,B17)) -> 1 | J17: =IF(B17="","",SUMIF('🤸 Ingresos Pole'!$C$2:$C$1000,B17,'🤸 Ingresos Pole'!$N$2:$N$1000)) -> 480000 | K17: =IF(OR(B17="",I17=0),"",_xlfn.MINIFS('🤸 Ingresos Pole'!$B$2:$B$1000,'🤸 Ingresos Pole'!$C$2:$C$1000,B17)) -> 46281 | L17: =IF(OR(B17="",I17=0),"",_xlfn.MAXIFS('🤸 Ingresos Pole'!$B$2:$B$1000,'🤸 Ingresos Pole'!$C$2:$C$1000,B17)) -> 46281 | M17: =IF(OR(B17="",I17=0),"",IF(H17=0,"Sin paquete",IF(H17=1,"Nueva","Recurrente"))) -> Nueva
A18: A-017 | B18: Alejandra Ortega | C18: 3114401669 | G18: =IF(F18="","",DATEDIF(F18,TODAY(),"Y")) | H18: =IF(B18="","",COUNTIFS('🤸 Ingresos Pole'!$C$2:$C$1000,B18,'🤸 Ingresos Pole'!$J$2:$J$1000,"Paquete")) -> 1 | I18: =IF(B18="","",COUNTIF('🤸 Ingresos Pole'!$C$2:$C$1000,B18)) -> 1 | J18: =IF(B18="","",SUMIF('🤸 Ingresos Pole'!$C$2:$C$1000,B18,'🤸 Ingresos Pole'!$N$2:$N$1000)) -> 240000 | K18: =IF(OR(B18="",I18=0),"",_xlfn.MINIFS('🤸 Ingresos Pole'!$B$2:$B$1000,'🤸 Ingresos Pole'!$C$2:$C$1000,B18)) -> 46283 | L18: =IF(OR(B18="",I18=0),"",_xlfn.MAXIFS('🤸 Ingresos Pole'!$B$2:$B$1000,'🤸 Ingresos Pole'!$C$2:$C$1000,B18)) -> 46283 | M18: =IF(OR(B18="",I18=0),"",IF(H18=0,"Sin paquete",IF(H18=1,"Nueva","Recurrente"))) -> Nueva
A19: A-018 | B19: Mary Aurora Osorio Alvarez | C19: 3186650375 | G19: =IF(F19="","",DATEDIF(F19,TODAY(),"Y")) | H19: =IF(B19="","",COUNTIFS('🤸 Ingresos Pole'!$C$2:$C$1000,B19,'🤸 Ingresos Pole'!$J$2:$J$1000,"Paquete")) -> 1 | I19: =IF(B19="","",COUNTIF('🤸 Ingresos Pole'!$C$2:$C$1000,B19)) -> 2 | J19: =IF(B19="","",SUMIF('🤸 Ingresos Pole'!$C$2:$C$1000,B19,'🤸 Ingresos Pole'!$N$2:$N$1000)) -> 290000 | K19: =IF(OR(B19="",I19=0),"",_xlfn.MINIFS('🤸 Ingresos Pole'!$B$2:$B$1000,'🤸 Ingresos Pole'!$C$2:$C$1000,B19)) -> 46283 | L19: =IF(OR(B19="",I19=0),"",_xlfn.MAXIFS('🤸 Ingresos Pole'!$B$2:$B$1000,'🤸 Ingresos Pole'!$C$2:$C$1000,B19)) -> 46295 | M19: =IF(OR(B19="",I19=0),"",IF(H19=0,"Sin paquete",IF(H19=1,"Nueva","Recurrente"))) -> Nueva
A20: A-019 | B20: Elizabeth Lopez salamanca | C20: 3197067161 | G20: =IF(F20="","",DATEDIF(F20,TODAY(),"Y")) | H20: =IF(B20="","",COUNTIFS('🤸 Ingresos Pole'!$C$2:$C$1000,B20,'🤸 Ingresos Pole'!$J$2:$J$1000,"Paquete")) -> 0 | I20: =IF(B20="","",COUNTIF('🤸 Ingresos Pole'!$C$2:$C$1000,B20)) -> 1 | J20: =IF(B20="","",SUMIF('🤸 Ingresos Pole'!$C$2:$C$1000,B20,'🤸 Ingresos Pole'!$N$2:$N$1000)) -> 50000 | K20: =IF(OR(B20="",I20=0),"",_xlfn.MINIFS('🤸 Ingresos Pole'!$B$2:$B$1000,'🤸 Ingresos Pole'!$C$2:$C$1000,B20)) -> 46283 | L20: =IF(OR(B20="",I20=0),"",_xlfn.MAXIFS('🤸 Ingresos Pole'!$B$2:$B$1000,'🤸 Ingresos Pole'!$C$2:$C$1000,B20)) -> 46283 | M20: =IF(OR(B20="",I20=0),"",IF(H20=0,"Sin paquete",IF(H20=1,"Nueva","Recurrente"))) -> Sin paquete
A21: A-020 | B21: Paula Andrea Pinzon | G21: =IF(F21="","",DATEDIF(F21,TODAY(),"Y")) | H21: =IF(B21="","",COUNTIFS('🤸 Ingresos Pole'!$C$2:$C$1000,B21,'🤸 Ingresos Pole'!$J$2:$J$1000,"Paquete")) -> 1 | I21: =IF(B21="","",COUNTIF('🤸 Ingresos Pole'!$C$2:$C$1000,B21)) -> 2 | J21: =IF(B21="","",SUMIF('🤸 Ingresos Pole'!$C$2:$C$1000,B21,'🤸 Ingresos Pole'!$N$2:$N$1000)) -> 200000 | K21: =IF(OR(B21="",I21=0),"",_xlfn.MINIFS('🤸 Ingresos Pole'!$B$2:$B$1000,'🤸 Ingresos Pole'!$C$2:$C$1000,B21)) -> 46287 | L21: =IF(OR(B21="",I21=0),"",_xlfn.MAXIFS('🤸 Ingresos Pole'!$B$2:$B$1000,'🤸 Ingresos Pole'!$C$2:$C$1000,B21)) -> 46291 | M21: =IF(OR(B21="",I21=0),"",IF(H21=0,"Sin paquete",IF(H21=1,"Nueva","Recurrente"))) -> Nueva
A22: A-021 | B22: Marcela Garcia Sanabria | C22: 3123221477 | G22: =IF(F22="","",DATEDIF(F22,TODAY(),"Y")) | H22: =IF(B22="","",COUNTIFS('🤸 Ingresos Pole'!$C$2:$C$1000,B22,'🤸 Ingresos Pole'!$J$2:$J$1000,"Paquete")) -> 1 | I22: =IF(B22="","",COUNTIF('🤸 Ingresos Pole'!$C$2:$C$1000,B22)) -> 1 | J22: =IF(B22="","",SUMIF('🤸 Ingresos Pole'!$C$2:$C$1000,B22,'🤸 Ingresos Pole'!$N$2:$N$1000)) -> 350000 | K22: =IF(OR(B22="",I22=0),"",_xlfn.MINIFS('🤸 Ingresos Pole'!$B$2:$B$1000,'🤸 Ingresos Pole'!$C$2:$C$1000,B22)) -> 46291 | L22: =IF(OR(B22="",I22=0),"",_xlfn.MAXIFS('🤸 Ingresos Pole'!$B$2:$B$1000,'🤸 Ingresos Pole'!$C$2:$C$1000,B22)) -> 46291 | M22: =IF(OR(B22="",I22=0),"",IF(H22=0,"Sin paquete",IF(H22=1,"Nueva","Recurrente"))) -> Nueva
A23: A-022 | B23: Carolina Lopez | G23: =IF(F23="","",DATEDIF(F23,TODAY(),"Y")) | H23: =IF(B23="","",COUNTIFS('🤸 Ingresos Pole'!$C$2:$C$1000,B23,'🤸 Ingresos Pole'!$J$2:$J$1000,"Paquete")) -> 1 | I23: =IF(B23="","",COUNTIF('🤸 Ingresos Pole'!$C$2:$C$1000,B23)) -> 1 | J23: =IF(B23="","",SUMIF('🤸 Ingresos Pole'!$C$2:$C$1000,B23,'🤸 Ingresos Pole'!$N$2:$N$1000)) -> 240000 | K23: =IF(OR(B23="",I23=0),"",_xlfn.MINIFS('🤸 Ingresos Pole'!$B$2:$B$1000,'🤸 Ingresos Pole'!$C$2:$C$1000,B23)) -> 46293 | L23: =IF(OR(B23="",I23=0),"",_xlfn.MAXIFS('🤸 Ingresos Pole'!$B$2:$B$1000,'🤸 Ingresos Pole'!$C$2:$C$1000,B23)) -> 46293 | M23: =IF(OR(B23="",I23=0),"",IF(H23=0,"Sin paquete",IF(H23=1,"Nueva","Recurrente"))) -> Nueva
A24: A-023 | B24: Francya Dámaris Arias | G24: =IF(F24="","",DATEDIF(F24,TODAY(),"Y")) | H24: =IF(B24="","",COUNTIFS('🤸 Ingresos Pole'!$C$2:$C$1000,B24,'🤸 Ingresos Pole'!$J$2:$J$1000,"Paquete")) -> 1 | I24: =IF(B24="","",COUNTIF('🤸 Ingresos Pole'!$C$2:$C$1000,B24)) -> 1 | J24: =IF(B24="","",SUMIF('🤸 Ingresos Pole'!$C$2:$C$1000,B24,'🤸 Ingresos Pole'!$N$2:$N$1000)) -> 480000 | K24: =IF(OR(B24="",I24=0),"",_xlfn.MINIFS('🤸 Ingresos Pole'!$B$2:$B$1000,'🤸 Ingresos Pole'!$C$2:$C$1000,B24)) -> 46294 | L24: =IF(OR(B24="",I24=0),"",_xlfn.MAXIFS('🤸 Ingresos Pole'!$B$2:$B$1000,'🤸 Ingresos Pole'!$C$2:$C$1000,B24)) -> 46294 | M24: =IF(OR(B24="",I24=0),"",IF(H24=0,"Sin paquete",IF(H24=1,"Nueva","Recurrente"))) -> Nueva
A25: A-024 | B25: Karen Arias Ospitia | G25: =IF(F25="","",DATEDIF(F25,TODAY(),"Y")) | H25: =IF(B25="","",COUNTIFS('🤸 Ingresos Pole'!$C$2:$C$1000,B25,'🤸 Ingresos Pole'!$J$2:$J$1000,"Paquete")) -> 1 | I25: =IF(B25="","",COUNTIF('🤸 Ingresos Pole'!$C$2:$C$1000,B25)) -> 1 | J25: =IF(B25="","",SUMIF('🤸 Ingresos Pole'!$C$2:$C$1000,B25,'🤸 Ingresos Pole'!$N$2:$N$1000)) -> 0 | K25: =IF(OR(B25="",I25=0),"",_xlfn.MINIFS('🤸 Ingresos Pole'!$B$2:$B$1000,'🤸 Ingresos Pole'!$C$2:$C$1000,B25)) -> 46294 | L25: =IF(OR(B25="",I25=0),"",_xlfn.MAXIFS('🤸 Ingresos Pole'!$B$2:$B$1000,'🤸 Ingresos Pole'!$C$2:$C$1000,B25)) -> 46294 | M25: =IF(OR(B25="",I25=0),"",IF(H25=0,"Sin paquete",IF(H25=1,"Nueva","Recurrente"))) -> Nueva
A26: A-025 | B26: Yendi Alejandra Dugarte | G26: =IF(F26="","",DATEDIF(F26,TODAY(),"Y")) | H26: =IF(B26="","",COUNTIFS('🤸 Ingresos Pole'!$C$2:$C$1000,B26,'🤸 Ingresos Pole'!$J$2:$J$1000,"Paquete")) -> 1 | I26: =IF(B26="","",COUNTIF('🤸 Ingresos Pole'!$C$2:$C$1000,B26)) -> 1 | J26: =IF(B26="","",SUMIF('🤸 Ingresos Pole'!$C$2:$C$1000,B26,'🤸 Ingresos Pole'!$N$2:$N$1000)) -> 240000 | K26: =IF(OR(B26="",I26=0),"",_xlfn.MINIFS('🤸 Ingresos Pole'!$B$2:$B$1000,'🤸 Ingresos Pole'!$C$2:$C$1000,B26)) -> 46294 | L26: =IF(OR(B26="",I26=0),"",_xlfn.MAXIFS('🤸 Ingresos Pole'!$B$2:$B$1000,'🤸 Ingresos Pole'!$C$2:$C$1000,B26)) -> 46294 | M26: =IF(OR(B26="",I26=0),"",IF(H26=0,"Sin paquete",IF(H26=1,"Nueva","Recurrente"))) -> Nueva
A27: A-026 | B27: Martha Yasmin Aragón | G27: =IF(F27="","",DATEDIF(F27,TODAY(),"Y")) | H27: =IF(B27="","",COUNTIFS('🤸 Ingresos Pole'!$C$2:$C$1000,B27,'🤸 Ingresos Pole'!$J$2:$J$1000,"Paquete")) -> 1 | I27: =IF(B27="","",COUNTIF('🤸 Ingresos Pole'!$C$2:$C$1000,B27)) -> 2 | J27: =IF(B27="","",SUMIF('🤸 Ingresos Pole'!$C$2:$C$1000,B27,'🤸 Ingresos Pole'!$N$2:$N$1000)) -> 290000 | K27: =IF(OR(B27="",I27=0),"",_xlfn.MINIFS('🤸 Ingresos Pole'!$B$2:$B$1000,'🤸 Ingresos Pole'!$C$2:$C$1000,B27)) -> 46294 | L27: =IF(OR(B27="",I27=0),"",_xlfn.MAXIFS('🤸 Ingresos Pole'!$B$2:$B$1000,'🤸 Ingresos Pole'!$C$2:$C$1000,B27)) -> 46295 | M27: =IF(OR(B27="",I27=0),"",IF(H27=0,"Sin paquete",IF(H27=1,"Nueva","Recurrente"))) -> Nueva
A28: A-027 | B28: Melanie Jankey Ávila | G28: =IF(F28="","",DATEDIF(F28,TODAY(),"Y")) | H28: =IF(B28="","",COUNTIFS('🤸 Ingresos Pole'!$C$2:$C$1000,B28,'🤸 Ingresos Pole'!$J$2:$J$1000,"Paquete")) -> 1 | I28: =IF(B28="","",COUNTIF('🤸 Ingresos Pole'!$C$2:$C$1000,B28)) -> 1 | J28: =IF(B28="","",SUMIF('🤸 Ingresos Pole'!$C$2:$C$1000,B28,'🤸 Ingresos Pole'!$N$2:$N$1000)) -> 240000 | K28: =IF(OR(B28="",I28=0),"",_xlfn.MINIFS('🤸 Ingresos Pole'!$B$2:$B$1000,'🤸 Ingresos Pole'!$C$2:$C$1000,B28)) -> 46295 | L28: =IF(OR(B28="",I28=0),"",_xlfn.MAXIFS('🤸 Ingresos Pole'!$B$2:$B$1000,'🤸 Ingresos Pole'!$C$2:$C$1000,B28)) -> 46295 | M28: =IF(OR(B28="",I28=0),"",IF(H28=0,"Sin paquete",IF(H28=1,"Nueva","Recurrente"))) -> Nueva
A29: A-028 | G29: =IF(F29="","",DATEDIF(F29,TODAY(),"Y")) | H29: =IF(B29="","",COUNTIFS('🤸 Ingresos Pole'!$C$2:$C$1000,B29,'🤸 Ingresos Pole'!$J$2:$J$1000,"Paquete")) | I29: =IF(B29="","",COUNTIF('🤸 Ingresos Pole'!$C$2:$C$1000,B29)) | J29: =IF(B29="","",SUMIF('🤸 Ingresos Pole'!$C$2:$C$1000,B29,'🤸 Ingresos Pole'!$N$2:$N$1000)) | K29: =IF(OR(B29="",I29=0),"",_xlfn.MINIFS('🤸 Ingresos Pole'!$B$2:$B$1000,'🤸 Ingresos Pole'!$C$2:$C$1000,B29)) | L29: =IF(OR(B29="",I29=0),"",_xlfn.MAXIFS('🤸 Ingresos Pole'!$B$2:$B$1000,'🤸 Ingresos Pole'!$C$2:$C$1000,B29)) | M29: =IF(OR(B29="",I29=0),"",IF(H29=0,"Sin paquete",IF(H29=1,"Nueva","Recurrente")))
A30: A-029 | G30: =IF(F30="","",DATEDIF(F30,TODAY(),"Y")) | H30: =IF(B30="","",COUNTIFS('🤸 Ingresos Pole'!$C$2:$C$1000,B30,'🤸 Ingresos Pole'!$J$2:$J$1000,"Paquete")) | I30: =IF(B30="","",COUNTIF('🤸 Ingresos Pole'!$C$2:$C$1000,B30)) | J30: =IF(B30="","",SUMIF('🤸 Ingresos Pole'!$C$2:$C$1000,B30,'🤸 Ingresos Pole'!$N$2:$N$1000)) | K30: =IF(OR(B30="",I30=0),"",_xlfn.MINIFS('🤸 Ingresos Pole'!$B$2:$B$1000,'🤸 Ingresos Pole'!$C$2:$C$1000,B30)) | L30: =IF(OR(B30="",I30=0),"",_xlfn.MAXIFS('🤸 Ingresos Pole'!$B$2:$B$1000,'🤸 Ingresos Pole'!$C$2:$C$1000,B30)) | M30: =IF(OR(B30="",I30=0),"",IF(H30=0,"Sin paquete",IF(H30=1,"Nueva","Recurrente")))
A31: A-030 | G31: =IF(F31="","",DATEDIF(F31,TODAY(),"Y")) | H31: =IF(B31="","",COUNTIFS('🤸 Ingresos Pole'!$C$2:$C$1000,B31,'🤸 Ingresos Pole'!$J$2:$J$1000,"Paquete")) | I31: =IF(B31="","",COUNTIF('🤸 Ingresos Pole'!$C$2:$C$1000,B31)) | J31: =IF(B31="","",SUMIF('🤸 Ingresos Pole'!$C$2:$C$1000,B31,'🤸 Ingresos Pole'!$N$2:$N$1000)) | K31: =IF(OR(B31="",I31=0),"",_xlfn.MINIFS('🤸 Ingresos Pole'!$B$2:$B$1000,'🤸 Ingresos Pole'!$C$2:$C$1000,B31)) | L31: =IF(OR(B31="",I31=0),"",_xlfn.MAXIFS('🤸 Ingresos Pole'!$B$2:$B$1000,'🤸 Ingresos Pole'!$C$2:$C$1000,B31)) | M31: =IF(OR(B31="",I31=0),"",IF(H31=0,"Sin paquete",IF(H31=1,"Nueva","Recurrente")))
A32: A-031 | G32: =IF(F32="","",DATEDIF(F32,TODAY(),"Y")) | H32: =IF(B32="","",COUNTIFS('🤸 Ingresos Pole'!$C$2:$C$1000,B32,'🤸 Ingresos Pole'!$J$2:$J$1000,"Paquete")) | I32: =IF(B32="","",COUNTIF('🤸 Ingresos Pole'!$C$2:$C$1000,B32)) | J32: =IF(B32="","",SUMIF('🤸 Ingresos Pole'!$C$2:$C$1000,B32,'🤸 Ingresos Pole'!$N$2:$N$1000)) | K32: =IF(OR(B32="",I32=0),"",_xlfn.MINIFS('🤸 Ingresos Pole'!$B$2:$B$1000,'🤸 Ingresos Pole'!$C$2:$C$1000,B32)) | L32: =IF(OR(B32="",I32=0),"",_xlfn.MAXIFS('🤸 Ingresos Pole'!$B$2:$B$1000,'🤸 Ingresos Pole'!$C$2:$C$1000,B32)) | M32: =IF(OR(B32="",I32=0),"",IF(H32=0,"Sin paquete",IF(H32=1,"Nueva","Recurrente")))
A33: A-032 | G33: =IF(F33="","",DATEDIF(F33,TODAY(),"Y")) | H33: =IF(B33="","",COUNTIFS('🤸 Ingresos Pole'!$C$2:$C$1000,B33,'🤸 Ingresos Pole'!$J$2:$J$1000,"Paquete")) | I33: =IF(B33="","",COUNTIF('🤸 Ingresos Pole'!$C$2:$C$1000,B33)) | J33: =IF(B33="","",SUMIF('🤸 Ingresos Pole'!$C$2:$C$1000,B33,'🤸 Ingresos Pole'!$N$2:$N$1000)) | K33: =IF(OR(B33="",I33=0),"",_xlfn.MINIFS('🤸 Ingresos Pole'!$B$2:$B$1000,'🤸 Ingresos Pole'!$C$2:$C$1000,B33)) | L33: =IF(OR(B33="",I33=0),"",_xlfn.MAXIFS('🤸 Ingresos Pole'!$B$2:$B$1000,'🤸 Ingresos Pole'!$C$2:$C$1000,B33)) | M33: =IF(OR(B33="",I33=0),"",IF(H33=0,"Sin paquete",IF(H33=1,"Nueva","Recurrente")))
A34: A-033 | G34: =IF(F34="","",DATEDIF(F34,TODAY(),"Y")) | H34: =IF(B34="","",COUNTIFS('🤸 Ingresos Pole'!$C$2:$C$1000,B34,'🤸 Ingresos Pole'!$J$2:$J$1000,"Paquete")) | I34: =IF(B34="","",COUNTIF('🤸 Ingresos Pole'!$C$2:$C$1000,B34)) | J34: =IF(B34="","",SUMIF('🤸 Ingresos Pole'!$C$2:$C$1000,B34,'🤸 Ingresos Pole'!$N$2:$N$1000)) | K34: =IF(OR(B34="",I34=0),"",_xlfn.MINIFS('🤸 Ingresos Pole'!$B$2:$B$1000,'🤸 Ingresos Pole'!$C$2:$C$1000,B34)) | L34: =IF(OR(B34="",I34=0),"",_xlfn.MAXIFS('🤸 Ingresos Pole'!$B$2:$B$1000,'🤸 Ingresos Pole'!$C$2:$C$1000,B34)) | M34: =IF(OR(B34="",I34=0),"",IF(H34=0,"Sin paquete",IF(H34=1,"Nueva","Recurrente")))
A35: A-034 | G35: =IF(F35="","",DATEDIF(F35,TODAY(),"Y")) | H35: =IF(B35="","",COUNTIFS('🤸 Ingresos Pole'!$C$2:$C$1000,B35,'🤸 Ingresos Pole'!$J$2:$J$1000,"Paquete")) | I35: =IF(B35="","",COUNTIF('🤸 Ingresos Pole'!$C$2:$C$1000,B35)) | J35: =IF(B35="","",SUMIF('🤸 Ingresos Pole'!$C$2:$C$1000,B35,'🤸 Ingresos Pole'!$N$2:$N$1000)) | K35: =IF(OR(B35="",I35=0),"",_xlfn.MINIFS('🤸 Ingresos Pole'!$B$2:$B$1000,'🤸 Ingresos Pole'!$C$2:$C$1000,B35)) | L35: =IF(OR(B35="",I35=0),"",_xlfn.MAXIFS('🤸 Ingresos Pole'!$B$2:$B$1000,'🤸 Ingresos Pole'!$C$2:$C$1000,B35)) | M35: =IF(OR(B35="",I35=0),"",IF(H35=0,"Sin paquete",IF(H35=1,"Nueva","Recurrente")))
A36: A-035 | G36: =IF(F36="","",DATEDIF(F36,TODAY(),"Y")) | H36: =IF(B36="","",COUNTIFS('🤸 Ingresos Pole'!$C$2:$C$1000,B36,'🤸 Ingresos Pole'!$J$2:$J$1000,"Paquete")) | I36: =IF(B36="","",COUNTIF('🤸 Ingresos Pole'!$C$2:$C$1000,B36)) | J36: =IF(B36="","",SUMIF('🤸 Ingresos Pole'!$C$2:$C$1000,B36,'🤸 Ingresos Pole'!$N$2:$N$1000)) | K36: =IF(OR(B36="",I36=0),"",_xlfn.MINIFS('🤸 Ingresos Pole'!$B$2:$B$1000,'🤸 Ingresos Pole'!$C$2:$C$1000,B36)) | L36: =IF(OR(B36="",I36=0),"",_xlfn.MAXIFS('🤸 Ingresos Pole'!$B$2:$B$1000,'🤸 Ingresos Pole'!$C$2:$C$1000,B36)) | M36: =IF(OR(B36="",I36=0),"",IF(H36=0,"Sin paquete",IF(H36=1,"Nueva","Recurrente")))
A37: A-036 | G37: =IF(F37="","",DATEDIF(F37,TODAY(),"Y")) | H37: =IF(B37="","",COUNTIFS('🤸 Ingresos Pole'!$C$2:$C$1000,B37,'🤸 Ingresos Pole'!$J$2:$J$1000,"Paquete")) | I37: =IF(B37="","",COUNTIF('🤸 Ingresos Pole'!$C$2:$C$1000,B37)) | J37: =IF(B37="","",SUMIF('🤸 Ingresos Pole'!$C$2:$C$1000,B37,'🤸 Ingresos Pole'!$N$2:$N$1000)) | K37: =IF(OR(B37="",I37=0),"",_xlfn.MINIFS('🤸 Ingresos Pole'!$B$2:$B$1000,'🤸 Ingresos Pole'!$C$2:$C$1000,B37)) | L37: =IF(OR(B37="",I37=0),"",_xlfn.MAXIFS('🤸 Ingresos Pole'!$B$2:$B$1000,'🤸 Ingresos Pole'!$C$2:$C$1000,B37)) | M37: =IF(OR(B37="",I37=0),"",IF(H37=0,"Sin paquete",IF(H37=1,"Nueva","Recurrente")))
A38: A-037 | G38: =IF(F38="","",DATEDIF(F38,TODAY(),"Y")) | H38: =IF(B38="","",COUNTIFS('🤸 Ingresos Pole'!$C$2:$C$1000,B38,'🤸 Ingresos Pole'!$J$2:$J$1000,"Paquete")) | I38: =IF(B38="","",COUNTIF('🤸 Ingresos Pole'!$C$2:$C$1000,B38)) | J38: =IF(B38="","",SUMIF('🤸 Ingresos Pole'!$C$2:$C$1000,B38,'🤸 Ingresos Pole'!$N$2:$N$1000)) | K38: =IF(OR(B38="",I38=0),"",_xlfn.MINIFS('🤸 Ingresos Pole'!$B$2:$B$1000,'🤸 Ingresos Pole'!$C$2:$C$1000,B38)) | L38: =IF(OR(B38="",I38=0),"",_xlfn.MAXIFS('🤸 Ingresos Pole'!$B$2:$B$1000,'🤸 Ingresos Pole'!$C$2:$C$1000,B38)) | M38: =IF(OR(B38="",I38=0),"",IF(H38=0,"Sin paquete",IF(H38=1,"Nueva","Recurrente")))
A39: A-038 | G39: =IF(F39="","",DATEDIF(F39,TODAY(),"Y")) | H39: =IF(B39="","",COUNTIFS('🤸 Ingresos Pole'!$C$2:$C$1000,B39,'🤸 Ingresos Pole'!$J$2:$J$1000,"Paquete")) | I39: =IF(B39="","",COUNTIF('🤸 Ingresos Pole'!$C$2:$C$1000,B39)) | J39: =IF(B39="","",SUMIF('🤸 Ingresos Pole'!$C$2:$C$1000,B39,'🤸 Ingresos Pole'!$N$2:$N$1000)) | K39: =IF(OR(B39="",I39=0),"",_xlfn.MINIFS('🤸 Ingresos Pole'!$B$2:$B$1000,'🤸 Ingresos Pole'!$C$2:$C$1000,B39)) | L39: =IF(OR(B39="",I39=0),"",_xlfn.MAXIFS('🤸 Ingresos Pole'!$B$2:$B$1000,'🤸 Ingresos Pole'!$C$2:$C$1000,B39)) | M39: =IF(OR(B39="",I39=0),"",IF(H39=0,"Sin paquete",IF(H39=1,"Nueva","Recurrente")))
A40: A-039 | G40: =IF(F40="","",DATEDIF(F40,TODAY(),"Y")) | H40: =IF(B40="","",COUNTIFS('🤸 Ingresos Pole'!$C$2:$C$1000,B40,'🤸 Ingresos Pole'!$J$2:$J$1000,"Paquete")) | I40: =IF(B40="","",COUNTIF('🤸 Ingresos Pole'!$C$2:$C$1000,B40)) | J40: =IF(B40="","",SUMIF('🤸 Ingresos Pole'!$C$2:$C$1000,B40,'🤸 Ingresos Pole'!$N$2:$N$1000)) | K40: =IF(OR(B40="",I40=0),"",_xlfn.MINIFS('🤸 Ingresos Pole'!$B$2:$B$1000,'🤸 Ingresos Pole'!$C$2:$C$1000,B40)) | L40: =IF(OR(B40="",I40=0),"",_xlfn.MAXIFS('🤸 Ingresos Pole'!$B$2:$B$1000,'🤸 Ingresos Pole'!$C$2:$C$1000,B40)) | M40: =IF(OR(B40="",I40=0),"",IF(H40=0,"Sin paquete",IF(H40=1,"Nueva","Recurrente")))
... A300: A-299 | G300: =IF(F300="","",DATEDIF(F300,TODAY(),"Y")) | H300: =IF(B300="","",COUNTIFS('🤸 Ingresos Pole'!$C$2:$C$1000,B300,'🤸 Ingresos Pole'!$J$2:$J$1000,"Paquete")) | I300: =IF(B300="","",COUNTIF('🤸 Ingresos Pole'!$C$2:$C$1000,B300)) | J300: =IF(B300="","",SUMIF('🤸 Ingresos Pole'!$C$2:$C$1000,B300,'🤸 Ingresos Pole'!$N$2:$N$1000)) | K300: =IF(OR(B300="",I300=0),"",_xlfn.MINIFS('🤸 Ingresos Pole'!$B$2:$B$1000,'🤸 Ingresos Pole'!$C$2:$C$1000,B300)) | L300: =IF(OR(B300="",I300=0),"",_xlfn.MAXIFS('🤸 Ingresos Pole'!$B$2:$B$1000,'🤸 Ingresos Pole'!$C$2:$C$1000,B300)) | M300: =IF(OR(B300="",I300=0),"",IF(H300=0,"Sin paquete",IF(H300=1,"Nueva","Recurrente")))

Sheet 🤸 Ingresos Pole
A1: ID Ingreso | B1: Fecha | C1: Alumna | D1: Cel | E1: Correo | F1: Dirección | G1: Fecha de nacimiento | H1: Edad | I1: Concepto | J1: Tipo | K1: Descripción | L1: Cantidad | M1: Valor Unitario ($) | N1: Total ($) | O1: Porcentaje que paga | P1: Método de Pago | Q1: Registrado Por | R1: ¿Alumna nueva? | S1: N° de inscripción | T1: Notas
A2: I-001 | B2: 46264 | C2: Ana Carolina Lopez Galvan | D2: =IF($C2="","",IFERROR(IF(INDEX('🎓 Alumnas'!$C$2:$C$1000,MATCH($C2,'🎓 Alumnas'!$B$2:$B$1000,0))="","",INDEX('🎓 Alumnas'!$C$2:$C$1000,MATCH($C2,'🎓 Alumnas'!$B$2:$B$1000,0))),"")) -> 3229015452 | E2: =IF($C2="","",IFERROR(IF(INDEX('🎓 Alumnas'!$D$2:$D$1000,MATCH($C2,'🎓 Alumnas'!$B$2:$B$1000,0))="","",INDEX('🎓 Alumnas'!$D$2:$D$1000,MATCH($C2,'🎓 Alumnas'!$B$2:$B$1000,0))),"")) -> anacaloga88@gmail.com | F2: =IF($C2="","",IFERROR(IF(INDEX('🎓 Alumnas'!$E$2:$E$1000,MATCH($C2,'🎓 Alumnas'!$B$2:$B$1000,0))="","",INDEX('🎓 Alumnas'!$E$2:$E$1000,MATCH($C2,'🎓 Alumnas'!$B$2:$B$1000,0))),"")) -> carrera 79a#16f | G2: =IF($C2="","",IFERROR(IF(INDEX('🎓 Alumnas'!$F$2:$F$1000,MATCH($C2,'🎓 Alumnas'!$B$2:$B$1000,0))="","",INDEX('🎓 Alumnas'!$F$2:$F$1000,MATCH($C2,'🎓 Alumnas'!$B$2:$B$1000,0))),"")) -> 32232 | H2: =IF(G2="","",DATEDIF(G2,TODAY(),"Y")) -> 38 | I2: 4 clases: Sport Fitness Challenge $200.000 | J2: =IF(I2="","",IF(LEFT(I2,6)="1 Pole","Alquiler",IF(LEFT(I2,7)="1 Clase","Clase suelta","Paquete"))) -> Paquete | L2: 1 | M2: 200000 | N2: =IF(M2="","",L2*M2) -> 200000 | O2: 1 | P2: Transferencia Bancaria | Q2: Carolina | R2: =IF(C2="","",IF(COUNTIF($C$2:C2,C2)=1,"Nueva","Recurrente")) -> Nueva | S2: =IF(OR(C2="",J2<>"Paquete"),"",COUNTIFS($C$2:C2,C2,$J$2:J2,"Paquete")) -> 1
A3: I-002 | B3: 46265 | C3: Francya Damaris Arias Ospitia | D3: =IF($C3="","",IFERROR(IF(INDEX('🎓 Alumnas'!$C$2:$C$1000,MATCH($C3,'🎓 Alumnas'!$B$2:$B$1000,0))="","",INDEX('🎓 Alumnas'!$C$2:$C$1000,MATCH($C3,'🎓 Alumnas'!$B$2:$B$1000,0))),"")) -> 3142183412 | E3: =IF($C3="","",IFERROR(IF(INDEX('🎓 Alumnas'!$D$2:$D$1000,MATCH($C3,'🎓 Alumnas'!$B$2:$B$1000,0))="","",INDEX('🎓 Alumnas'!$D$2:$D$1000,MATCH($C3,'🎓 Alumnas'!$B$2:$B$1000,0))),"")) -> fraariaspi@hotmail.com | F3: =IF($C3="","",IFERROR(IF(INDEX('🎓 Alumnas'!$E$2:$E$1000,MATCH($C3,'🎓 Alumnas'!$B$2:$B$1000,0))="","",INDEX('🎓 Alumnas'!$E$2:$E$1000,MATCH($C3,'🎓 Alumnas'!$B$2:$B$1000,0))),"")) -> Cra 73# 7f-07 | G3: =IF($C3="","",IFERROR(IF(INDEX('🎓 Alumnas'!$F$2:$F$1000,MATCH($C3,'🎓 Alumnas'!$B$2:$B$1000,0))="","",INDEX('🎓 Alumnas'!$F$2:$F$1000,MATCH($C3,'🎓 Alumnas'!$B$2:$B$1000,0))),"")) -> 27887 | H3: =IF(G3="","",DATEDIF(G3,TODAY(),"Y")) -> 50 | I3: 9 clases: Sport Power Team $350.000 | J3: =IF(I3="","",IF(LEFT(I3,6)="1 Pole","Alquiler",IF(LEFT(I3,7)="1 Clase","Clase suelta","Paquete"))) -> Paquete | L3: 1 | M3: 350000 | N3: =IF(M3="","",L3*M3) -> 350000 | O3: 1 | P3: Efectivo | Q3: Jose | R3: =IF(C3="","",IF(COUNTIF($C$2:C3,C3)=1,"Nueva","Recurrente")) -> Nueva | S3: =IF(OR(C3="",J3<>"Paquete"),"",COUNTIFS($C$2:C3,C3,$J$2:J3,"Paquete")) -> 1
A4: I-003 | B4: 46264 | C4: Diana Bermudez Cardona | D4: =IF($C4="","",IFERROR(IF(INDEX('🎓 Alumnas'!$C$2:$C$1000,MATCH($C4,'🎓 Alumnas'!$B$2:$B$1000,0))="","",INDEX('🎓 Alumnas'!$C$2:$C$1000,MATCH($C4,'🎓 Alumnas'!$B$2:$B$1000,0))),"")) -> 3196364084 | E4: =IF($C4="","",IFERROR(IF(INDEX('🎓 Alumnas'!$D$2:$D$1000,MATCH($C4,'🎓 Alumnas'!$B$2:$B$1000,0))="","",INDEX('🎓 Alumnas'!$D$2:$D$1000,MATCH($C4,'🎓 Alumnas'!$B$2:$B$1000,0))),"")) -> diana0.bermudez@gmail.com | F4: =IF($C4="","",IFERROR(IF(INDEX('🎓 Alumnas'!$E$2:$E$1000,MATCH($C4,'🎓 Alumnas'!$B$2:$B$1000,0))="","",INDEX('🎓 Alumnas'!$E$2:$E$1000,MATCH($C4,'🎓 Alumnas'!$B$2:$B$1000,0))),"")) -> Cra 72k # 39a 96 sur | G4: =IF($C4="","",IFERROR(IF(INDEX('🎓 Alumnas'!$F$2:$F$1000,MATCH($C4,'🎓 Alumnas'!$B$2:$B$1000,0))="","",INDEX('🎓 Alumnas'!$F$2:$F$1000,MATCH($C4,'🎓 Alumnas'!$B$2:$B$1000,0))),"")) -> 33374 | H4: =IF(G4="","",DATEDIF(G4,TODAY(),"Y")) -> 35 | I4: 16 clases : Sport Elite club $480.000 | J4: =IF(I4="","",IF(LEFT(I4,6)="1 Pole","Alquiler",IF(LEFT(I4,7)="1 Clase","Clase suelta","Paquete"))) -> Paquete | K4: Promo 2x1 | L4: 1 | M4: 480000 | N4: =IF(M4="","",L4*M4) -> 480000 | O4: 1 | P4: Transferencia Bancaria | Q4: Carolina | R4: =IF(C4="","",IF(COUNTIF($C$2:C4,C4)=1,"Nueva","Recurrente")) -> Nueva | S4: =IF(OR(C4="",J4<>"Paquete"),"",COUNTIFS($C$2:C4,C4,$J$2:J4,"Paquete")) -> 1
A5: I-004 | B5: 46264 | C5: Jessica Torres Olarte | D5: =IF($C5="","",IFERROR(IF(INDEX('🎓 Alumnas'!$C$2:$C$1000,MATCH($C5,'🎓 Alumnas'!$B$2:$B$1000,0))="","",INDEX('🎓 Alumnas'!$C$2:$C$1000,MATCH($C5,'🎓 Alumnas'!$B$2:$B$1000,0))),"")) -> 3104775381 | E5: =IF($C5="","",IFERROR(IF(INDEX('🎓 Alumnas'!$D$2:$D$1000,MATCH($C5,'🎓 Alumnas'!$B$2:$B$1000,0))="","",INDEX('🎓 Alumnas'!$D$2:$D$1000,MATCH($C5,'🎓 Alumnas'!$B$2:$B$1000,0))),"")) -> Jessicatorresolarte@gmail.com | F5: =IF($C5="","",IFERROR(IF(INDEX('🎓 Alumnas'!$E$2:$E$1000,MATCH($C5,'🎓 Alumnas'!$B$2:$B$1000,0))="","",INDEX('🎓 Alumnas'!$E$2:$E$1000,MATCH($C5,'🎓 Alumnas'!$B$2:$B$1000,0))),"")) -> Calle 6b 80b 85 | G5: =IF($C5="","",IFERROR(IF(INDEX('🎓 Alumnas'!$F$2:$F$1000,MATCH($C5,'🎓 Alumnas'!$B$2:$B$1000,0))="","",INDEX('🎓 Alumnas'!$F$2:$F$1000,MATCH($C5,'🎓 Alumnas'!$B$2:$B$1000,0))),"")) -> 31592 | H5: =IF(G5="","",DATEDIF(G5,TODAY(),"Y")) -> 40 | I5: 16 clases : Sport Elite club $480.000 | J5: =IF(I5="","",IF(LEFT(I5,6)="1 Pole","Alquiler",IF(LEFT(I5,7)="1 Clase","Clase suelta","Paquete"))) -> Paquete | K5: Promo 2x1 | L5: 1 | M5: 0 | N5: =IF(M5="","",L5*M5) -> 0 | O5: 0 | R5: =IF(C5="","",IF(COUNTIF($C$2:C5,C5)=1,"Nueva","Recurrente")) -> Nueva | S5: =IF(OR(C5="",J5<>"Paquete"),"",COUNTIFS($C$2:C5,C5,$J$2:J5,"Paquete")) -> 1
A6: I-005 | B6: 46265 | C6: Laura Camila Ramirez Galvis | D6: =IF($C6="","",IFERROR(IF(INDEX('🎓 Alumnas'!$C$2:$C$1000,MATCH($C6,'🎓 Alumnas'!$B$2:$B$1000,0))="","",INDEX('🎓 Alumnas'!$C$2:$C$1000,MATCH($C6,'🎓 Alumnas'!$B$2:$B$1000,0))),"")) | E6: =IF($C6="","",IFERROR(IF(INDEX('🎓 Alumnas'!$D$2:$D$1000,MATCH($C6,'🎓 Alumnas'!$B$2:$B$1000,0))="","",INDEX('🎓 Alumnas'!$D$2:$D$1000,MATCH($C6,'🎓 Alumnas'!$B$2:$B$1000,0))),"")) | F6: =IF($C6="","",IFERROR(IF(INDEX('🎓 Alumnas'!$E$2:$E$1000,MATCH($C6,'🎓 Alumnas'!$B$2:$B$1000,0))="","",INDEX('🎓 Alumnas'!$E$2:$E$1000,MATCH($C6,'🎓 Alumnas'!$B$2:$B$1000,0))),"")) | G6: =IF($C6="","",IFERROR(IF(INDEX('🎓 Alumnas'!$F$2:$F$1000,MATCH($C6,'🎓 Alumnas'!$B$2:$B$1000,0))="","",INDEX('🎓 Alumnas'!$F$2:$F$1000,MATCH($C6,'🎓 Alumnas'!$B$2:$B$1000,0))),"")) | H6: =IF(G6="","",DATEDIF(G6,TODAY(),"Y")) | I6: 16 clases : Sport Elite club $480.000 | J6: =IF(I6="","",IF(LEFT(I6,6)="1 Pole","Alquiler",IF(LEFT(I6,7)="1 Clase","Clase suelta","Paquete"))) -> Paquete | K6: Promo 2x1 | L6: 1 | M6: 480000 | N6: =IF(M6="","",L6*M6) -> 480000 | O6: 1 | P6: Transferencia Bancaria | R6: =IF(C6="","",IF(COUNTIF($C$2:C6,C6)=1,"Nueva","Recurrente")) -> Nueva | S6: =IF(OR(C6="",J6<>"Paquete"),"",COUNTIFS($C$2:C6,C6,$J$2:J6,"Paquete")) -> 1
A7: I-006 | B7: 46267 | C7: Juliana Bossa | D7: =IF($C7="","",IFERROR(IF(INDEX('🎓 Alumnas'!$C$2:$C$1000,MATCH($C7,'🎓 Alumnas'!$B$2:$B$1000,0))="","",INDEX('🎓 Alumnas'!$C$2:$C$1000,MATCH($C7,'🎓 Alumnas'!$B$2:$B$1000,0))),"")) -> 3185937737 | E7: =IF($C7="","",IFERROR(IF(INDEX('🎓 Alumnas'!$D$2:$D$1000,MATCH($C7,'🎓 Alumnas'!$B$2:$B$1000,0))="","",INDEX('🎓 Alumnas'!$D$2:$D$1000,MATCH($C7,'🎓 Alumnas'!$B$2:$B$1000,0))),"")) | F7: =IF($C7="","",IFERROR(IF(INDEX('🎓 Alumnas'!$E$2:$E$1000,MATCH($C7,'🎓 Alumnas'!$B$2:$B$1000,0))="","",INDEX('🎓 Alumnas'!$E$2:$E$1000,MATCH($C7,'🎓 Alumnas'!$B$2:$B$1000,0))),"")) | G7: =IF($C7="","",IFERROR(IF(INDEX('🎓 Alumnas'!$F$2:$F$1000,MATCH($C7,'🎓 Alumnas'!$B$2:$B$1000,0))="","",INDEX('🎓 Alumnas'!$F$2:$F$1000,MATCH($C7,'🎓 Alumnas'!$B$2:$B$1000,0))),"")) | H7: =IF(G7="","",DATEDIF(G7,TODAY(),"Y")) | I7: 1 Pole: Alquiler $22000 | J7: =IF(I7="","",IF(LEFT(I7,6)="1 Pole","Alquiler",IF(LEFT(I7,7)="1 Clase","Clase suelta","Paquete"))) -> Alquiler | L7: 1 | M7: 22000 | N7: =IF(M7="","",L7*M7) -> 22000 | O7: 1 | P7: Nequi | R7: =IF(C7="","",IF(COUNTIF($C$2:C7,C7)=1,"Nueva","Recurrente")) -> Nueva | S7: =IF(OR(C7="",J7<>"Paquete"),"",COUNTIFS($C$2:C7,C7,$J$2:J7,"Paquete"))
A8: I-007 | B8: 46267 | C8: Laura Vanesa Guerra | D8: =IF($C8="","",IFERROR(IF(INDEX('🎓 Alumnas'!$C$2:$C$1000,MATCH($C8,'🎓 Alumnas'!$B$2:$B$1000,0))="","",INDEX('🎓 Alumnas'!$C$2:$C$1000,MATCH($C8,'🎓 Alumnas'!$B$2:$B$1000,0))),"")) | E8: =IF($C8="","",IFERROR(IF(INDEX('🎓 Alumnas'!$D$2:$D$1000,MATCH($C8,'🎓 Alumnas'!$B$2:$B$1000,0))="","",INDEX('🎓 Alumnas'!$D$2:$D$1000,MATCH($C8,'🎓 Alumnas'!$B$2:$B$1000,0))),"")) | F8: =IF($C8="","",IFERROR(IF(INDEX('🎓 Alumnas'!$E$2:$E$1000,MATCH($C8,'🎓 Alumnas'!$B$2:$B$1000,0))="","",INDEX('🎓 Alumnas'!$E$2:$E$1000,MATCH($C8,'🎓 Alumnas'!$B$2:$B$1000,0))),"")) | G8: =IF($C8="","",IFERROR(IF(INDEX('🎓 Alumnas'!$F$2:$F$1000,MATCH($C8,'🎓 Alumnas'!$B$2:$B$1000,0))="","",INDEX('🎓 Alumnas'!$F$2:$F$1000,MATCH($C8,'🎓 Alumnas'!$B$2:$B$1000,0))),"")) | H8: =IF(G8="","",DATEDIF(G8,TODAY(),"Y")) | I8: 16 clases : Sport Elite club $480.000 | J8: =IF(I8="","",IF(LEFT(I8,6)="1 Pole","Alquiler",IF(LEFT(I8,7)="1 Clase","Clase suelta","Paquete"))) -> Paquete | K8: Promo 2x1 | L8: 1 | M8: 240000 | N8: =IF(M8="","",L8*M8) -> 240000 | O8: 0.5 | P8: Transferencia Bancaria | R8: =IF(C8="","",IF(COUNTIF($C$2:C8,C8)=1,"Nueva","Recurrente")) -> Nueva | S8: =IF(OR(C8="",J8<>"Paquete"),"",COUNTIFS($C$2:C8,C8,$J$2:J8,"Paquete")) -> 1
A9: I-008 | B9: 46267 | C9: Shirley Dayana Chavarro | D9: =IF($C9="","",IFERROR(IF(INDEX('🎓 Alumnas'!$C$2:$C$1000,MATCH($C9,'🎓 Alumnas'!$B$2:$B$1000,0))="","",INDEX('🎓 Alumnas'!$C$2:$C$1000,MATCH($C9,'🎓 Alumnas'!$B$2:$B$1000,0))),"")) -> 3115269836 | E9: =IF($C9="","",IFERROR(IF(INDEX('🎓 Alumnas'!$D$2:$D$1000,MATCH($C9,'🎓 Alumnas'!$B$2:$B$1000,0))="","",INDEX('🎓 Alumnas'!$D$2:$D$1000,MATCH($C9,'🎓 Alumnas'!$B$2:$B$1000,0))),"")) | F9: =IF($C9="","",IFERROR(IF(INDEX('🎓 Alumnas'!$E$2:$E$1000,MATCH($C9,'🎓 Alumnas'!$B$2:$B$1000,0))="","",INDEX('🎓 Alumnas'!$E$2:$E$1000,MATCH($C9,'🎓 Alumnas'!$B$2:$B$1000,0))),"")) | G9: =IF($C9="","",IFERROR(IF(INDEX('🎓 Alumnas'!$F$2:$F$1000,MATCH($C9,'🎓 Alumnas'!$B$2:$B$1000,0))="","",INDEX('🎓 Alumnas'!$F$2:$F$1000,MATCH($C9,'🎓 Alumnas'!$B$2:$B$1000,0))),"")) | H9: =IF(G9="","",DATEDIF(G9,TODAY(),"Y")) | I9: 16 clases : Sport Elite club $480.000 | J9: =IF(I9="","",IF(LEFT(I9,6)="1 Pole","Alquiler",IF(LEFT(I9,7)="1 Clase","Clase suelta","Paquete"))) -> Paquete | K9: Promo 2x1 | L9: 1 | M9: 240000 | N9: =IF(M9="","",L9*M9) -> 240000 | O9: 0.5 | P9: Nequi | R9: =IF(C9="","",IF(COUNTIF($C$2:C9,C9)=1,"Nueva","Recurrente")) -> Nueva | S9: =IF(OR(C9="",J9<>"Paquete"),"",COUNTIFS($C$2:C9,C9,$J$2:J9,"Paquete")) -> 1
A10: I-009 | B10: 46267 | C10: Maria Paula Leon | D10: =IF($C10="","",IFERROR(IF(INDEX('🎓 Alumnas'!$C$2:$C$1000,MATCH($C10,'🎓 Alumnas'!$B$2:$B$1000,0))="","",INDEX('🎓 Alumnas'!$C$2:$C$1000,MATCH($C10,'🎓 Alumnas'!$B$2:$B$1000,0))),"")) | E10: =IF($C10="","",IFERROR(IF(INDEX('🎓 Alumnas'!$D$2:$D$1000,MATCH($C10,'🎓 Alumnas'!$B$2:$B$1000,0))="","",INDEX('🎓 Alumnas'!$D$2:$D$1000,MATCH($C10,'🎓 Alumnas'!$B$2:$B$1000,0))),"")) | F10: =IF($C10="","",IFERROR(IF(INDEX('🎓 Alumnas'!$E$2:$E$1000,MATCH($C10,'🎓 Alumnas'!$B$2:$B$1000,0))="","",INDEX('🎓 Alumnas'!$E$2:$E$1000,MATCH($C10,'🎓 Alumnas'!$B$2:$B$1000,0))),"")) | G10: =IF($C10="","",IFERROR(IF(INDEX('🎓 Alumnas'!$F$2:$F$1000,MATCH($C10,'🎓 Alumnas'!$B$2:$B$1000,0))="","",INDEX('🎓 Alumnas'!$F$2:$F$1000,MATCH($C10,'🎓 Alumnas'!$B$2:$B$1000,0))),"")) | H10: =IF(G10="","",DATEDIF(G10,TODAY(),"Y")) | I10: 16 clases : Sport Elite club $480.000 | J10: =IF(I10="","",IF(LEFT(I10,6)="1 Pole","Alquiler",IF(LEFT(I10,7)="1 Clase","Clase suelta","Paquete"))) -> Paquete | K10: Promo 2x1 | L10: 1 | M10: 240000 | N10: =IF(M10="","",L10*M10) -> 240000 | O10: 0.5 | P10: Transferencia Bancaria | R10: =IF(C10="","",IF(COUNTIF($C$2:C10,C10)=1,"Nueva","Recurrente")) -> Nueva | S10: =IF(OR(C10="",J10<>"Paquete"),"",COUNTIFS($C$2:C10,C10,$J$2:J10,"Paquete")) -> 1
A11: I-010 | B11: 46272 | C11: Ntalia Alejandra Luna | D11: =IF($C11="","",IFERROR(IF(INDEX('🎓 Alumnas'!$C$2:$C$1000,MATCH($C11,'🎓 Alumnas'!$B$2:$B$1000,0))="","",INDEX('🎓 Alumnas'!$C$2:$C$1000,MATCH($C11,'🎓 Alumnas'!$B$2:$B$1000,0))),"")) | E11: =IF($C11="","",IFERROR(IF(INDEX('🎓 Alumnas'!$D$2:$D$1000,MATCH($C11,'🎓 Alumnas'!$B$2:$B$1000,0))="","",INDEX('🎓 Alumnas'!$D$2:$D$1000,MATCH($C11,'🎓 Alumnas'!$B$2:$B$1000,0))),"")) | F11: =IF($C11="","",IFERROR(IF(INDEX('🎓 Alumnas'!$E$2:$E$1000,MATCH($C11,'🎓 Alumnas'!$B$2:$B$1000,0))="","",INDEX('🎓 Alumnas'!$E$2:$E$1000,MATCH($C11,'🎓 Alumnas'!$B$2:$B$1000,0))),"")) | G11: =IF($C11="","",IFERROR(IF(INDEX('🎓 Alumnas'!$F$2:$F$1000,MATCH($C11,'🎓 Alumnas'!$B$2:$B$1000,0))="","",INDEX('🎓 Alumnas'!$F$2:$F$1000,MATCH($C11,'🎓 Alumnas'!$B$2:$B$1000,0))),"")) | H11: =IF(G11="","",DATEDIF(G11,TODAY(),"Y")) | I11: 16 clases : Sport Elite club $480.000 | J11: =IF(I11="","",IF(LEFT(I11,6)="1 Pole","Alquiler",IF(LEFT(I11,7)="1 Clase","Clase suelta","Paquete"))) -> Paquete | K11: Promo 2x1 | L11: 1 | M11: 240000 | N11: =IF(M11="","",L11*M11) -> 240000 | O11: 0.5 | P11: Transferencia Bancaria | R11: =IF(C11="","",IF(COUNTIF($C$2:C11,C11)=1,"Nueva","Recurrente")) -> Nueva | S11: =IF(OR(C11="",J11<>"Paquete"),"",COUNTIFS($C$2:C11,C11,$J$2:J11,"Paquete")) -> 1
A12: I-011 | B12: 46272 | C12: Marcella Cuellar | D12: =IF($C12="","",IFERROR(IF(INDEX('🎓 Alumnas'!$C$2:$C$1000,MATCH($C12,'🎓 Alumnas'!$B$2:$B$1000,0))="","",INDEX('🎓 Alumnas'!$C$2:$C$1000,MATCH($C12,'🎓 Alumnas'!$B$2:$B$1000,0))),"")) | E12: =IF($C12="","",IFERROR(IF(INDEX('🎓 Alumnas'!$D$2:$D$1000,MATCH($C12,'🎓 Alumnas'!$B$2:$B$1000,0))="","",INDEX('🎓 Alumnas'!$D$2:$D$1000,MATCH($C12,'🎓 Alumnas'!$B$2:$B$1000,0))),"")) | F12: =IF($C12="","",IFERROR(IF(INDEX('🎓 Alumnas'!$E$2:$E$1000,MATCH($C12,'🎓 Alumnas'!$B$2:$B$1000,0))="","",INDEX('🎓 Alumnas'!$E$2:$E$1000,MATCH($C12,'🎓 Alumnas'!$B$2:$B$1000,0))),"")) | G12: =IF($C12="","",IFERROR(IF(INDEX('🎓 Alumnas'!$F$2:$F$1000,MATCH($C12,'🎓 Alumnas'!$B$2:$B$1000,0))="","",INDEX('🎓 Alumnas'!$F$2:$F$1000,MATCH($C12,'🎓 Alumnas'!$B$2:$B$1000,0))),"")) | H12: =IF(G12="","",DATEDIF(G12,TODAY(),"Y")) | I12: 16 clases : Sport Elite club $480.000 | J12: =IF(I12="","",IF(LEFT(I12,6)="1 Pole","Alquiler",IF(LEFT(I12,7)="1 Clase","Clase suelta","Paquete"))) -> Paquete | K12: Promo 2x1 | L12: 1 | M12: 240000 | N12: =IF(M12="","",L12*M12) -> 240000 | O12: 0.5 | P12: Transferencia Bancaria | R12: =IF(C12="","",IF(COUNTIF($C$2:C12,C12)=1,"Nueva","Recurrente")) -> Nueva | S12: =IF(OR(C12="",J12<>"Paquete"),"",COUNTIFS($C$2:C12,C12,$J$2:J12,"Paquete")) -> 1
A13: I-012 | B13: 46274 | C13: Danial Avila | D13: =IF($C13="","",IFERROR(IF(INDEX('🎓 Alumnas'!$C$2:$C$1000,MATCH($C13,'🎓 Alumnas'!$B$2:$B$1000,0))="","",INDEX('🎓 Alumnas'!$C$2:$C$1000,MATCH($C13,'🎓 Alumnas'!$B$2:$B$1000,0))),"")) | E13: =IF($C13="","",IFERROR(IF(INDEX('🎓 Alumnas'!$D$2:$D$1000,MATCH($C13,'🎓 Alumnas'!$B$2:$B$1000,0))="","",INDEX('🎓 Alumnas'!$D$2:$D$1000,MATCH($C13,'🎓 Alumnas'!$B$2:$B$1000,0))),"")) | F13: =IF($C13="","",IFERROR(IF(INDEX('🎓 Alumnas'!$E$2:$E$1000,MATCH($C13,'🎓 Alumnas'!$B$2:$B$1000,0))="","",INDEX('🎓 Alumnas'!$E$2:$E$1000,MATCH($C13,'🎓 Alumnas'!$B$2:$B$1000,0))),"")) | G13: =IF($C13="","",IFERROR(IF(INDEX('🎓 Alumnas'!$F$2:$F$1000,MATCH($C13,'🎓 Alumnas'!$B$2:$B$1000,0))="","",INDEX('🎓 Alumnas'!$F$2:$F$1000,MATCH($C13,'🎓 Alumnas'!$B$2:$B$1000,0))),"")) | H13: =IF(G13="","",DATEDIF(G13,TODAY(),"Y")) | I13: 1 Pole: Alquiler $22000 | J13: =IF(I13="","",IF(LEFT(I13,6)="1 Pole","Alquiler",IF(LEFT(I13,7)="1 Clase","Clase suelta","Paquete"))) -> Alquiler | L13: 1 | M13: 22000 | N13: =IF(M13="","",L13*M13) -> 22000 | O13: 1 | P13: Transferencia Bancaria | R13: =IF(C13="","",IF(COUNTIF($C$2:C13,C13)=1,"Nueva","Recurrente")) -> Nueva | S13: =IF(OR(C13="",J13<>"Paquete"),"",COUNTIFS($C$2:C13,C13,$J$2:J13,"Paquete"))
A14: I-013 | B14: 46274 | C14: Karol Sierra | D14: =IF($C14="","",IFERROR(IF(INDEX('🎓 Alumnas'!$C$2:$C$1000,MATCH($C14,'🎓 Alumnas'!$B$2:$B$1000,0))="","",INDEX('🎓 Alumnas'!$C$2:$C$1000,MATCH($C14,'🎓 Alumnas'!$B$2:$B$1000,0))),"")) | E14: =IF($C14="","",IFERROR(IF(INDEX('🎓 Alumnas'!$D$2:$D$1000,MATCH($C14,'🎓 Alumnas'!$B$2:$B$1000,0))="","",INDEX('🎓 Alumnas'!$D$2:$D$1000,MATCH($C14,'🎓 Alumnas'!$B$2:$B$1000,0))),"")) | F14: =IF($C14="","",IFERROR(IF(INDEX('🎓 Alumnas'!$E$2:$E$1000,MATCH($C14,'🎓 Alumnas'!$B$2:$B$1000,0))="","",INDEX('🎓 Alumnas'!$E$2:$E$1000,MATCH($C14,'🎓 Alumnas'!$B$2:$B$1000,0))),"")) | G14: =IF($C14="","",IFERROR(IF(INDEX('🎓 Alumnas'!$F$2:$F$1000,MATCH($C14,'🎓 Alumnas'!$B$2:$B$1000,0))="","",INDEX('🎓 Alumnas'!$F$2:$F$1000,MATCH($C14,'🎓 Alumnas'!$B$2:$B$1000,0))),"")) | H14: =IF(G14="","",DATEDIF(G14,TODAY(),"Y")) | I14: 1 Pole: Alquiler $22000 | J14: =IF(I14="","",IF(LEFT(I14,6)="1 Pole","Alquiler",IF(LEFT(I14,7)="1 Clase","Clase suelta","Paquete"))) -> Alquiler | L14: 1 | M14: 22000 | N14: =IF(M14="","",L14*M14) -> 22000 | O14: 1 | P14: Transferencia Bancaria | R14: =IF(C14="","",IF(COUNTIF($C$2:C14,C14)=1,"Nueva","Recurrente")) -> Nueva | S14: =IF(OR(C14="",J14<>"Paquete"),"",COUNTIFS($C$2:C14,C14,$J$2:J14,"Paquete"))
A15: I-015 | B15: 46276 | C15: Maira Alejandra Vergara | D15: =IF($C15="","",IFERROR(IF(INDEX('🎓 Alumnas'!$C$2:$C$1000,MATCH($C15,'🎓 Alumnas'!$B$2:$B$1000,0))="","",INDEX('🎓 Alumnas'!$C$2:$C$1000,MATCH($C15,'🎓 Alumnas'!$B$2:$B$1000,0))),"")) | E15: =IF($C15="","",IFERROR(IF(INDEX('🎓 Alumnas'!$D$2:$D$1000,MATCH($C15,'🎓 Alumnas'!$B$2:$B$1000,0))="","",INDEX('🎓 Alumnas'!$D$2:$D$1000,MATCH($C15,'🎓 Alumnas'!$B$2:$B$1000,0))),"")) | F15: =IF($C15="","",IFERROR(IF(INDEX('🎓 Alumnas'!$E$2:$E$1000,MATCH($C15,'🎓 Alumnas'!$B$2:$B$1000,0))="","",INDEX('🎓 Alumnas'!$E$2:$E$1000,MATCH($C15,'🎓 Alumnas'!$B$2:$B$1000,0))),"")) | G15: =IF($C15="","",IFERROR(IF(INDEX('🎓 Alumnas'!$F$2:$F$1000,MATCH($C15,'🎓 Alumnas'!$B$2:$B$1000,0))="","",INDEX('🎓 Alumnas'!$F$2:$F$1000,MATCH($C15,'🎓 Alumnas'!$B$2:$B$1000,0))),"")) | H15: =IF(G15="","",DATEDIF(G15,TODAY(),"Y")) | I15: 9 clases: Sport Power Team $350.000 | J15: =IF(I15="","",IF(LEFT(I15,6)="1 Pole","Alquiler",IF(LEFT(I15,7)="1 Clase","Clase suelta","Paquete"))) -> Paquete | L15: 1 | M15: 350000 | N15: =IF(M15="","",L15*M15) -> 350000 | O15: 1 | P15: Transferencia Bancaria | R15: =IF(C15="","",IF(COUNTIF($C$2:C15,C15)=1,"Nueva","Recurrente")) -> Nueva | S15: =IF(OR(C15="",J15<>"Paquete"),"",COUNTIFS($C$2:C15,C15,$J$2:J15,"Paquete")) -> 1
A16: I-016 | B16: 46280 | C16: Jose Alberto Rojas Gonzalez | D16: =IF($C16="","",IFERROR(IF(INDEX('🎓 Alumnas'!$C$2:$C$1000,MATCH($C16,'🎓 Alumnas'!$B$2:$B$1000,0))="","",INDEX('🎓 Alumnas'!$C$2:$C$1000,MATCH($C16,'🎓 Alumnas'!$B$2:$B$1000,0))),"")) | E16: =IF($C16="","",IFERROR(IF(INDEX('🎓 Alumnas'!$D$2:$D$1000,MATCH($C16,'🎓 Alumnas'!$B$2:$B$1000,0))="","",INDEX('🎓 Alumnas'!$D$2:$D$1000,MATCH($C16,'🎓 Alumnas'!$B$2:$B$1000,0))),"")) | F16: =IF($C16="","",IFERROR(IF(INDEX('🎓 Alumnas'!$E$2:$E$1000,MATCH($C16,'🎓 Alumnas'!$B$2:$B$1000,0))="","",INDEX('🎓 Alumnas'!$E$2:$E$1000,MATCH($C16,'🎓 Alumnas'!$B$2:$B$1000,0))),"")) | G16: =IF($C16="","",IFERROR(IF(INDEX('🎓 Alumnas'!$F$2:$F$1000,MATCH($C16,'🎓 Alumnas'!$B$2:$B$1000,0))="","",INDEX('🎓 Alumnas'!$F$2:$F$1000,MATCH($C16,'🎓 Alumnas'!$B$2:$B$1000,0))),"")) | H16: =IF(G16="","",DATEDIF(G16,TODAY(),"Y")) | I16: 1 Pole: Alquiler $22000 | J16: =IF(I16="","",IF(LEFT(I16,6)="1 Pole","Alquiler",IF(LEFT(I16,7)="1 Clase","Clase suelta","Paquete"))) -> Alquiler | L16: 2 | M16: 22000 | N16: =IF(M16="","",L16*M16) -> 44000 | O16: 1 | P16: Transferencia Bancaria | R16: =IF(C16="","",IF(COUNTIF($C$2:C16,C16)=1,"Nueva","Recurrente")) -> Nueva | S16: =IF(OR(C16="",J16<>"Paquete"),"",COUNTIFS($C$2:C16,C16,$J$2:J16,"Paquete"))
A17: I-017 | B17: 46281 | C17: Danial Avila | D17: =IF($C17="","",IFERROR(IF(INDEX('🎓 Alumnas'!$C$2:$C$1000,MATCH($C17,'🎓 Alumnas'!$B$2:$B$1000,0))="","",INDEX('🎓 Alumnas'!$C$2:$C$1000,MATCH($C17,'🎓 Alumnas'!$B$2:$B$1000,0))),"")) | E17: =IF($C17="","",IFERROR(IF(INDEX('🎓 Alumnas'!$D$2:$D$1000,MATCH($C17,'🎓 Alumnas'!$B$2:$B$1000,0))="","",INDEX('🎓 Alumnas'!$D$2:$D$1000,MATCH($C17,'🎓 Alumnas'!$B$2:$B$1000,0))),"")) | F17: =IF($C17="","",IFERROR(IF(INDEX('🎓 Alumnas'!$E$2:$E$1000,MATCH($C17,'🎓 Alumnas'!$B$2:$B$1000,0))="","",INDEX('🎓 Alumnas'!$E$2:$E$1000,MATCH($C17,'🎓 Alumnas'!$B$2:$B$1000,0))),"")) | G17: =IF($C17="","",IFERROR(IF(INDEX('🎓 Alumnas'!$F$2:$F$1000,MATCH($C17,'🎓 Alumnas'!$B$2:$B$1000,0))="","",INDEX('🎓 Alumnas'!$F$2:$F$1000,MATCH($C17,'🎓 Alumnas'!$B$2:$B$1000,0))),"")) | H17: =IF(G17="","",DATEDIF(G17,TODAY(),"Y")) | I17: 1 Pole: Alquiler $22000 | J17: =IF(I17="","",IF(LEFT(I17,6)="1 Pole","Alquiler",IF(LEFT(I17,7)="1 Clase","Clase suelta","Paquete"))) -> Alquiler | L17: 1 | M17: 22000 | N17: =IF(M17="","",L17*M17) -> 22000 | O17: 1 | P17: Transferencia Bancaria | R17: =IF(C17="","",IF(COUNTIF($C$2:C17,C17)=1,"Nueva","Recurrente")) -> Recurrente | S17: =IF(OR(C17="",J17<>"Paquete"),"",COUNTIFS($C$2:C17,C17,$J$2:J17,"Paquete"))
A18: I-018 | B18: 46281 | C18: Laura Sofia Hilarion | D18: =IF($C18="","",IFERROR(IF(INDEX('🎓 Alumnas'!$C$2:$C$1000,MATCH($C18,'🎓 Alumnas'!$B$2:$B$1000,0))="","",INDEX('🎓 Alumnas'!$C$2:$C$1000,MATCH($C18,'🎓 Alumnas'!$B$2:$B$1000,0))),"")) -> 3204479014 | E18: =IF($C18="","",IFERROR(IF(INDEX('🎓 Alumnas'!$D$2:$D$1000,MATCH($C18,'🎓 Alumnas'!$B$2:$B$1000,0))="","",INDEX('🎓 Alumnas'!$D$2:$D$1000,MATCH($C18,'🎓 Alumnas'!$B$2:$B$1000,0))),"")) | F18: =IF($C18="","",IFERROR(IF(INDEX('🎓 Alumnas'!$E$2:$E$1000,MATCH($C18,'🎓 Alumnas'!$B$2:$B$1000,0))="","",INDEX('🎓 Alumnas'!$E$2:$E$1000,MATCH($C18,'🎓 Alumnas'!$B$2:$B$1000,0))),"")) | G18: =IF($C18="","",IFERROR(IF(INDEX('🎓 Alumnas'!$F$2:$F$1000,MATCH($C18,'🎓 Alumnas'!$B$2:$B$1000,0))="","",INDEX('🎓 Alumnas'!$F$2:$F$1000,MATCH($C18,'🎓 Alumnas'!$B$2:$B$1000,0))),"")) | H18: =IF(G18="","",DATEDIF(G18,TODAY(),"Y")) | I18: 16 clases : Sport Elite club $480.000 | J18: =IF(I18="","",IF(LEFT(I18,6)="1 Pole","Alquiler",IF(LEFT(I18,7)="1 Clase","Clase suelta","Paquete"))) -> Paquete | L18: 1 | M18: 480000 | N18: =IF(M18="","",L18*M18) -> 480000 | O18: 1 | P18: Nequi | R18: =IF(C18="","",IF(COUNTIF($C$2:C18,C18)=1,"Nueva","Recurrente")) -> Nueva | S18: =IF(OR(C18="",J18<>"Paquete"),"",COUNTIFS($C$2:C18,C18,$J$2:J18,"Paquete")) -> 1
A19: I-019 | B19: 46283 | C19: Alejandra Ortega | D19: =IF($C19="","",IFERROR(IF(INDEX('🎓 Alumnas'!$C$2:$C$1000,MATCH($C19,'🎓 Alumnas'!$B$2:$B$1000,0))="","",INDEX('🎓 Alumnas'!$C$2:$C$1000,MATCH($C19,'🎓 Alumnas'!$B$2:$B$1000,0))),"")) -> 3114401669 | E19: =IF($C19="","",IFERROR(IF(INDEX('🎓 Alumnas'!$D$2:$D$1000,MATCH($C19,'🎓 Alumnas'!$B$2:$B$1000,0))="","",INDEX('🎓 Alumnas'!$D$2:$D$1000,MATCH($C19,'🎓 Alumnas'!$B$2:$B$1000,0))),"")) | F19: =IF($C19="","",IFERROR(IF(INDEX('🎓 Alumnas'!$E$2:$E$1000,MATCH($C19,'🎓 Alumnas'!$B$2:$B$1000,0))="","",INDEX('🎓 Alumnas'!$E$2:$E$1000,MATCH($C19,'🎓 Alumnas'!$B$2:$B$1000,0))),"")) | G19: =IF($C19="","",IFERROR(IF(INDEX('🎓 Alumnas'!$F$2:$F$1000,MATCH($C19,'🎓 Alumnas'!$B$2:$B$1000,0))="","",INDEX('🎓 Alumnas'!$F$2:$F$1000,MATCH($C19,'🎓 Alumnas'!$B$2:$B$1000,0))),"")) | H19: =IF(G19="","",DATEDIF(G19,TODAY(),"Y")) | I19: 16 clases : Sport Elite club $480.000 | J19: =IF(I19="","",IF(LEFT(I19,6)="1 Pole","Alquiler",IF(LEFT(I19,7)="1 Clase","Clase suelta","Paquete"))) -> Paquete | K19: Promo 2x1 | L19: 1 | M19: 240000 | N19: =IF(M19="","",L19*M19) -> 240000 | O19: 0.5 | P19: Nequi | R19: =IF(C19="","",IF(COUNTIF($C$2:C19,C19)=1,"Nueva","Recurrente")) -> Nueva | S19: =IF(OR(C19="",J19<>"Paquete"),"",COUNTIFS($C$2:C19,C19,$J$2:J19,"Paquete")) -> 1
A20: I-020 | B20: 46283 | C20: Juliana Bossa | D20: =IF($C20="","",IFERROR(IF(INDEX('🎓 Alumnas'!$C$2:$C$1000,MATCH($C20,'🎓 Alumnas'!$B$2:$B$1000,0))="","",INDEX('🎓 Alumnas'!$C$2:$C$1000,MATCH($C20,'🎓 Alumnas'!$B$2:$B$1000,0))),"")) -> 3185937737 | E20: =IF($C20="","",IFERROR(IF(INDEX('🎓 Alumnas'!$D$2:$D$1000,MATCH($C20,'🎓 Alumnas'!$B$2:$B$1000,0))="","",INDEX('🎓 Alumnas'!$D$2:$D$1000,MATCH($C20,'🎓 Alumnas'!$B$2:$B$1000,0))),"")) | F20: =IF($C20="","",IFERROR(IF(INDEX('🎓 Alumnas'!$E$2:$E$1000,MATCH($C20,'🎓 Alumnas'!$B$2:$B$1000,0))="","",INDEX('🎓 Alumnas'!$E$2:$E$1000,MATCH($C20,'🎓 Alumnas'!$B$2:$B$1000,0))),"")) | G20: =IF($C20="","",IFERROR(IF(INDEX('🎓 Alumnas'!$F$2:$F$1000,MATCH($C20,'🎓 Alumnas'!$B$2:$B$1000,0))="","",INDEX('🎓 Alumnas'!$F$2:$F$1000,MATCH($C20,'🎓 Alumnas'!$B$2:$B$1000,0))),"")) | H20: =IF(G20="","",DATEDIF(G20,TODAY(),"Y")) | I20: 1 Pole: Alquiler $22000 | J20: =IF(I20="","",IF(LEFT(I20,6)="1 Pole","Alquiler",IF(LEFT(I20,7)="1 Clase","Clase suelta","Paquete"))) -> Alquiler | L20: 1 | M20: 22000 | N20: =IF(M20="","",L20*M20) -> 22000 | O20: 1 | P20: Transferencia Bancaria | R20: =IF(C20="","",IF(COUNTIF($C$2:C20,C20)=1,"Nueva","Recurrente")) -> Recurrente | S20: =IF(OR(C20="",J20<>"Paquete"),"",COUNTIFS($C$2:C20,C20,$J$2:J20,"Paquete"))
A21: I-021 | B21: 46283 | C21: Mary Aurora Osorio Alvarez | D21: =IF($C21="","",IFERROR(IF(INDEX('🎓 Alumnas'!$C$2:$C$1000,MATCH($C21,'🎓 Alumnas'!$B$2:$B$1000,0))="","",INDEX('🎓 Alumnas'!$C$2:$C$1000,MATCH($C21,'🎓 Alumnas'!$B$2:$B$1000,0))),"")) -> 3186650375 | E21: =IF($C21="","",IFERROR(IF(INDEX('🎓 Alumnas'!$D$2:$D$1000,MATCH($C21,'🎓 Alumnas'!$B$2:$B$1000,0))="","",INDEX('🎓 Alumnas'!$D$2:$D$1000,MATCH($C21,'🎓 Alumnas'!$B$2:$B$1000,0))),"")) | F21: =IF($C21="","",IFERROR(IF(INDEX('🎓 Alumnas'!$E$2:$E$1000,MATCH($C21,'🎓 Alumnas'!$B$2:$B$1000,0))="","",INDEX('🎓 Alumnas'!$E$2:$E$1000,MATCH($C21,'🎓 Alumnas'!$B$2:$B$1000,0))),"")) | G21: =IF($C21="","",IFERROR(IF(INDEX('🎓 Alumnas'!$F$2:$F$1000,MATCH($C21,'🎓 Alumnas'!$B$2:$B$1000,0))="","",INDEX('🎓 Alumnas'!$F$2:$F$1000,MATCH($C21,'🎓 Alumnas'!$B$2:$B$1000,0))),"")) | H21: =IF(G21="","",DATEDIF(G21,TODAY(),"Y")) | I21: 1 Clase: Individual $50000 | J21: =IF(I21="","",IF(LEFT(I21,6)="1 Pole","Alquiler",IF(LEFT(I21,7)="1 Clase","Clase suelta","Paquete"))) -> Clase suelta | L21: 1 | M21: 50000 | N21: =IF(M21="","",L21*M21) -> 50000 | O21: 1 | P21: Nequi | R21: =IF(C21="","",IF(COUNTIF($C$2:C21,C21)=1,"Nueva","Recurrente")) -> Nueva | S21: =IF(OR(C21="",J21<>"Paquete"),"",COUNTIFS($C$2:C21,C21,$J$2:J21,"Paquete"))
A22: I-022 | B22: 46283 | C22: Elizabeth Lopez salamanca | D22: =IF($C22="","",IFERROR(IF(INDEX('🎓 Alumnas'!$C$2:$C$1000,MATCH($C22,'🎓 Alumnas'!$B$2:$B$1000,0))="","",INDEX('🎓 Alumnas'!$C$2:$C$1000,MATCH($C22,'🎓 Alumnas'!$B$2:$B$1000,0))),"")) -> 3197067161 | E22: =IF($C22="","",IFERROR(IF(INDEX('🎓 Alumnas'!$D$2:$D$1000,MATCH($C22,'🎓 Alumnas'!$B$2:$B$1000,0))="","",INDEX('🎓 Alumnas'!$D$2:$D$1000,MATCH($C22,'🎓 Alumnas'!$B$2:$B$1000,0))),"")) | F22: =IF($C22="","",IFERROR(IF(INDEX('🎓 Alumnas'!$E$2:$E$1000,MATCH($C22,'🎓 Alumnas'!$B$2:$B$1000,0))="","",INDEX('🎓 Alumnas'!$E$2:$E$1000,MATCH($C22,'🎓 Alumnas'!$B$2:$B$1000,0))),"")) | G22: =IF($C22="","",IFERROR(IF(INDEX('🎓 Alumnas'!$F$2:$F$1000,MATCH($C22,'🎓 Alumnas'!$B$2:$B$1000,0))="","",INDEX('🎓 Alumnas'!$F$2:$F$1000,MATCH($C22,'🎓 Alumnas'!$B$2:$B$1000,0))),"")) | H22: =IF(G22="","",DATEDIF(G22,TODAY(),"Y")) | I22: 1 Clase: Individual $50000 | J22: =IF(I22="","",IF(LEFT(I22,6)="1 Pole","Alquiler",IF(LEFT(I22,7)="1 Clase","Clase suelta","Paquete"))) -> Clase suelta | L22: 1 | M22: 50000 | N22: =IF(M22="","",L22*M22) -> 50000 | O22: 1 | P22: Nequi | R22: =IF(C22="","",IF(COUNTIF($C$2:C22,C22)=1,"Nueva","Recurrente")) -> Nueva | S22: =IF(OR(C22="",J22<>"Paquete"),"",COUNTIFS($C$2:C22,C22,$J$2:J22,"Paquete"))
A23: I-023 | B23: 46286 | C23: Karol Sierra | D23: =IF($C23="","",IFERROR(IF(INDEX('🎓 Alumnas'!$C$2:$C$1000,MATCH($C23,'🎓 Alumnas'!$B$2:$B$1000,0))="","",INDEX('🎓 Alumnas'!$C$2:$C$1000,MATCH($C23,'🎓 Alumnas'!$B$2:$B$1000,0))),"")) | E23: =IF($C23="","",IFERROR(IF(INDEX('🎓 Alumnas'!$D$2:$D$1000,MATCH($C23,'🎓 Alumnas'!$B$2:$B$1000,0))="","",INDEX('🎓 Alumnas'!$D$2:$D$1000,MATCH($C23,'🎓 Alumnas'!$B$2:$B$1000,0))),"")) | F23: =IF($C23="","",IFERROR(IF(INDEX('🎓 Alumnas'!$E$2:$E$1000,MATCH($C23,'🎓 Alumnas'!$B$2:$B$1000,0))="","",INDEX('🎓 Alumnas'!$E$2:$E$1000,MATCH($C23,'🎓 Alumnas'!$B$2:$B$1000,0))),"")) | G23: =IF($C23="","",IFERROR(IF(INDEX('🎓 Alumnas'!$F$2:$F$1000,MATCH($C23,'🎓 Alumnas'!$B$2:$B$1000,0))="","",INDEX('🎓 Alumnas'!$F$2:$F$1000,MATCH($C23,'🎓 Alumnas'!$B$2:$B$1000,0))),"")) | H23: =IF(G23="","",DATEDIF(G23,TODAY(),"Y")) | I23: 1 Pole: Alquiler $22000 | J23: =IF(I23="","",IF(LEFT(I23,6)="1 Pole","Alquiler",IF(LEFT(I23,7)="1 Clase","Clase suelta","Paquete"))) -> Alquiler | L23: 2 | M23: 22000 | N23: =IF(M23="","",L23*M23) -> 44000 | O23: 1 | P23: Transferencia Bancaria | R23: =IF(C23="","",IF(COUNTIF($C$2:C23,C23)=1,"Nueva","Recurrente")) -> Recurrente | S23: =IF(OR(C23="",J23<>"Paquete"),"",COUNTIFS($C$2:C23,C23,$J$2:J23,"Paquete"))
A24: I-024 | B24: 46287 | C24: Paula Andrea Pinzon | D24: =IF($C24="","",IFERROR(IF(INDEX('🎓 Alumnas'!$C$2:$C$1000,MATCH($C24,'🎓 Alumnas'!$B$2:$B$1000,0))="","",INDEX('🎓 Alumnas'!$C$2:$C$1000,MATCH($C24,'🎓 Alumnas'!$B$2:$B$1000,0))),"")) | E24: =IF($C24="","",IFERROR(IF(INDEX('🎓 Alumnas'!$D$2:$D$1000,MATCH($C24,'🎓 Alumnas'!$B$2:$B$1000,0))="","",INDEX('🎓 Alumnas'!$D$2:$D$1000,MATCH($C24,'🎓 Alumnas'!$B$2:$B$1000,0))),"")) | F24: =IF($C24="","",IFERROR(IF(INDEX('🎓 Alumnas'!$E$2:$E$1000,MATCH($C24,'🎓 Alumnas'!$B$2:$B$1000,0))="","",INDEX('🎓 Alumnas'!$E$2:$E$1000,MATCH($C24,'🎓 Alumnas'!$B$2:$B$1000,0))),"")) | G24: =IF($C24="","",IFERROR(IF(INDEX('🎓 Alumnas'!$F$2:$F$1000,MATCH($C24,'🎓 Alumnas'!$B$2:$B$1000,0))="","",INDEX('🎓 Alumnas'!$F$2:$F$1000,MATCH($C24,'🎓 Alumnas'!$B$2:$B$1000,0))),"")) | H24: =IF(G24="","",DATEDIF(G24,TODAY(),"Y")) | I24: 1 Clase: Individual $50000 | J24: =IF(I24="","",IF(LEFT(I24,6)="1 Pole","Alquiler",IF(LEFT(I24,7)="1 Clase","Clase suelta","Paquete"))) -> Clase suelta | L24: 1 | M24: 50000 | N24: =IF(M24="","",L24*M24) -> 50000 | O24: 1 | P24: Transferencia Bancaria | R24: =IF(C24="","",IF(COUNTIF($C$2:C24,C24)=1,"Nueva","Recurrente")) -> Nueva | S24: =IF(OR(C24="",J24<>"Paquete"),"",COUNTIFS($C$2:C24,C24,$J$2:J24,"Paquete"))
A25: I-025 | B25: 46291 | C25: Marcela Garcia Sanabria | D25: =IF($C25="","",IFERROR(IF(INDEX('🎓 Alumnas'!$C$2:$C$1000,MATCH($C25,'🎓 Alumnas'!$B$2:$B$1000,0))="","",INDEX('🎓 Alumnas'!$C$2:$C$1000,MATCH($C25,'🎓 Alumnas'!$B$2:$B$1000,0))),"")) -> 3123221477 | E25: =IF($C25="","",IFERROR(IF(INDEX('🎓 Alumnas'!$D$2:$D$1000,MATCH($C25,'🎓 Alumnas'!$B$2:$B$1000,0))="","",INDEX('🎓 Alumnas'!$D$2:$D$1000,MATCH($C25,'🎓 Alumnas'!$B$2:$B$1000,0))),"")) | F25: =IF($C25="","",IFERROR(IF(INDEX('🎓 Alumnas'!$E$2:$E$1000,MATCH($C25,'🎓 Alumnas'!$B$2:$B$1000,0))="","",INDEX('🎓 Alumnas'!$E$2:$E$1000,MATCH($C25,'🎓 Alumnas'!$B$2:$B$1000,0))),"")) | G25: =IF($C25="","",IFERROR(IF(INDEX('🎓 Alumnas'!$F$2:$F$1000,MATCH($C25,'🎓 Alumnas'!$B$2:$B$1000,0))="","",INDEX('🎓 Alumnas'!$F$2:$F$1000,MATCH($C25,'🎓 Alumnas'!$B$2:$B$1000,0))),"")) | H25: =IF(G25="","",DATEDIF(G25,TODAY(),"Y")) | I25: 9 clases: Sport Power Team $350.000 | J25: =IF(I25="","",IF(LEFT(I25,6)="1 Pole","Alquiler",IF(LEFT(I25,7)="1 Clase","Clase suelta","Paquete"))) -> Paquete | L25: 1 | M25: 350000 | N25: =IF(M25="","",L25*M25) -> 350000 | O25: 1 | P25: Nequi | R25: =IF(C25="","",IF(COUNTIF($C$2:C25,C25)=1,"Nueva","Recurrente")) -> Nueva | S25: =IF(OR(C25="",J25<>"Paquete"),"",COUNTIFS($C$2:C25,C25,$J$2:J25,"Paquete")) -> 1
A26: I-026 | B26: 46291 | C26: Paula Andrea Pinzon | D26: =IF($C26="","",IFERROR(IF(INDEX('🎓 Alumnas'!$C$2:$C$1000,MATCH($C26,'🎓 Alumnas'!$B$2:$B$1000,0))="","",INDEX('🎓 Alumnas'!$C$2:$C$1000,MATCH($C26,'🎓 Alumnas'!$B$2:$B$1000,0))),"")) | E26: =IF($C26="","",IFERROR(IF(INDEX('🎓 Alumnas'!$D$2:$D$1000,MATCH($C26,'🎓 Alumnas'!$B$2:$B$1000,0))="","",INDEX('🎓 Alumnas'!$D$2:$D$1000,MATCH($C26,'🎓 Alumnas'!$B$2:$B$1000,0))),"")) | F26: =IF($C26="","",IFERROR(IF(INDEX('🎓 Alumnas'!$E$2:$E$1000,MATCH($C26,'🎓 Alumnas'!$B$2:$B$1000,0))="","",INDEX('🎓 Alumnas'!$E$2:$E$1000,MATCH($C26,'🎓 Alumnas'!$B$2:$B$1000,0))),"")) | G26: =IF($C26="","",IFERROR(IF(INDEX('🎓 Alumnas'!$F$2:$F$1000,MATCH($C26,'🎓 Alumnas'!$B$2:$B$1000,0))="","",INDEX('🎓 Alumnas'!$F$2:$F$1000,MATCH($C26,'🎓 Alumnas'!$B$2:$B$1000,0))),"")) | H26: =IF(G26="","",DATEDIF(G26,TODAY(),"Y")) | I26: 4 clases: Sport Fitness Challenge $200.000 | J26: =IF(I26="","",IF(LEFT(I26,6)="1 Pole","Alquiler",IF(LEFT(I26,7)="1 Clase","Clase suelta","Paquete"))) -> Paquete | L26: 1 | M26: 150000 | N26: =IF(M26="","",L26*M26) -> 150000 | O26: 1 | P26: Transferencia Bancaria | R26: =IF(C26="","",IF(COUNTIF($C$2:C26,C26)=1,"Nueva","Recurrente")) -> Recurrente | S26: =IF(OR(C26="",J26<>"Paquete"),"",COUNTIFS($C$2:C26,C26,$J$2:J26,"Paquete")) -> 1
A27: I-027 | B27: 46293 | C27: Carolina Lopez | D27: =IF($C27="","",IFERROR(IF(INDEX('🎓 Alumnas'!$C$2:$C$1000,MATCH($C27,'🎓 Alumnas'!$B$2:$B$1000,0))="","",INDEX('🎓 Alumnas'!$C$2:$C$1000,MATCH($C27,'🎓 Alumnas'!$B$2:$B$1000,0))),"")) | E27: =IF($C27="","",IFERROR(IF(INDEX('🎓 Alumnas'!$D$2:$D$1000,MATCH($C27,'🎓 Alumnas'!$B$2:$B$1000,0))="","",INDEX('🎓 Alumnas'!$D$2:$D$1000,MATCH($C27,'🎓 Alumnas'!$B$2:$B$1000,0))),"")) | F27: =IF($C27="","",IFERROR(IF(INDEX('🎓 Alumnas'!$E$2:$E$1000,MATCH($C27,'🎓 Alumnas'!$B$2:$B$1000,0))="","",INDEX('🎓 Alumnas'!$E$2:$E$1000,MATCH($C27,'🎓 Alumnas'!$B$2:$B$1000,0))),"")) | G27: =IF($C27="","",IFERROR(IF(INDEX('🎓 Alumnas'!$F$2:$F$1000,MATCH($C27,'🎓 Alumnas'!$B$2:$B$1000,0))="","",INDEX('🎓 Alumnas'!$F$2:$F$1000,MATCH($C27,'🎓 Alumnas'!$B$2:$B$1000,0))),"")) | H27: =IF(G27="","",DATEDIF(G27,TODAY(),"Y")) | I27: 16 clases : Sport Elite club $480.000 | J27: =IF(I27="","",IF(LEFT(I27,6)="1 Pole","Alquiler",IF(LEFT(I27,7)="1 Clase","Clase suelta","Paquete"))) -> Paquete | K27: Promo 2x1 | L27: 1 | M27: 240000 | N27: =IF(M27="","",L27*M27) -> 240000 | O27: 0.5 | P27: Transferencia Bancaria | R27: =IF(C27="","",IF(COUNTIF($C$2:C27,C27)=1,"Nueva","Recurrente")) -> Nueva | S27: =IF(OR(C27="",J27<>"Paquete"),"",COUNTIFS($C$2:C27,C27,$J$2:J27,"Paquete")) -> 1
A28: I-028 | B28: 46293 | C28: Karol Sierra | D28: =IF($C28="","",IFERROR(IF(INDEX('🎓 Alumnas'!$C$2:$C$1000,MATCH($C28,'🎓 Alumnas'!$B$2:$B$1000,0))="","",INDEX('🎓 Alumnas'!$C$2:$C$1000,MATCH($C28,'🎓 Alumnas'!$B$2:$B$1000,0))),"")) | E28: =IF($C28="","",IFERROR(IF(INDEX('🎓 Alumnas'!$D$2:$D$1000,MATCH($C28,'🎓 Alumnas'!$B$2:$B$1000,0))="","",INDEX('🎓 Alumnas'!$D$2:$D$1000,MATCH($C28,'🎓 Alumnas'!$B$2:$B$1000,0))),"")) | F28: =IF($C28="","",IFERROR(IF(INDEX('🎓 Alumnas'!$E$2:$E$1000,MATCH($C28,'🎓 Alumnas'!$B$2:$B$1000,0))="","",INDEX('🎓 Alumnas'!$E$2:$E$1000,MATCH($C28,'🎓 Alumnas'!$B$2:$B$1000,0))),"")) | G28: =IF($C28="","",IFERROR(IF(INDEX('🎓 Alumnas'!$F$2:$F$1000,MATCH($C28,'🎓 Alumnas'!$B$2:$B$1000,0))="","",INDEX('🎓 Alumnas'!$F$2:$F$1000,MATCH($C28,'🎓 Alumnas'!$B$2:$B$1000,0))),"")) | H28: =IF(G28="","",DATEDIF(G28,TODAY(),"Y")) | I28: 1 Pole: Alquiler $22000 | J28: =IF(I28="","",IF(LEFT(I28,6)="1 Pole","Alquiler",IF(LEFT(I28,7)="1 Clase","Clase suelta","Paquete"))) -> Alquiler | L28: 1 | M28: 22000 | N28: =IF(M28="","",L28*M28) -> 22000 | O28: 1 | P28: Nequi | R28: =IF(C28="","",IF(COUNTIF($C$2:C28,C28)=1,"Nueva","Recurrente")) -> Recurrente | S28: =IF(OR(C28="",J28<>"Paquete"),"",COUNTIFS($C$2:C28,C28,$J$2:J28,"Paquete"))
A29: I-029 | B29: 46294 | C29: Francya Dámaris Arias | D29: =IF($C29="","",IFERROR(IF(INDEX('🎓 Alumnas'!$C$2:$C$1000,MATCH($C29,'🎓 Alumnas'!$B$2:$B$1000,0))="","",INDEX('🎓 Alumnas'!$C$2:$C$1000,MATCH($C29,'🎓 Alumnas'!$B$2:$B$1000,0))),"")) | E29: =IF($C29="","",IFERROR(IF(INDEX('🎓 Alumnas'!$D$2:$D$1000,MATCH($C29,'🎓 Alumnas'!$B$2:$B$1000,0))="","",INDEX('🎓 Alumnas'!$D$2:$D$1000,MATCH($C29,'🎓 Alumnas'!$B$2:$B$1000,0))),"")) | F29: =IF($C29="","",IFERROR(IF(INDEX('🎓 Alumnas'!$E$2:$E$1000,MATCH($C29,'🎓 Alumnas'!$B$2:$B$1000,0))="","",INDEX('🎓 Alumnas'!$E$2:$E$1000,MATCH($C29,'🎓 Alumnas'!$B$2:$B$1000,0))),"")) | G29: =IF($C29="","",IFERROR(IF(INDEX('🎓 Alumnas'!$F$2:$F$1000,MATCH($C29,'🎓 Alumnas'!$B$2:$B$1000,0))="","",INDEX('🎓 Alumnas'!$F$2:$F$1000,MATCH($C29,'🎓 Alumnas'!$B$2:$B$1000,0))),"")) | H29: =IF(G29="","",DATEDIF(G29,TODAY(),"Y")) | I29: 16 clases : Sport Elite club $480.000 | J29: =IF(I29="","",IF(LEFT(I29,6)="1 Pole","Alquiler",IF(LEFT(I29,7)="1 Clase","Clase suelta","Paquete"))) -> Paquete | K29: Promo 2x1 | L29: 1 | M29: 480000 | N29: =IF(M29="","",L29*M29) -> 480000 | O29: 1 | P29: Transferencia Bancaria | R29: =IF(C29="","",IF(COUNTIF($C$2:C29,C29)=1,"Nueva","Recurrente")) -> Nueva | S29: =IF(OR(C29="",J29<>"Paquete"),"",COUNTIFS($C$2:C29,C29,$J$2:J29,"Paquete")) -> 1
A30: I-030 | B30: 46294 | C30: Karen Arias Ospitia | D30: =IF($C30="","",IFERROR(IF(INDEX('🎓 Alumnas'!$C$2:$C$1000,MATCH($C30,'🎓 Alumnas'!$B$2:$B$1000,0))="","",INDEX('🎓 Alumnas'!$C$2:$C$1000,MATCH($C30,'🎓 Alumnas'!$B$2:$B$1000,0))),"")) | E30: =IF($C30="","",IFERROR(IF(INDEX('🎓 Alumnas'!$D$2:$D$1000,MATCH($C30,'🎓 Alumnas'!$B$2:$B$1000,0))="","",INDEX('🎓 Alumnas'!$D$2:$D$1000,MATCH($C30,'🎓 Alumnas'!$B$2:$B$1000,0))),"")) | F30: =IF($C30="","",IFERROR(IF(INDEX('🎓 Alumnas'!$E$2:$E$1000,MATCH($C30,'🎓 Alumnas'!$B$2:$B$1000,0))="","",INDEX('🎓 Alumnas'!$E$2:$E$1000,MATCH($C30,'🎓 Alumnas'!$B$2:$B$1000,0))),"")) | G30: =IF($C30="","",IFERROR(IF(INDEX('🎓 Alumnas'!$F$2:$F$1000,MATCH($C30,'🎓 Alumnas'!$B$2:$B$1000,0))="","",INDEX('🎓 Alumnas'!$F$2:$F$1000,MATCH($C30,'🎓 Alumnas'!$B$2:$B$1000,0))),"")) | H30: =IF(G30="","",DATEDIF(G30,TODAY(),"Y")) | I30: 16 clases : Sport Elite club $480.000 | J30: =IF(I30="","",IF(LEFT(I30,6)="1 Pole","Alquiler",IF(LEFT(I30,7)="1 Clase","Clase suelta","Paquete"))) -> Paquete | K30: Promo 2x1 | L30: 1 | M30: 0 | N30: =IF(M30="","",L30*M30) -> 0 | O30: 0 | R30: =IF(C30="","",IF(COUNTIF($C$2:C30,C30)=1,"Nueva","Recurrente")) -> Nueva | S30: =IF(OR(C30="",J30<>"Paquete"),"",COUNTIFS($C$2:C30,C30,$J$2:J30,"Paquete")) -> 1
A31: I-031 | B31: 46294 | C31: Yendi Alejandra Dugarte | D31: =IF($C31="","",IFERROR(IF(INDEX('🎓 Alumnas'!$C$2:$C$1000,MATCH($C31,'🎓 Alumnas'!$B$2:$B$1000,0))="","",INDEX('🎓 Alumnas'!$C$2:$C$1000,MATCH($C31,'🎓 Alumnas'!$B$2:$B$1000,0))),"")) | E31: =IF($C31="","",IFERROR(IF(INDEX('🎓 Alumnas'!$D$2:$D$1000,MATCH($C31,'🎓 Alumnas'!$B$2:$B$1000,0))="","",INDEX('🎓 Alumnas'!$D$2:$D$1000,MATCH($C31,'🎓 Alumnas'!$B$2:$B$1000,0))),"")) | F31: =IF($C31="","",IFERROR(IF(INDEX('🎓 Alumnas'!$E$2:$E$1000,MATCH($C31,'🎓 Alumnas'!$B$2:$B$1000,0))="","",INDEX('🎓 Alumnas'!$E$2:$E$1000,MATCH($C31,'🎓 Alumnas'!$B$2:$B$1000,0))),"")) | G31: =IF($C31="","",IFERROR(IF(INDEX('🎓 Alumnas'!$F$2:$F$1000,MATCH($C31,'🎓 Alumnas'!$B$2:$B$1000,0))="","",INDEX('🎓 Alumnas'!$F$2:$F$1000,MATCH($C31,'🎓 Alumnas'!$B$2:$B$1000,0))),"")) | H31: =IF(G31="","",DATEDIF(G31,TODAY(),"Y")) | I31: 16 clases : Sport Elite club $480.000 | J31: =IF(I31="","",IF(LEFT(I31,6)="1 Pole","Alquiler",IF(LEFT(I31,7)="1 Clase","Clase suelta","Paquete"))) -> Paquete | K31: Promo 2x1 | L31: 1 | M31: 240000 | N31: =IF(M31="","",L31*M31) -> 240000 | O31: 0.5 | P31: Transferencia Bancaria | R31: =IF(C31="","",IF(COUNTIF($C$2:C31,C31)=1,"Nueva","Recurrente")) -> Nueva | S31: =IF(OR(C31="",J31<>"Paquete"),"",COUNTIFS($C$2:C31,C31,$J$2:J31,"Paquete")) -> 1
A32: I-032 | B32: 46294 | C32: Martha Yasmin Aragón | D32: =IF($C32="","",IFERROR(IF(INDEX('🎓 Alumnas'!$C$2:$C$1000,MATCH($C32,'🎓 Alumnas'!$B$2:$B$1000,0))="","",INDEX('🎓 Alumnas'!$C$2:$C$1000,MATCH($C32,'🎓 Alumnas'!$B$2:$B$1000,0))),"")) | E32: =IF($C32="","",IFERROR(IF(INDEX('🎓 Alumnas'!$D$2:$D$1000,MATCH($C32,'🎓 Alumnas'!$B$2:$B$1000,0))="","",INDEX('🎓 Alumnas'!$D$2:$D$1000,MATCH($C32,'🎓 Alumnas'!$B$2:$B$1000,0))),"")) | F32: =IF($C32="","",IFERROR(IF(INDEX('🎓 Alumnas'!$E$2:$E$1000,MATCH($C32,'🎓 Alumnas'!$B$2:$B$1000,0))="","",INDEX('🎓 Alumnas'!$E$2:$E$1000,MATCH($C32,'🎓 Alumnas'!$B$2:$B$1000,0))),"")) | G32: =IF($C32="","",IFERROR(IF(INDEX('🎓 Alumnas'!$F$2:$F$1000,MATCH($C32,'🎓 Alumnas'!$B$2:$B$1000,0))="","",INDEX('🎓 Alumnas'!$F$2:$F$1000,MATCH($C32,'🎓 Alumnas'!$B$2:$B$1000,0))),"")) | H32: =IF(G32="","",DATEDIF(G32,TODAY(),"Y")) | I32: 1 Clase: Individual $50000 | J32: =IF(I32="","",IF(LEFT(I32,6)="1 Pole","Alquiler",IF(LEFT(I32,7)="1 Clase","Clase suelta","Paquete"))) -> Clase suelta | L32: 1 | M32: 50000 | N32: =IF(M32="","",L32*M32) -> 50000 | O32: 1 | P32: Transferencia Bancaria | R32: =IF(C32="","",IF(COUNTIF($C$2:C32,C32)=1,"Nueva","Recurrente")) -> Nueva | S32: =IF(OR(C32="",J32<>"Paquete"),"",COUNTIFS($C$2:C32,C32,$J$2:J32,"Paquete"))
A33: I-033 | B33: 46295 | C33: Melanie Jankey Ávila | D33: =IF($C33="","",IFERROR(IF(INDEX('🎓 Alumnas'!$C$2:$C$1000,MATCH($C33,'🎓 Alumnas'!$B$2:$B$1000,0))="","",INDEX('🎓 Alumnas'!$C$2:$C$1000,MATCH($C33,'🎓 Alumnas'!$B$2:$B$1000,0))),"")) | E33: =IF($C33="","",IFERROR(IF(INDEX('🎓 Alumnas'!$D$2:$D$1000,MATCH($C33,'🎓 Alumnas'!$B$2:$B$1000,0))="","",INDEX('🎓 Alumnas'!$D$2:$D$1000,MATCH($C33,'🎓 Alumnas'!$B$2:$B$1000,0))),"")) | F33: =IF($C33="","",IFERROR(IF(INDEX('🎓 Alumnas'!$E$2:$E$1000,MATCH($C33,'🎓 Alumnas'!$B$2:$B$1000,0))="","",INDEX('🎓 Alumnas'!$E$2:$E$1000,MATCH($C33,'🎓 Alumnas'!$B$2:$B$1000,0))),"")) | G33: =IF($C33="","",IFERROR(IF(INDEX('🎓 Alumnas'!$F$2:$F$1000,MATCH($C33,'🎓 Alumnas'!$B$2:$B$1000,0))="","",INDEX('🎓 Alumnas'!$F$2:$F$1000,MATCH($C33,'🎓 Alumnas'!$B$2:$B$1000,0))),"")) | H33: =IF(G33="","",DATEDIF(G33,TODAY(),"Y")) | I33: 16 clases : Sport Elite club $480.000 | J33: =IF(I33="","",IF(LEFT(I33,6)="1 Pole","Alquiler",IF(LEFT(I33,7)="1 Clase","Clase suelta","Paquete"))) -> Paquete | K33: Promo 2x1 | L33: 1 | M33: 240000 | N33: =IF(M33="","",L33*M33) -> 240000 | O33: 0.5 | P33: Transferencia Bancaria | R33: =IF(C33="","",IF(COUNTIF($C$2:C33,C33)=1,"Nueva","Recurrente")) -> Nueva | S33: =IF(OR(C33="",J33<>"Paquete"),"",COUNTIFS($C$2:C33,C33,$J$2:J33,"Paquete")) -> 1
A34: I-034 | B34: 46295 | C34: Diana Bermudez Cardona | D34: =IF($C34="","",IFERROR(IF(INDEX('🎓 Alumnas'!$C$2:$C$1000,MATCH($C34,'🎓 Alumnas'!$B$2:$B$1000,0))="","",INDEX('🎓 Alumnas'!$C$2:$C$1000,MATCH($C34,'🎓 Alumnas'!$B$2:$B$1000,0))),"")) -> 3196364084 | E34: =IF($C34="","",IFERROR(IF(INDEX('🎓 Alumnas'!$D$2:$D$1000,MATCH($C34,'🎓 Alumnas'!$B$2:$B$1000,0))="","",INDEX('🎓 Alumnas'!$D$2:$D$1000,MATCH($C34,'🎓 Alumnas'!$B$2:$B$1000,0))),"")) -> diana0.bermudez@gmail.com | F34: =IF($C34="","",IFERROR(IF(INDEX('🎓 Alumnas'!$E$2:$E$1000,MATCH($C34,'🎓 Alumnas'!$B$2:$B$1000,0))="","",INDEX('🎓 Alumnas'!$E$2:$E$1000,MATCH($C34,'🎓 Alumnas'!$B$2:$B$1000,0))),"")) -> Cra 72k # 39a 96 sur | G34: =IF($C34="","",IFERROR(IF(INDEX('🎓 Alumnas'!$F$2:$F$1000,MATCH($C34,'🎓 Alumnas'!$B$2:$B$1000,0))="","",INDEX('🎓 Alumnas'!$F$2:$F$1000,MATCH($C34,'🎓 Alumnas'!$B$2:$B$1000,0))),"")) -> 33374 | H34: =IF(G34="","",DATEDIF(G34,TODAY(),"Y")) -> 35 | I34: 16 clases : Sport Elite club $480.000 | J34: =IF(I34="","",IF(LEFT(I34,6)="1 Pole","Alquiler",IF(LEFT(I34,7)="1 Clase","Clase suelta","Paquete"))) -> Paquete | K34: Promo 2x1 | L34: 1 | M34: 480000 | N34: =IF(M34="","",L34*M34) -> 480000 | O34: 1 | P34: Transferencia Bancaria | Q34: Carolina | R34: =IF(C34="","",IF(COUNTIF($C$2:C34,C34)=1,"Nueva","Recurrente")) -> Recurrente | S34: =IF(OR(C34="",J34<>"Paquete"),"",COUNTIFS($C$2:C34,C34,$J$2:J34,"Paquete")) -> 2
A35: I-035 | B35: 46295 | C35: Jessica Torres Olarte | D35: =IF($C35="","",IFERROR(IF(INDEX('🎓 Alumnas'!$C$2:$C$1000,MATCH($C35,'🎓 Alumnas'!$B$2:$B$1000,0))="","",INDEX('🎓 Alumnas'!$C$2:$C$1000,MATCH($C35,'🎓 Alumnas'!$B$2:$B$1000,0))),"")) -> 3104775381 | E35: =IF($C35="","",IFERROR(IF(INDEX('🎓 Alumnas'!$D$2:$D$1000,MATCH($C35,'🎓 Alumnas'!$B$2:$B$1000,0))="","",INDEX('🎓 Alumnas'!$D$2:$D$1000,MATCH($C35,'🎓 Alumnas'!$B$2:$B$1000,0))),"")) -> Jessicatorresolarte@gmail.com | F35: =IF($C35="","",IFERROR(IF(INDEX('🎓 Alumnas'!$E$2:$E$1000,MATCH($C35,'🎓 Alumnas'!$B$2:$B$1000,0))="","",INDEX('🎓 Alumnas'!$E$2:$E$1000,MATCH($C35,'🎓 Alumnas'!$B$2:$B$1000,0))),"")) -> Calle 6b 80b 85 | G35: =IF($C35="","",IFERROR(IF(INDEX('🎓 Alumnas'!$F$2:$F$1000,MATCH($C35,'🎓 Alumnas'!$B$2:$B$1000,0))="","",INDEX('🎓 Alumnas'!$F$2:$F$1000,MATCH($C35,'🎓 Alumnas'!$B$2:$B$1000,0))),"")) -> 31592 | H35: =IF(G35="","",DATEDIF(G35,TODAY(),"Y")) -> 40 | I35: 16 clases : Sport Elite club $480.000 | J35: =IF(I35="","",IF(LEFT(I35,6)="1 Pole","Alquiler",IF(LEFT(I35,7)="1 Clase","Clase suelta","Paquete"))) -> Paquete | K35: Promo 2x1 | L35: 1 | M35: 0 | N35: =IF(M35="","",L35*M35) -> 0 | O35: 0 | R35: =IF(C35="","",IF(COUNTIF($C$2:C35,C35)=1,"Nueva","Recurrente")) -> Recurrente | S35: =IF(OR(C35="",J35<>"Paquete"),"",COUNTIFS($C$2:C35,C35,$J$2:J35,"Paquete")) -> 2
A36: I-036 | B36: 46295 | C36: Martha Yasmin Aragón | D36: =IF($C36="","",IFERROR(IF(INDEX('🎓 Alumnas'!$C$2:$C$1000,MATCH($C36,'🎓 Alumnas'!$B$2:$B$1000,0))="","",INDEX('🎓 Alumnas'!$C$2:$C$1000,MATCH($C36,'🎓 Alumnas'!$B$2:$B$1000,0))),"")) | E36: =IF($C36="","",IFERROR(IF(INDEX('🎓 Alumnas'!$D$2:$D$1000,MATCH($C36,'🎓 Alumnas'!$B$2:$B$1000,0))="","",INDEX('🎓 Alumnas'!$D$2:$D$1000,MATCH($C36,'🎓 Alumnas'!$B$2:$B$1000,0))),"")) | F36: =IF($C36="","",IFERROR(IF(INDEX('🎓 Alumnas'!$E$2:$E$1000,MATCH($C36,'🎓 Alumnas'!$B$2:$B$1000,0))="","",INDEX('🎓 Alumnas'!$E$2:$E$1000,MATCH($C36,'🎓 Alumnas'!$B$2:$B$1000,0))),"")) | G36: =IF($C36="","",IFERROR(IF(INDEX('🎓 Alumnas'!$F$2:$F$1000,MATCH($C36,'🎓 Alumnas'!$B$2:$B$1000,0))="","",INDEX('🎓 Alumnas'!$F$2:$F$1000,MATCH($C36,'🎓 Alumnas'!$B$2:$B$1000,0))),"")) | H36: =IF(G36="","",DATEDIF(G36,TODAY(),"Y")) | I36: 16 clases : Sport Elite club $480.000 | J36: =IF(I36="","",IF(LEFT(I36,6)="1 Pole","Alquiler",IF(LEFT(I36,7)="1 Clase","Clase suelta","Paquete"))) -> Paquete | K36: Promo 2x1 | L36: 1 | M36: 240000 | N36: =IF(M36="","",L36*M36) -> 240000 | O36: 0.5 | P36: Transferencia Bancaria | R36: =IF(C36="","",IF(COUNTIF($C$2:C36,C36)=1,"Nueva","Recurrente")) -> Recurrente | S36: =IF(OR(C36="",J36<>"Paquete"),"",COUNTIFS($C$2:C36,C36,$J$2:J36,"Paquete")) -> 1
A37: I-037 | B37: 46295 | C37: Shirley Dayana Chavarro | D37: =IF($C37="","",IFERROR(IF(INDEX('🎓 Alumnas'!$C$2:$C$1000,MATCH($C37,'🎓 Alumnas'!$B$2:$B$1000,0))="","",INDEX('🎓 Alumnas'!$C$2:$C$1000,MATCH($C37,'🎓 Alumnas'!$B$2:$B$1000,0))),"")) -> 3115269836 | E37: =IF($C37="","",IFERROR(IF(INDEX('🎓 Alumnas'!$D$2:$D$1000,MATCH($C37,'🎓 Alumnas'!$B$2:$B$1000,0))="","",INDEX('🎓 Alumnas'!$D$2:$D$1000,MATCH($C37,'🎓 Alumnas'!$B$2:$B$1000,0))),"")) | F37: =IF($C37="","",IFERROR(IF(INDEX('🎓 Alumnas'!$E$2:$E$1000,MATCH($C37,'🎓 Alumnas'!$B$2:$B$1000,0))="","",INDEX('🎓 Alumnas'!$E$2:$E$1000,MATCH($C37,'🎓 Alumnas'!$B$2:$B$1000,0))),"")) | G37: =IF($C37="","",IFERROR(IF(INDEX('🎓 Alumnas'!$F$2:$F$1000,MATCH($C37,'🎓 Alumnas'!$B$2:$B$1000,0))="","",INDEX('🎓 Alumnas'!$F$2:$F$1000,MATCH($C37,'🎓 Alumnas'!$B$2:$B$1000,0))),"")) | H37: =IF(G37="","",DATEDIF(G37,TODAY(),"Y")) | I37: 16 clases : Sport Elite club $480.000 | J37: =IF(I37="","",IF(LEFT(I37,6)="1 Pole","Alquiler",IF(LEFT(I37,7)="1 Clase","Clase suelta","Paquete"))) -> Paquete | K37: Promo 2x1 | L37: 1 | M37: 240000 | N37: =IF(M37="","",L37*M37) -> 240000 | O37: 0.5 | P37: Transferencia Bancaria | R37: =IF(C37="","",IF(COUNTIF($C$2:C37,C37)=1,"Nueva","Recurrente")) -> Recurrente | S37: =IF(OR(C37="",J37<>"Paquete"),"",COUNTIFS($C$2:C37,C37,$J$2:J37,"Paquete")) -> 2
A38: I-038 | B38: 46295 | C38: Laura Vanesa Guerra | D38: =IF($C38="","",IFERROR(IF(INDEX('🎓 Alumnas'!$C$2:$C$1000,MATCH($C38,'🎓 Alumnas'!$B$2:$B$1000,0))="","",INDEX('🎓 Alumnas'!$C$2:$C$1000,MATCH($C38,'🎓 Alumnas'!$B$2:$B$1000,0))),"")) | E38: =IF($C38="","",IFERROR(IF(INDEX('🎓 Alumnas'!$D$2:$D$1000,MATCH($C38,'🎓 Alumnas'!$B$2:$B$1000,0))="","",INDEX('🎓 Alumnas'!$D$2:$D$1000,MATCH($C38,'🎓 Alumnas'!$B$2:$B$1000,0))),"")) | F38: =IF($C38="","",IFERROR(IF(INDEX('🎓 Alumnas'!$E$2:$E$1000,MATCH($C38,'🎓 Alumnas'!$B$2:$B$1000,0))="","",INDEX('🎓 Alumnas'!$E$2:$E$1000,MATCH($C38,'🎓 Alumnas'!$B$2:$B$1000,0))),"")) | G38: =IF($C38="","",IFERROR(IF(INDEX('🎓 Alumnas'!$F$2:$F$1000,MATCH($C38,'🎓 Alumnas'!$B$2:$B$1000,0))="","",INDEX('🎓 Alumnas'!$F$2:$F$1000,MATCH($C38,'🎓 Alumnas'!$B$2:$B$1000,0))),"")) | H38: =IF(G38="","",DATEDIF(G38,TODAY(),"Y")) | I38: 16 clases : Sport Elite club $480.000 | J38: =IF(I38="","",IF(LEFT(I38,6)="1 Pole","Alquiler",IF(LEFT(I38,7)="1 Clase","Clase suelta","Paquete"))) -> Paquete | K38: Promo 2x1 | L38: 1 | M38: 240000 | N38: =IF(M38="","",L38*M38) -> 240000 | O38: 0.5 | P38: Daviplata | R38: =IF(C38="","",IF(COUNTIF($C$2:C38,C38)=1,"Nueva","Recurrente")) -> Recurrente | S38: =IF(OR(C38="",J38<>"Paquete"),"",COUNTIFS($C$2:C38,C38,$J$2:J38,"Paquete")) -> 2
A39: I-039 | B39: 46295 | C39: Mary Aurora Osorio Alvarez | D39: =IF($C39="","",IFERROR(IF(INDEX('🎓 Alumnas'!$C$2:$C$1000,MATCH($C39,'🎓 Alumnas'!$B$2:$B$1000,0))="","",INDEX('🎓 Alumnas'!$C$2:$C$1000,MATCH($C39,'🎓 Alumnas'!$B$2:$B$1000,0))),"")) -> 3186650375 | E39: =IF($C39="","",IFERROR(IF(INDEX('🎓 Alumnas'!$D$2:$D$1000,MATCH($C39,'🎓 Alumnas'!$B$2:$B$1000,0))="","",INDEX('🎓 Alumnas'!$D$2:$D$1000,MATCH($C39,'🎓 Alumnas'!$B$2:$B$1000,0))),"")) | F39: =IF($C39="","",IFERROR(IF(INDEX('🎓 Alumnas'!$E$2:$E$1000,MATCH($C39,'🎓 Alumnas'!$B$2:$B$1000,0))="","",INDEX('🎓 Alumnas'!$E$2:$E$1000,MATCH($C39,'🎓 Alumnas'!$B$2:$B$1000,0))),"")) | G39: =IF($C39="","",IFERROR(IF(INDEX('🎓 Alumnas'!$F$2:$F$1000,MATCH($C39,'🎓 Alumnas'!$B$2:$B$1000,0))="","",INDEX('🎓 Alumnas'!$F$2:$F$1000,MATCH($C39,'🎓 Alumnas'!$B$2:$B$1000,0))),"")) | H39: =IF(G39="","",DATEDIF(G39,TODAY(),"Y")) | I39: 16 clases : Sport Elite club $480.000 | J39: =IF(I39="","",IF(LEFT(I39,6)="1 Pole","Alquiler",IF(LEFT(I39,7)="1 Clase","Clase suelta","Paquete"))) -> Paquete | K39: Promo 2x1 | L39: 1 | M39: 240000 | N39: =IF(M39="","",L39*M39) -> 240000 | O39: 0.5 | P39: Nequi | R39: =IF(C39="","",IF(COUNTIF($C$2:C39,C39)=1,"Nueva","Recurrente")) -> Recurrente | S39: =IF(OR(C39="",J39<>"Paquete"),"",COUNTIFS($C$2:C39,C39,$J$2:J39,"Paquete")) -> 1
A40: I-040 | B40: 46295 | C40: Maira Alejandra Vergara | D40: =IF($C40="","",IFERROR(IF(INDEX('🎓 Alumnas'!$C$2:$C$1000,MATCH($C40,'🎓 Alumnas'!$B$2:$B$1000,0))="","",INDEX('🎓 Alumnas'!$C$2:$C$1000,MATCH($C40,'🎓 Alumnas'!$B$2:$B$1000,0))),"")) | E40: =IF($C40="","",IFERROR(IF(INDEX('🎓 Alumnas'!$D$2:$D$1000,MATCH($C40,'🎓 Alumnas'!$B$2:$B$1000,0))="","",INDEX('🎓 Alumnas'!$D$2:$D$1000,MATCH($C40,'🎓 Alumnas'!$B$2:$B$1000,0))),"")) | F40: =IF($C40="","",IFERROR(IF(INDEX('🎓 Alumnas'!$E$2:$E$1000,MATCH($C40,'🎓 Alumnas'!$B$2:$B$1000,0))="","",INDEX('🎓 Alumnas'!$E$2:$E$1000,MATCH($C40,'🎓 Alumnas'!$B$2:$B$1000,0))),"")) | G40: =IF($C40="","",IFERROR(IF(INDEX('🎓 Alumnas'!$F$2:$F$1000,MATCH($C40,'🎓 Alumnas'!$B$2:$B$1000,0))="","",INDEX('🎓 Alumnas'!$F$2:$F$1000,MATCH($C40,'🎓 Alumnas'!$B$2:$B$1000,0))),"")) | H40: =IF(G40="","",DATEDIF(G40,TODAY(),"Y")) | I40: 16 clases : Sport Elite club $480.000 | J40: =IF(I40="","",IF(LEFT(I40,6)="1 Pole","Alquiler",IF(LEFT(I40,7)="1 Clase","Clase suelta","Paquete"))) -> Paquete | K40: Promo 2x1 | L40: 1 | M40: 240000 | N40: =IF(M40="","",L40*M40) -> 240000 | O40: 0.5 | P40: Transferencia Bancaria | R40: =IF(C40="","",IF(COUNTIF($C$2:C40,C40)=1,"Nueva","Recurrente")) -> Recurrente | S40: =IF(OR(C40="",J40<>"Paquete"),"",COUNTIFS($C$2:C40,C40,$J$2:J40,"Paquete")) -> 2
A41: I-041 | B41: 46295 | C41: Karol Sierra | D41: =IF($C41="","",IFERROR(IF(INDEX('🎓 Alumnas'!$C$2:$C$1000,MATCH($C41,'🎓 Alumnas'!$B$2:$B$1000,0))="","",INDEX('🎓 Alumnas'!$C$2:$C$1000,MATCH($C41,'🎓 Alumnas'!$B$2:$B$1000,0))),"")) | E41: =IF($C41="","",IFERROR(IF(INDEX('🎓 Alumnas'!$D$2:$D$1000,MATCH($C41,'🎓 Alumnas'!$B$2:$B$1000,0))="","",INDEX('🎓 Alumnas'!$D$2:$D$1000,MATCH($C41,'🎓 Alumnas'!$B$2:$B$1000,0))),"")) | F41: =IF($C41="","",IFERROR(IF(INDEX('🎓 Alumnas'!$E$2:$E$1000,MATCH($C41,'🎓 Alumnas'!$B$2:$B$1000,0))="","",INDEX('🎓 Alumnas'!$E$2:$E$1000,MATCH($C41,'🎓 Alumnas'!$B$2:$B$1000,0))),"")) | G41: =IF($C41="","",IFERROR(IF(INDEX('🎓 Alumnas'!$F$2:$F$1000,MATCH($C41,'🎓 Alumnas'!$B$2:$B$1000,0))="","",INDEX('🎓 Alumnas'!$F$2:$F$1000,MATCH($C41,'🎓 Alumnas'!$B$2:$B$1000,0))),"")) | H41: =IF(G41="","",DATEDIF(G41,TODAY(),"Y")) | I41: 1 Pole: Alquiler $22000 | J41: =IF(I41="","",IF(LEFT(I41,6)="1 Pole","Alquiler",IF(LEFT(I41,7)="1 Clase","Clase suelta","Paquete"))) -> Alquiler | L41: 2 | M41: 22000 | N41: =IF(M41="","",L41*M41) -> 44000 | O41: 1 | P41: Transferencia Bancaria | R41: =IF(C41="","",IF(COUNTIF($C$2:C41,C41)=1,"Nueva","Recurrente")) -> Recurrente | S41: =IF(OR(C41="",J41<>"Paquete"),"",COUNTIFS($C$2:C41,C41,$J$2:J41,"Paquete"))
A42: I-042 | D42: =IF($C42="","",IFERROR(IF(INDEX('🎓 Alumnas'!$C$2:$C$1000,MATCH($C42,'🎓 Alumnas'!$B$2:$B$1000,0))="","",INDEX('🎓 Alumnas'!$C$2:$C$1000,MATCH($C42,'🎓 Alumnas'!$B$2:$B$1000,0))),"")) | E42: =IF($C42="","",IFERROR(IF(INDEX('🎓 Alumnas'!$D$2:$D$1000,MATCH($C42,'🎓 Alumnas'!$B$2:$B$1000,0))="","",INDEX('🎓 Alumnas'!$D$2:$D$1000,MATCH($C42,'🎓 Alumnas'!$B$2:$B$1000,0))),"")) | F42: =IF($C42="","",IFERROR(IF(INDEX('🎓 Alumnas'!$E$2:$E$1000,MATCH($C42,'🎓 Alumnas'!$B$2:$B$1000,0))="","",INDEX('🎓 Alumnas'!$E$2:$E$1000,MATCH($C42,'🎓 Alumnas'!$B$2:$B$1000,0))),"")) | G42: =IF($C42="","",IFERROR(IF(INDEX('🎓 Alumnas'!$F$2:$F$1000,MATCH($C42,'🎓 Alumnas'!$B$2:$B$1000,0))="","",INDEX('🎓 Alumnas'!$F$2:$F$1000,MATCH($C42,'🎓 Alumnas'!$B$2:$B$1000,0))),"")) | H42: =IF(G42="","",DATEDIF(G42,TODAY(),"Y")) | J42: =IF(I42="","",IF(LEFT(I42,6)="1 Pole","Alquiler",IF(LEFT(I42,7)="1 Clase","Clase suelta","Paquete"))) | N42: =IF(M42="","",L42*M42) | R42: =IF(C42="","",IF(COUNTIF($C$2:C42,C42)=1,"Nueva","Recurrente")) | S42: =IF(OR(C42="",J42<>"Paquete"),"",COUNTIFS($C$2:C42,C42,$J$2:J42,"Paquete"))
A43: I-043 | D43: =IF($C43="","",IFERROR(IF(INDEX('🎓 Alumnas'!$C$2:$C$1000,MATCH($C43,'🎓 Alumnas'!$B$2:$B$1000,0))="","",INDEX('🎓 Alumnas'!$C$2:$C$1000,MATCH($C43,'🎓 Alumnas'!$B$2:$B$1000,0))),"")) | E43: =IF($C43="","",IFERROR(IF(INDEX('🎓 Alumnas'!$D$2:$D$1000,MATCH($C43,'🎓 Alumnas'!$B$2:$B$1000,0))="","",INDEX('🎓 Alumnas'!$D$2:$D$1000,MATCH($C43,'🎓 Alumnas'!$B$2:$B$1000,0))),"")) | F43: =IF($C43="","",IFERROR(IF(INDEX('🎓 Alumnas'!$E$2:$E$1000,MATCH($C43,'🎓 Alumnas'!$B$2:$B$1000,0))="","",INDEX('🎓 Alumnas'!$E$2:$E$1000,MATCH($C43,'🎓 Alumnas'!$B$2:$B$1000,0))),"")) | G43: =IF($C43="","",IFERROR(IF(INDEX('🎓 Alumnas'!$F$2:$F$1000,MATCH($C43,'🎓 Alumnas'!$B$2:$B$1000,0))="","",INDEX('🎓 Alumnas'!$F$2:$F$1000,MATCH($C43,'🎓 Alumnas'!$B$2:$B$1000,0))),"")) | H43: =IF(G43="","",DATEDIF(G43,TODAY(),"Y")) | J43: =IF(I43="","",IF(LEFT(I43,6)="1 Pole","Alquiler",IF(LEFT(I43,7)="1 Clase","Clase suelta","Paquete"))) | N43: =IF(M43="","",L43*M43) | R43: =IF(C43="","",IF(COUNTIF($C$2:C43,C43)=1,"Nueva","Recurrente")) | S43: =IF(OR(C43="",J43<>"Paquete"),"",COUNTIFS($C$2:C43,C43,$J$2:J43,"Paquete"))
A44: I-044 | D44: =IF($C44="","",IFERROR(IF(INDEX('🎓 Alumnas'!$C$2:$C$1000,MATCH($C44,'🎓 Alumnas'!$B$2:$B$1000,0))="","",INDEX('🎓 Alumnas'!$C$2:$C$1000,MATCH($C44,'🎓 Alumnas'!$B$2:$B$1000,0))),"")) | E44: =IF($C44="","",IFERROR(IF(INDEX('🎓 Alumnas'!$D$2:$D$1000,MATCH($C44,'🎓 Alumnas'!$B$2:$B$1000,0))="","",INDEX('🎓 Alumnas'!$D$2:$D$1000,MATCH($C44,'🎓 Alumnas'!$B$2:$B$1000,0))),"")) | F44: =IF($C44="","",IFERROR(IF(INDEX('🎓 Alumnas'!$E$2:$E$1000,MATCH($C44,'🎓 Alumnas'!$B$2:$B$1000,0))="","",INDEX('🎓 Alumnas'!$E$2:$E$1000,MATCH($C44,'🎓 Alumnas'!$B$2:$B$1000,0))),"")) | G44: =IF($C44="","",IFERROR(IF(INDEX('🎓 Alumnas'!$F$2:$F$1000,MATCH($C44,'🎓 Alumnas'!$B$2:$B$1000,0))="","",INDEX('🎓 Alumnas'!$F$2:$F$1000,MATCH($C44,'🎓 Alumnas'!$B$2:$B$1000,0))),"")) | H44: =IF(G44="","",DATEDIF(G44,TODAY(),"Y")) | J44: =IF(I44="","",IF(LEFT(I44,6)="1 Pole","Alquiler",IF(LEFT(I44,7)="1 Clase","Clase suelta","Paquete"))) | N44: =IF(M44="","",L44*M44) | R44: =IF(C44="","",IF(COUNTIF($C$2:C44,C44)=1,"Nueva","Recurrente")) | S44: =IF(OR(C44="",J44<>"Paquete"),"",COUNTIFS($C$2:C44,C44,$J$2:J44,"Paquete"))
A45: I-045 | D45: =IF($C45="","",IFERROR(IF(INDEX('🎓 Alumnas'!$C$2:$C$1000,MATCH($C45,'🎓 Alumnas'!$B$2:$B$1000,0))="","",INDEX('🎓 Alumnas'!$C$2:$C$1000,MATCH($C45,'🎓 Alumnas'!$B$2:$B$1000,0))),"")) | E45: =IF($C45="","",IFERROR(IF(INDEX('🎓 Alumnas'!$D$2:$D$1000,MATCH($C45,'🎓 Alumnas'!$B$2:$B$1000,0))="","",INDEX('🎓 Alumnas'!$D$2:$D$1000,MATCH($C45,'🎓 Alumnas'!$B$2:$B$1000,0))),"")) | F45: =IF($C45="","",IFERROR(IF(INDEX('🎓 Alumnas'!$E$2:$E$1000,MATCH($C45,'🎓 Alumnas'!$B$2:$B$1000,0))="","",INDEX('🎓 Alumnas'!$E$2:$E$1000,MATCH($C45,'🎓 Alumnas'!$B$2:$B$1000,0))),"")) | G45: =IF($C45="","",IFERROR(IF(INDEX('🎓 Alumnas'!$F$2:$F$1000,MATCH($C45,'🎓 Alumnas'!$B$2:$B$1000,0))="","",INDEX('🎓 Alumnas'!$F$2:$F$1000,MATCH($C45,'🎓 Alumnas'!$B$2:$B$1000,0))),"")) | H45: =IF(G45="","",DATEDIF(G45,TODAY(),"Y")) | J45: =IF(I45="","",IF(LEFT(I45,6)="1 Pole","Alquiler",IF(LEFT(I45,7)="1 Clase","Clase suelta","Paquete"))) | N45: =IF(M45="","",L45*M45) | R45: =IF(C45="","",IF(COUNTIF($C$2:C45,C45)=1,"Nueva","Recurrente")) | S45: =IF(OR(C45="",J45<>"Paquete"),"",COUNTIFS($C$2:C45,C45,$J$2:J45,"Paquete"))
A46: I-046 | D46: =IF($C46="","",IFERROR(IF(INDEX('🎓 Alumnas'!$C$2:$C$1000,MATCH($C46,'🎓 Alumnas'!$B$2:$B$1000,0))="","",INDEX('🎓 Alumnas'!$C$2:$C$1000,MATCH($C46,'🎓 Alumnas'!$B$2:$B$1000,0))),"")) | E46: =IF($C46="","",IFERROR(IF(INDEX('🎓 Alumnas'!$D$2:$D$1000,MATCH($C46,'🎓 Alumnas'!$B$2:$B$1000,0))="","",INDEX('🎓 Alumnas'!$D$2:$D$1000,MATCH($C46,'🎓 Alumnas'!$B$2:$B$1000,0))),"")) | F46: =IF($C46="","",IFERROR(IF(INDEX('🎓 Alumnas'!$E$2:$E$1000,MATCH($C46,'🎓 Alumnas'!$B$2:$B$1000,0))="","",INDEX('🎓 Alumnas'!$E$2:$E$1000,MATCH($C46,'🎓 Alumnas'!$B$2:$B$1000,0))),"")) | G46: =IF($C46="","",IFERROR(IF(INDEX('🎓 Alumnas'!$F$2:$F$1000,MATCH($C46,'🎓 Alumnas'!$B$2:$B$1000,0))="","",INDEX('🎓 Alumnas'!$F$2:$F$1000,MATCH($C46,'🎓 Alumnas'!$B$2:$B$1000,0))),"")) | H46: =IF(G46="","",DATEDIF(G46,TODAY(),"Y")) | J46: =IF(I46="","",IF(LEFT(I46,6)="1 Pole","Alquiler",IF(LEFT(I46,7)="1 Clase","Clase suelta","Paquete"))) | N46: =IF(M46="","",L46*M46) | R46: =IF(C46="","",IF(COUNTIF($C$2:C46,C46)=1,"Nueva","Recurrente")) | S46: =IF(OR(C46="",J46<>"Paquete"),"",COUNTIFS($C$2:C46,C46,$J$2:J46,"Paquete"))
A47: I-047 | D47: =IF($C47="","",IFERROR(IF(INDEX('🎓 Alumnas'!$C$2:$C$1000,MATCH($C47,'🎓 Alumnas'!$B$2:$B$1000,0))="","",INDEX('🎓 Alumnas'!$C$2:$C$1000,MATCH($C47,'🎓 Alumnas'!$B$2:$B$1000,0))),"")) | E47: =IF($C47="","",IFERROR(IF(INDEX('🎓 Alumnas'!$D$2:$D$1000,MATCH($C47,'🎓 Alumnas'!$B$2:$B$1000,0))="","",INDEX('🎓 Alumnas'!$D$2:$D$1000,MATCH($C47,'🎓 Alumnas'!$B$2:$B$1000,0))),"")) | F47: =IF($C47="","",IFERROR(IF(INDEX('🎓 Alumnas'!$E$2:$E$1000,MATCH($C47,'🎓 Alumnas'!$B$2:$B$1000,0))="","",INDEX('🎓 Alumnas'!$E$2:$E$1000,MATCH($C47,'🎓 Alumnas'!$B$2:$B$1000,0))),"")) | G47: =IF($C47="","",IFERROR(IF(INDEX('🎓 Alumnas'!$F$2:$F$1000,MATCH($C47,'🎓 Alumnas'!$B$2:$B$1000,0))="","",INDEX('🎓 Alumnas'!$F$2:$F$1000,MATCH($C47,'🎓 Alumnas'!$B$2:$B$1000,0))),"")) | H47: =IF(G47="","",DATEDIF(G47,TODAY(),"Y")) | J47: =IF(I47="","",IF(LEFT(I47,6)="1 Pole","Alquiler",IF(LEFT(I47,7)="1 Clase","Clase suelta","Paquete"))) | N47: =IF(M47="","",L47*M47) | R47: =IF(C47="","",IF(COUNTIF($C$2:C47,C47)=1,"Nueva","Recurrente")) | S47: =IF(OR(C47="",J47<>"Paquete"),"",COUNTIFS($C$2:C47,C47,$J$2:J47,"Paquete"))
A48: I-048 | D48: =IF($C48="","",IFERROR(IF(INDEX('🎓 Alumnas'!$C$2:$C$1000,MATCH($C48,'🎓 Alumnas'!$B$2:$B$1000,0))="","",INDEX('🎓 Alumnas'!$C$2:$C$1000,MATCH($C48,'🎓 Alumnas'!$B$2:$B$1000,0))),"")) | E48: =IF($C48="","",IFERROR(IF(INDEX('🎓 Alumnas'!$D$2:$D$1000,MATCH($C48,'🎓 Alumnas'!$B$2:$B$1000,0))="","",INDEX('🎓 Alumnas'!$D$2:$D$1000,MATCH($C48,'🎓 Alumnas'!$B$2:$B$1000,0))),"")) | F48: =IF($C48="","",IFERROR(IF(INDEX('🎓 Alumnas'!$E$2:$E$1000,MATCH($C48,'🎓 Alumnas'!$B$2:$B$1000,0))="","",INDEX('🎓 Alumnas'!$E$2:$E$1000,MATCH($C48,'🎓 Alumnas'!$B$2:$B$1000,0))),"")) | G48: =IF($C48="","",IFERROR(IF(INDEX('🎓 Alumnas'!$F$2:$F$1000,MATCH($C48,'🎓 Alumnas'!$B$2:$B$1000,0))="","",INDEX('🎓 Alumnas'!$F$2:$F$1000,MATCH($C48,'🎓 Alumnas'!$B$2:$B$1000,0))),"")) | H48: =IF(G48="","",DATEDIF(G48,TODAY(),"Y")) | J48: =IF(I48="","",IF(LEFT(I48,6)="1 Pole","Alquiler",IF(LEFT(I48,7)="1 Clase","Clase suelta","Paquete"))) | N48: =IF(M48="","",L48*M48) | R48: =IF(C48="","",IF(COUNTIF($C$2:C48,C48)=1,"Nueva","Recurrente")) | S48: =IF(OR(C48="",J48<>"Paquete"),"",COUNTIFS($C$2:C48,C48,$J$2:J48,"Paquete"))
A49: I-049 | D49: =IF($C49="","",IFERROR(IF(INDEX('🎓 Alumnas'!$C$2:$C$1000,MATCH($C49,'🎓 Alumnas'!$B$2:$B$1000,0))="","",INDEX('🎓 Alumnas'!$C$2:$C$1000,MATCH($C49,'🎓 Alumnas'!$B$2:$B$1000,0))),"")) | E49: =IF($C49="","",IFERROR(IF(INDEX('🎓 Alumnas'!$D$2:$D$1000,MATCH($C49,'🎓 Alumnas'!$B$2:$B$1000,0))="","",INDEX('🎓 Alumnas'!$D$2:$D$1000,MATCH($C49,'🎓 Alumnas'!$B$2:$B$1000,0))),"")) | F49: =IF($C49="","",IFERROR(IF(INDEX('🎓 Alumnas'!$E$2:$E$1000,MATCH($C49,'🎓 Alumnas'!$B$2:$B$1000,0))="","",INDEX('🎓 Alumnas'!$E$2:$E$1000,MATCH($C49,'🎓 Alumnas'!$B$2:$B$1000,0))),"")) | G49: =IF($C49="","",IFERROR(IF(INDEX('🎓 Alumnas'!$F$2:$F$1000,MATCH($C49,'🎓 Alumnas'!$B$2:$B$1000,0))="","",INDEX('🎓 Alumnas'!$F$2:$F$1000,MATCH($C49,'🎓 Alumnas'!$B$2:$B$1000,0))),"")) | H49: =IF(G49="","",DATEDIF(G49,TODAY(),"Y")) | J49: =IF(I49="","",IF(LEFT(I49,6)="1 Pole","Alquiler",IF(LEFT(I49,7)="1 Clase","Clase suelta","Paquete"))) | N49: =IF(M49="","",L49*M49) | R49: =IF(C49="","",IF(COUNTIF($C$2:C49,C49)=1,"Nueva","Recurrente")) | S49: =IF(OR(C49="",J49<>"Paquete"),"",COUNTIFS($C$2:C49,C49,$J$2:J49,"Paquete"))
A50: I-050 | D50: =IF($C50="","",IFERROR(IF(INDEX('🎓 Alumnas'!$C$2:$C$1000,MATCH($C50,'🎓 Alumnas'!$B$2:$B$1000,0))="","",INDEX('🎓 Alumnas'!$C$2:$C$1000,MATCH($C50,'🎓 Alumnas'!$B$2:$B$1000,0))),"")) | E50: =IF($C50="","",IFERROR(IF(INDEX('🎓 Alumnas'!$D$2:$D$1000,MATCH($C50,'🎓 Alumnas'!$B$2:$B$1000,0))="","",INDEX('🎓 Alumnas'!$D$2:$D$1000,MATCH($C50,'🎓 Alumnas'!$B$2:$B$1000,0))),"")) | F50: =IF($C50="","",IFERROR(IF(INDEX('🎓 Alumnas'!$E$2:$E$1000,MATCH($C50,'🎓 Alumnas'!$B$2:$B$1000,0))="","",INDEX('🎓 Alumnas'!$E$2:$E$1000,MATCH($C50,'🎓 Alumnas'!$B$2:$B$1000,0))),"")) | G50: =IF($C50="","",IFERROR(IF(INDEX('🎓 Alumnas'!$F$2:$F$1000,MATCH($C50,'🎓 Alumnas'!$B$2:$B$1000,0))="","",INDEX('🎓 Alumnas'!$F$2:$F$1000,MATCH($C50,'🎓 Alumnas'!$B$2:$B$1000,0))),"")) | H50: =IF(G50="","",DATEDIF(G50,TODAY(),"Y")) | J50: =IF(I50="","",IF(LEFT(I50,6)="1 Pole","Alquiler",IF(LEFT(I50,7)="1 Clase","Clase suelta","Paquete"))) | N50: =IF(M50="","",L50*M50) | R50: =IF(C50="","",IF(COUNTIF($C$2:C50,C50)=1,"Nueva","Recurrente")) | S50: =IF(OR(C50="",J50<>"Paquete"),"",COUNTIFS($C$2:C50,C50,$J$2:J50,"Paquete"))
A51: I-051 | D51: =IF($C51="","",IFERROR(IF(INDEX('🎓 Alumnas'!$C$2:$C$1000,MATCH($C51,'🎓 Alumnas'!$B$2:$B$1000,0))="","",INDEX('🎓 Alumnas'!$C$2:$C$1000,MATCH($C51,'🎓 Alumnas'!$B$2:$B$1000,0))),"")) | E51: =IF($C51="","",IFERROR(IF(INDEX('🎓 Alumnas'!$D$2:$D$1000,MATCH($C51,'🎓 Alumnas'!$B$2:$B$1000,0))="","",INDEX('🎓 Alumnas'!$D$2:$D$1000,MATCH($C51,'🎓 Alumnas'!$B$2:$B$1000,0))),"")) | F51: =IF($C51="","",IFERROR(IF(INDEX('🎓 Alumnas'!$E$2:$E$1000,MATCH($C51,'🎓 Alumnas'!$B$2:$B$1000,0))="","",INDEX('🎓 Alumnas'!$E$2:$E$1000,MATCH($C51,'🎓 Alumnas'!$B$2:$B$1000,0))),"")) | G51: =IF($C51="","",IFERROR(IF(INDEX('🎓 Alumnas'!$F$2:$F$1000,MATCH($C51,'🎓 Alumnas'!$B$2:$B$1000,0))="","",INDEX('🎓 Alumnas'!$F$2:$F$1000,MATCH($C51,'🎓 Alumnas'!$B$2:$B$1000,0))),"")) | H51: =IF(G51="","",DATEDIF(G51,TODAY(),"Y")) | J51: =IF(I51="","",IF(LEFT(I51,6)="1 Pole","Alquiler",IF(LEFT(I51,7)="1 Clase","Clase suelta","Paquete"))) | N51: =IF(M51="","",L51*M51) | R51: =IF(C51="","",IF(COUNTIF($C$2:C51,C51)=1,"Nueva","Recurrente")) | S51: =IF(OR(C51="",J51<>"Paquete"),"",COUNTIFS($C$2:C51,C51,$J$2:J51,"Paquete"))
A52: I-052 | D52: =IF($C52="","",IFERROR(IF(INDEX('🎓 Alumnas'!$C$2:$C$1000,MATCH($C52,'🎓 Alumnas'!$B$2:$B$1000,0))="","",INDEX('🎓 Alumnas'!$C$2:$C$1000,MATCH($C52,'🎓 Alumnas'!$B$2:$B$1000,0))),"")) | E52: =IF($C52="","",IFERROR(IF(INDEX('🎓 Alumnas'!$D$2:$D$1000,MATCH($C52,'🎓 Alumnas'!$B$2:$B$1000,0))="","",INDEX('🎓 Alumnas'!$D$2:$D$1000,MATCH($C52,'🎓 Alumnas'!$B$2:$B$1000,0))),"")) | F52: =IF($C52="","",IFERROR(IF(INDEX('🎓 Alumnas'!$E$2:$E$1000,MATCH($C52,'🎓 Alumnas'!$B$2:$B$1000,0))="","",INDEX('🎓 Alumnas'!$E$2:$E$1000,MATCH($C52,'🎓 Alumnas'!$B$2:$B$1000,0))),"")) | G52: =IF($C52="","",IFERROR(IF(INDEX('🎓 Alumnas'!$F$2:$F$1000,MATCH($C52,'🎓 Alumnas'!$B$2:$B$1000,0))="","",INDEX('🎓 Alumnas'!$F$2:$F$1000,MATCH($C52,'🎓 Alumnas'!$B$2:$B$1000,0))),"")) | H52: =IF(G52="","",DATEDIF(G52,TODAY(),"Y")) | J52: =IF(I52="","",IF(LEFT(I52,6)="1 Pole","Alquiler",IF(LEFT(I52,7)="1 Clase","Clase suelta","Paquete"))) | N52: =IF(M52="","",L52*M52) | R52: =IF(C52="","",IF(COUNTIF($C$2:C52,C52)=1,"Nueva","Recurrente")) | S52: =IF(OR(C52="",J52<>"Paquete"),"",COUNTIFS($C$2:C52,C52,$J$2:J52,"Paquete"))
A53: I-053 | D53: =IF($C53="","",IFERROR(IF(INDEX('🎓 Alumnas'!$C$2:$C$1000,MATCH($C53,'🎓 Alumnas'!$B$2:$B$1000,0))="","",INDEX('🎓 Alumnas'!$C$2:$C$1000,MATCH($C53,'🎓 Alumnas'!$B$2:$B$1000,0))),"")) | E53: =IF($C53="","",IFERROR(IF(INDEX('🎓 Alumnas'!$D$2:$D$1000,MATCH($C53,'🎓 Alumnas'!$B$2:$B$1000,0))="","",INDEX('🎓 Alumnas'!$D$2:$D$1000,MATCH($C53,'🎓 Alumnas'!$B$2:$B$1000,0))),"")) | F53: =IF($C53="","",IFERROR(IF(INDEX('🎓 Alumnas'!$E$2:$E$1000,MATCH($C53,'🎓 Alumnas'!$B$2:$B$1000,0))="","",INDEX('🎓 Alumnas'!$E$2:$E$1000,MATCH($C53,'🎓 Alumnas'!$B$2:$B$1000,0))),"")) | G53: =IF($C53="","",IFERROR(IF(INDEX('🎓 Alumnas'!$F$2:$F$1000,MATCH($C53,'🎓 Alumnas'!$B$2:$B$1000,0))="","",INDEX('🎓 Alumnas'!$F$2:$F$1000,MATCH($C53,'🎓 Alumnas'!$B$2:$B$1000,0))),"")) | H53: =IF(G53="","",DATEDIF(G53,TODAY(),"Y")) | J53: =IF(I53="","",IF(LEFT(I53,6)="1 Pole","Alquiler",IF(LEFT(I53,7)="1 Clase","Clase suelta","Paquete"))) | N53: =IF(M53="","",L53*M53) | R53: =IF(C53="","",IF(COUNTIF($C$2:C53,C53)=1,"Nueva","Recurrente")) | S53: =IF(OR(C53="",J53<>"Paquete"),"",COUNTIFS($C$2:C53,C53,$J$2:J53,"Paquete"))
... A400: I-399 | D400: =IF($C400="","",IFERROR(IF(INDEX('🎓 Alumnas'!$C$2:$C$1000,MATCH($C400,'🎓 Alumnas'!$B$2:$B$1000,0))="","",INDEX('🎓 Alumnas'!$C$2:$C$1000,MATCH($C400,'🎓 Alumnas'!$B$2:$B$1000,0))),"")) | E400: =IF($C400="","",IFERROR(IF(INDEX('🎓 Alumnas'!$D$2:$D$1000,MATCH($C400,'🎓 Alumnas'!$B$2:$B$1000,0))="","",INDEX('🎓 Alumnas'!$D$2:$D$1000,MATCH($C400,'🎓 Alumnas'!$B$2:$B$1000,0))),"")) | F400: =IF($C400="","",IFERROR(IF(INDEX('🎓 Alumnas'!$E$2:$E$1000,MATCH($C400,'🎓 Alumnas'!$B$2:$B$1000,0))="","",INDEX('🎓 Alumnas'!$E$2:$E$1000,MATCH($C400,'🎓 Alumnas'!$B$2:$B$1000,0))),"")) | G400: =IF($C400="","",IFERROR(IF(INDEX('🎓 Alumnas'!$F$2:$F$1000,MATCH($C400,'🎓 Alumnas'!$B$2:$B$1000,0))="","",INDEX('🎓 Alumnas'!$F$2:$F$1000,MATCH($C400,'🎓 Alumnas'!$B$2:$B$1000,0))),"")) | H400: =IF(G400="","",DATEDIF(G400,TODAY(),"Y")) | J400: =IF(I400="","",IF(LEFT(I400,6)="1 Pole","Alquiler",IF(LEFT(I400,7)="1 Clase","Clase suelta","Paquete"))) | N400: =IF(M400="","",L400*M400) | R400: =IF(C400="","",IF(COUNTIF($C$2:C400,C400)=1,"Nueva","Recurrente")) | S400: =IF(OR(C400="",J400<>"Paquete"),"",COUNTIFS($C$2:C400,C400,$J$2:J400,"Paquete"))

Sheet 📑 Resumen Contable
A1: 📑 RESUMEN CONTABLE SIMPLIFICADO
A2: No reemplaza a un contador, pero te ayuda a ver de un vistazo si el negocio del día a día es rentable, separado de lo que invertiste para montarlo.
A4: 1. RESULTADO OPERATIVO (el día a día del negocio)
A5: Ingresos por clases / membresías (Pole) | B5: =SUM('🤸 Ingresos Pole'!N2:N1000) -> 7624000 | D5: ← Lo que entra por clases, paquetes y membresías.
A6: Ingresos por venta de mercancía (ropa/accesorios) | B6: =SUM('🛒 Ventas'!I:I) -> 0 | D6: ← Lo que entra por vender ropa, tops, shorts, accesorios, etc.
A7: TOTAL INGRESOS OPERATIVOS | B7: =B5+B6 -> 7624000
A9: Gastos operativos (marcados como 'Operativo' en Gastos) | B9: =SUMIF('💸 Gastos'!F:F,"Operativo",'💸 Gastos'!E:E) -> 906000 | D9: ← Solo suma los gastos que marcaste como 'Operativo' (no cuenta preoperativos ni inversión).
A11: UTILIDAD / PÉRDIDA OPERATIVA | B11: =B7-B9 -> 6718000 | D11: ← Si es negativo, el negocio del mes/periodo aún no se sostiene solo con lo operativo.
A13: 2. LO QUE INVERTISTE PARA MONTAR EL NEGOCIO (no es gasto del mes a mes)
A14: Activos fijos marcados como 'Inversión Inicial' | B14: =SUMIF('🏢 Activos Fijos'!K:K,"Inversión Inicial",'🏢 Activos Fijos'!H:H) -> 20857007 | D14: ← Poles, colchonetas, mobiliario, equipos... todo lo que ya marcaste 'Inversión Inicial' en Activos Fijos.
A15: Costo de mercancía inicial (ropa/accesorios comprados para abrir) | B15: =SUMIF(Marcancia!M:M,"Inversión Inicial",Marcancia!J:J) -> 1393575 | D15: ← Columna 'Costo Total' de la hoja Mercancía, solo lo marcado como 'Inversión Inicial' (no cuenta reposiciones futuras).
A16: Gastos marcados como 'Preoperativo' | B16: =SUMIF('💸 Gastos'!F:F,"Preoperativo",'💸 Gastos'!E:E) -> 11050280 | D16: ← Gastos antes de abrir (arreglo del local, trámites, decoración inicial, etc.).
A17: Gastos marcados como 'Inversión Inicial' | B17: =SUMIF('💸 Gastos'!F:F,"Inversión Inicial",'💸 Gastos'!E:E) -> 2300000 | D17: ← Ojo: si ya registraste la compra de mercancía aquí en Gastos, bórrala de aquí para no duplicarla; la mercancía va en la hoja Mercancía.
A18: TOTAL INVERTIDO PARA ABRIR | B18: =B14+B15+B16+B17 -> 35600862 | D18: ← Este monto no se resta cada mes; es lo que "debes recuperar" con las utilidades del negocio con el tiempo.
A20: 3. BALANCE GENERAL DEL PERIODO
A21: Utilidad operativa | B21: =B11 -> 6718000
A22: Menos: inversión / preoperativos del periodo | B22: =-B18 -> -35600862
A23: BALANCE NETO (caja real, incluyendo inversión) | B23: =B21+B22 -> -28882862 | D23: ← Este sí mezcla todo: cuánto ha salido realmente de caja/bolsillo hasta hoy, contando la inversión inicial.

Sheet 💸 Gastos
A1: ID Gasto | B1: Fecha | C1: Categoría | D1: Concepto / Descripción | E1: Valor ($) | F1: Clasificación Contable | G1: Registrado Por | H1: Método de Pago | I1: Notas
A2: GAS-001 | B2: 46260 | C2: Mantenimiento Local/Infraestructura | D2: Arreglo del techo | E2: 5000000 | F2: Preoperativo | G2: Carolina | H2: Efectivo | I2: Se pagó en dos plazos: 3 y 2 millones
A3: GAS-002 | B3: 46259 | C3: Envíos/Transporte | D3: Envío de 2 colchonetas | E3: 195000 | F3: Preoperativo | G3: Carolina | H3: Efectivo
A4: GAS-003 | B4: 46248 | C4: Marketing y Publicidad | D4: Pegatina redonda con logo x 112 | E4: 6543 | F4: Preoperativo | G4: Carolina | H4: Efectivo
A5: GAS-004 | B5: 46248 | C5: Marketing y Publicidad | D5: Bolsa blanca x 50 | E5: 10362 | F5: Preoperativo | G5: Carolina | H5: Efectivo
A6: GAS-005 | B6: 46248 | C6: Marketing y Publicidad | D6: Llavero metalico personalizado x 20 | E6: 24090 | F6: Preoperativo | G6: Carolina | H6: Efectivo | I6: 1169 por unidad
A7: GAS-006 | B7: 46216 | C7: Seguridad/señalizacion | D7: Pegatina de timbre | E7: 2164 | F7: Preoperativo | G7: Carolina | H7: Efectivo
A8: GAS-007 | B8: 46216 | C8: Seguridad/señalizacion | D8: Pegatina de vigilancia por camara X5 | E8: 5339 | F8: Preoperativo | G8: Carolina | H8: Efectivo
A9: GAS-008 | B9: 46248 | C9: Marketing y Publicidad | D9: Bolsa blanca personalizada en tela x 10 | E9: 14031 | F9: Preoperativo | G9: Carolina | H9: Efectivo
A10: GAS-009 | B10: 46248 | C10: Marketing y Publicidad | D10: llavero en aclirico x 10 | E10: 11352 | F10: Preoperativo | G10: Carolina | H10: Efectivo
A11: GAS-011 | B11: 46248 | C11: Seguridad/señalizacion | D11: Aviso de prohibido pasar x 3 | E11: 6683 | F11: Preoperativo | G11: Carolina | H11: Efectivo
A12: GAS-012 | B12: 46248 | C12: Decoracion/adecuacion | D12: Pegatina de bailarinas/gimnasia | E12: 3701 | F12: Preoperativo | G12: Carolina | H12: Efectivo
A13: GAS-013 | B13: 46248 | C13: Seguridad/señalizacion | D13: Avisosde baño x3 | E13: 17691 | F13: Preoperativo | G13: Carolina | H13: Efectivo
A14: GAS-014 | B14: 46248 | C14: Seguridad/señalizacion | D14: Aviso de botiquin y extintor x 2 | E14: 2719 | F14: Preoperativo | G14: Carolina | H14: Efectivo
A15: GAS-015 | B15: 46248 | C15: Seguridad/señalizacion | D15: Aviso de zona de evacuacion x 3 | E15: 8984 | F15: Preoperativo | G15: Carolina | H15: Efectivo
A16: GAS-016 | B16: 46248 | C16: Seguridad/señalizacion | D16: Cinta antideslizante | E16: 13776 | F16: Preoperativo | G16: Carolina | H16: Efectivo
A17: GAS-017 | B17: 46248 | C17: Seguridad/señalizacion | D17: Pegatina antideslizantes para tapete x 12 | E17: 3508 | F17: Preoperativo | G17: Carolina | H17: Efectivo
A18: GAS-018 | B18: 46259 | C18: Insumos y Aseo | D18: Toalla de papel x 1388 | E18: 42443 | F18: Preoperativo | G18: Carolina | H18: Efectivo
... A45: GAS-045 | B45: 46262 | C45: Decoracion/adecuacion | D45: Ferreteria | E45: 16500 | F45: Preoperativo | G45: Carolina | H45: Efectivo
A46: GAS-046 | B46: 46262 | C46: Eventos/celebraciones | D46: Desechables y dulces | F46: Preoperativo | G46: Carolina | H46: Efectivo | I46: inaguracion
A47: GAS-047 | B47: 46260 | C47: Marketing y Publicidad | D47: Elaboracion del logo | E47: 400000 | F47: Preoperativo | G47: Carolina | H47: Efectivo
A48: GAS-048 | B48: 46261 | C48: Decoracion/adecuacion | D48: Canaletas para luces de espejo | E48: 4500 | F48: Preoperativo | G48: Carolina | H48: Efectivo
A49: GAS-049 | B49: 46261 | C49: Decoracion/adecuacion | D49: Materas y plantas | E49: 300000 | F49: Preoperativo | G49: Carolina | H49: Efectivo
A50: GAS-050 | B50: 46263 | C50: Eventos/celebraciones | D50: Vasos y bolsa de agua | E50: 5700 | F50: Preoperativo | G50: Carolina | H50: Efectivo | I50: Inaguracion
A51: GAS-051 | B51: 46263 | C51: Decoracion/adecuacion | D51: Interruptor timbre | E51: 9500 | F51: Preoperativo | G51: Carolina | H51: Efectivo
A52: GAS-052 | B52: 46263 | C52: Decoracion/adecuacion | D52: Canaletas para luces de espejo | E52: 4500 | F52: Preoperativo | G52: Carolina | H52: Efectivo
A53: GAS-053 | B53: 46263 | C53: Eventos/celebraciones | D53: Alquiler de sillas | E53: 19800 | F53: Preoperativo | G53: Carolina | H53: Efectivo | I53: Inaguracion
A54: GAS-054 | B54: 46265 | C54: Insumos y Aseo | D54: Glade con repuesto para ambientador | E54: 20900 | F54: Preoperativo | G54: Carolina | H54: Efectivo
A55: GAS-055 | B55: 46266 | C55: Eventos/celebraciones | D55: Uber para trasporte de sillas | E55: 16100 | F55: Preoperativo | G55: Carolina | H55: Efectivo | I55: inaguracion
A56: GAS-029 | B56: 46274 | C56: Servicios Públicos | D56: Luz | E56: 35850 | F56: Preoperativo | G56: Carolina | H56: Efectivo
A57: GAS-030 | B57: 46281 | C57: Seguridad/señalizacion | D57: Insumos del botiquin | E57: 28100 | F57: Preoperativo | G57: Carolina | H57: Efectivo
A58: GAS-031 | B58: 46281 | C58: Insumos y Aseo | D58: Churrusco del baño | E58: 8000 | F58: Preoperativo | G58: Carolina | H58: Efectivo
A59: GAS-041 | B59: 46244 | C59: Arriendo | D59: De 20 dias | E59: 1650000 | F59: Preoperativo | G59: Carolina | H59: Efectivo
A60: GAS-042 | B60: 46266 | C60: Arriendo | E60: 2300000 | F60: Inversión Inicial | G60: Carolina | H60: Efectivo
A61: GAS-043 | B61: 46274 | C61: Decoracion/adecuacion | D61: Instalacion de pole | E61: 475000 | F61: Preoperativo | G61: Carolina | H61: Efectivo
A62: GAS-044 | B62: 46275 | C62: Insumos y Aseo | D62: Pago de dia de limpieza | E62: 60000 | F62: Preoperativo | G62: Carolina | H62: Efectivo
A63: GAS-045 | B63: 46280 | C63: Nómina / Personal | D63: Pago de instructor | E63: 906000 | F63: Operativo | G63: Carolina | H63: Efectivo
A64: GAS-046
A65: GAS-047
E66: =SUM(E2:E65) -> 14256280
A69: Guía rápida: 'Preoperativo' = gastos antes de abrir el salón. 'Inversión Inicial' = compras grandes/activos para montar el negocio. 'Operativo' = gastos del día a día ya abiertos.

Sheet Marcancia
A1: ID Entrada | B1: Fecha | C1: Código Prenda | D1: Descripción | E1: Talla | F1: Color | G1: Cantidad (+) | H1: Unidad de Medida | I1: Precio compra($) | J1: Costo Total ($) | K1: Precio venta | L1: Proveedor / Notas | M1: Clasificación
A2: ENT-001 | B2: 46216 | C2: TM | D2: Top Negro con esptampado blanco | E2: =MID(C2,2,LEN(C2)) -> M | F2: Negro | G2: 1 | H2: UN | I2: 13727 | J2: =IF(OR(G2="",I2=""),"",G2*I2) -> 13727 | K2: =I2*2 -> 27454 | M2: Inversión Inicial
A3: ENT-002 | B3: 46216 | C3: SS | D3: Short con malla lateral negro | E3: =MID(C3,2,LEN(C3)) -> S | F3: Negro | G3: 1 | H3: UN | I3: 13856 | J3: =IF(OR(G3="",I3=""),"",G3*I3) -> 13856 | K3: =I3*2 -> 27712 | M3: Inversión Inicial
A4: ENT-003 | B4: 46216 | C4: TS | D4: Top blanco estampado negro de calabera | E4: =MID(C4,2,LEN(C4)) -> S | F4: Blanco | G4: 1 | H4: UN | I4: 13424 | J4: =IF(OR(G4="",I4=""),"",G4*I4) -> 13424 | K4: =I4*2 -> 26848 | M4: Inversión Inicial
A5: ENT-004 | B5: 46229 | C5: RS | D5: Rodillera negra | E5: =MID(C5,2,LEN(C5)) -> S | F5: Negro | G5: 2 | H5: Par | I5: 8659 | J5: =IF(OR(G5="",I5=""),"",G5*I5) -> 17318 | K5: =I5*2 -> 17318 | M5: Inversión Inicial
A6: ENT-005 | B6: 46216 | C6: SM | D6: Short de rayas blancas y negras | E6: =MID(C6,2,LEN(C6)) -> M | F6: Combinado | G6: 1 | H6: UN | I6: 9977 | J6: =IF(OR(G6="",I6=""),"",G6*I6) -> 9977 | K6: =I6*2 -> 19954 | M6: Inversión Inicial
A7: ENT-006 | B7: 46226 | C7: TM | D7: Top Azul con tirantes cruzados en espalda | E7: =MID(C7,2,LEN(C7)) -> M | F7: Azul | G7: 1 | H7: UN | I7: 8622 | J7: =IF(OR(G7="",I7=""),"",G7*I7) -> 8622 | K7: =I7*2 -> 17244 | M7: Inversión Inicial
A8: ENT-007 | B8: 46226 | C8: TS | D8: Top negro, malla en espalda y frente | E8: =MID(C8,2,LEN(C8)) -> S | F8: Negro | G8: 1 | H8: UN | I8: 7501 | J8: =IF(OR(G8="",I8=""),"",G8*I8) -> 7501 | K8: =I8*2 -> 15002 | M8: Inversión Inicial
A9: ENT-008 | B9: 46226 | C9: SM | D9: Short con corazon lateral | E9: =MID(C9,2,LEN(C9)) -> M | F9: Variado | G9: 3 | H9: UN | I9: 5672 | J9: =IF(OR(G9="",I9=""),"",G9*I9) -> 17016 | K9: =I9*2 -> 11344 | M9: Inversión Inicial
A10: ENT-009 | B10: 46226 | C10: SS | D10: Short con cintura de leopardo | E10: =MID(C10,2,LEN(C10)) -> S | F10: Negro | G10: 1 | H10: UN | I10: 13779 | J10: =IF(OR(G10="",I10=""),"",G10*I10) -> 13779 | K10: =I10*2 -> 27558 | M10: Inversión Inicial
A11: ENT-010 | B11: 46226 | C11: RM | D11: Rodillera negra | E11: =MID(C11,2,LEN(C11)) -> M | F11: Negro | G11: 2 | H11: Par | I11: 9762 | J11: =IF(OR(G11="",I11=""),"",G11*I11) -> 19524 | K11: =I11*2 -> 19524 | M11: Inversión Inicial
A12: ENT-011 | B12: 46248 | C12: SL | D12: Short gris acanalado | E12: =MID(C12,2,LEN(C12)) -> L | F12: Gris | G12: 1 | H12: UN | I12: 5420 | J12: =IF(OR(G12="",I12=""),"",G12*I12) -> 5420 | K12: =I12*2 -> 10840 | M12: Inversión Inicial
A13: ENT-012 | B13: 46248 | C13: SXL | D13: Short negro de pliegues laterales | E13: =MID(C13,2,LEN(C13)) -> XL | F13: Negro | G13: 1 | H13: UN | I13: 10074 | J13: =IF(OR(G13="",I13=""),"",G13*I13) -> 10074 | K13: =I13*2 -> 20148 | M13: Inversión Inicial
... A17: ENT-016 | B17: 46268 | C17: CS | D17: Conjunto con estampado de leopardo | E17: =MID(C17,2,LEN(C17)) -> S | F17: Combinado | G17: 1 | H17: UN | I17: 14979 | J17: =IF(OR(G17="",I17=""),"",G17*I17) -> 14979 | K17: =I17*2 -> 29958 | M17: Inversión Inicial
A18: ENT-017 | B18: 46268 | C18: MU | D18: Media en malla | E18: =MID(C18,2,LEN(C18)) -> U | F18: Variado | G18: 6 | H18: UN | I18: 2832 | J18: =IF(OR(G18="",I18=""),"",G18*I18) -> 16992 | K18: 10000 | M18: Inversión Inicial
A19: ENT-018 | B19: 46268 | C19: TS | D19: Top con correa y hebilla frontal estampadpo de leopardo | E19: =MID(C19,2,LEN(C19)) -> S | F19: Combinado | G19: 1 | H19: UN | I19: 10038 | J19: =IF(OR(G19="",I19=""),"",G19*I19) -> 10038 | K19: =I19*2 -> 20076 | M19: Inversión Inicial
A20: ENT-019 | B20: 46268 | C20: A | D20: Alas de ada | E20: =MID(C20,2,LEN(C20)) | F20: Combinado | G20: 1 | H20: UN | I20: 8078 | J20: =IF(OR(G20="",I20=""),"",G20*I20) -> 8078 | K20: =I20*2 -> 16156 | M20: Inversión Inicial
A21: ENT-020 | B21: 46268 | C21: TS | D21: Top corset rojo de leopardo | E21: =MID(C21,2,LEN(C21)) -> S | F21: Combinado | G21: 1 | H21: UN | I21: 6759 | J21: =IF(OR(G21="",I21=""),"",G21*I21) -> 6759 | K21: 15000 | M21: Inversión Inicial
A22: ENT-021 | B22: 46268 | C22: A | D22: Accesorio en cuero para la pierna | E22: =MID(C22,2,LEN(C22)) | F22: Negro | G22: 1 | H22: Par | I22: 4719 | J22: =IF(OR(G22="",I22=""),"",G22*I22) -> 4719 | K22: =I22*2 -> 9438 | M22: Inversión Inicial
A23: ENT-022 | B23: 46268 | C23: A | D23: Accesorio en cuero sintetico para el cuello | E23: =MID(C23,2,LEN(C23)) | F23: Negro | G23: 1 | H23: UN | I23: 5206 | J23: =IF(OR(G23="",I23=""),"",G23*I23) -> 5206 | K23: =I23*2 -> 10412 | M23: Inversión Inicial
A24: ENT-023 | B24: 46268 | C24: A | D24: Accesorio en cuero sintetico multicapa negro | E24: =MID(C24,2,LEN(C24)) | F24: Negro | G24: 1 | H24: UN | I24: 7600 | J24: =IF(OR(G24="",I24=""),"",G24*I24) -> 7600 | K24: =I24*2 -> 15200 | M24: Inversión Inicial
A25: ENT-024 | B25: 46268 | C25: A | D25: Accesorio monedero estampado de pole | E25: =MID(C25,2,LEN(C25)) | F25: Negro | G25: 1 | H25: UN | I25: 5498 | J25: =IF(OR(G25="",I25=""),"",G25*I25) -> 5498 | K25: =I25*2 -> 10996 | M25: Inversión Inicial
A26: ENT-025 | B26: 46268 | C26: A | D26: Accesorio, botella de agua con estampado de pole | E26: =MID(C26,2,LEN(C26)) | F26: Azul | G26: 1 | H26: UN | I26: 10995 | J26: =IF(OR(G26="",I26=""),"",G26*I26) -> 10995 | K26: =I26*2 -> 21990 | M26: Inversión Inicial
A27: ENT-026 | B27: 46268 | C27: SS | D27: Short acanalado | E27: =MID(C27,2,LEN(C27)) -> S | F27: Purpura | G27: 1 | H27: UN | I27: 12479 | J27: =IF(OR(G27="",I27=""),"",G27*I27) -> 12479 | K27: =I27*2 -> 24958 | M27: Inversión Inicial
A28: ENT-027 | B28: 46268 | C28: SL | D28: Short con cintura de leopardo | E28: =MID(C28,2,LEN(C28)) -> L | F28: Negro | G28: 1 | H28: UN | I28: 9069 | J28: =IF(OR(G28="",I28=""),"",G28*I28) -> 9069 | K28: =I28*2 -> 18138 | M28: Inversión Inicial
A29: ENT-028 | B29: 46268 | C29: TL | D29: Top rojo con malla en espalda y tirantes cruzados | E29: =MID(C29,2,LEN(C29)) -> L | F29: Rojo | G29: 1 | H29: UN | I29: 8141 | J29: =IF(OR(G29="",I29=""),"",G29*I29) -> 8141 | K29: =I29*2 -> 16282 | M29: Inversión Inicial
A30: ENT-029 | B30: 46268 | C30: TM | D30: Top cordon al cuello | E30: =MID(C30,2,LEN(C30)) -> M | F30: Borgoña | G30: 1 | H30: UN | I30: 9400 | J30: =IF(OR(G30="",I30=""),"",G30*I30) -> 9400 | K30: =I30*2 -> 18800 | M30: Inversión Inicial
A31: ENT-030 | B31: 46268 | C31: TL | D31: Top street casual | E31: =MID(C31,2,LEN(C31)) -> L | F31: Borgoña | G31: 1 | H31: UN | I31: 8608 | J31: =IF(OR(G31="",I31=""),"",G31*I31) -> 8608 | K31: =I31*2 -> 17216 | M31: Inversión Inicial
A32: ENT-031 | B32: 46268 | C32: TS | D32: Top street casual | E32: =MID(C32,2,LEN(C32)) -> S | F32: Blanco | G32: 1 | H32: UN | I32: 8358 | J32: =IF(OR(G32="",I32=""),"",G32*I32) -> 8358 | K32: =I32*2 -> 16716 | M32: Inversión Inicial
A33: ENT-032 | B33: 46268 | C33: TXL | D33: Top street casual leopardo | E33: =MID(C33,2,LEN(C33)) -> XL | F33: Combinado | G33: 1 | H33: UN | I33: 7825 | J33: =IF(OR(G33="",I33=""),"",G33*I33) -> 7825 | K33: =I33*2 -> 15650 | M33: Inversión Inicial
... A39: ENT-038 | B39: 46268 | C39: MU | D39: Medias en malla | E39: =MID(C39,2,LEN(C39)) -> U | F39: Negro | G39: 8 | H39: UN | I39: 2365 | J39: =IF(OR(G39="",I39=""),"",G39*I39) -> 18920 | K39: =I39*2 -> 4730 | M39: Inversión Inicial
A40: ENT-039 | B40: 46268 | D40: Accesorio bolso en yute estampado de pole | E40: =MID(C40,2,LEN(C40)) | F40: Blanco | G40: 1 | H40: UN | I40: 10362 | J40: =IF(OR(G40="",I40=""),"",G40*I40) -> 10362 | K40: =I40*2 -> 20724 | M40: Inversión Inicial
A41: ENT-040 | B41: 46268 | C41: SL | D41: Short falda de flecos | E41: =MID(C41,2,LEN(C41)) -> L | F41: Negro | G41: 1 | H41: UN | I41: 9918 | J41: =IF(OR(G41="",I41=""),"",G41*I41) -> 9918 | K41: =I41*2 -> 19836 | M41: Inversión Inicial
A42: ENT-041 | B42: 46268 | C42: SM | D42: Short falda de flecos | E42: =MID(C42,2,LEN(C42)) -> M | F42: Negro | G42: 1 | H42: UN | I42: 9666 | J42: =IF(OR(G42="",I42=""),"",G42*I42) -> 9666 | K42: =I42*2 -> 19332 | M42: Inversión Inicial
A43: ENT-042 | B43: 46268 | C43: TU | D43: Top body de flecos | E43: =MID(C43,2,LEN(C43)) -> U | F43: Negro | G43: 1 | H43: UN | I43: 7992 | J43: =IF(OR(G43="",I43=""),"",G43*I43) -> 7992 | K43: =I43*2 -> 15984 | M43: Inversión Inicial
A44: ENT-043 | B44: 46268 | D44: Accesirio bufanda de flecos y lentejuelas | E44: =MID(C44,2,LEN(C44)) | F44: Dorado | G44: 1 | H44: UN | I44: 1998 | J44: =IF(OR(G44="",I44=""),"",G44*I44) -> 1998 | K44: =I44*2 -> 3996 | M44: Inversión Inicial
A45: ENT-044 | B45: 46262 | D45: Itac 2 | E45: =MID(C45,2,LEN(C45)) | G45: 6 | H45: UN | I45: 70000 | J45: =IF(OR(G45="",I45=""),"",G45*I45) -> 420000 | K45: 100000 | M45: Inversión Inicial
A46: ENT-045 | B46: 46262 | D46: Monkey gluey de 100 ml | E46: =MID(C46,2,LEN(C46)) | G46: 6 | H46: UN | I46: 90000 | J46: =IF(OR(G46="",I46=""),"",G46*I46) -> 540000 | K46: 120000 | M46: Inversión Inicial
A47: ENT-046 | E47: =MID(C47,2,LEN(C47))
A48: ENT-047 | E48: =MID(C48,2,LEN(C48))
H51: Total | I51: =SUM(I2:I50) -> 533095 | J51: =SUM(J2:J50) -> 1393575
A54: Nota: todas las entradas actuales se marcaron 'Inversión Inicial' porque son el stock con el que abriste. Cuando compres mercancía nueva ya con el negocio abierto (reposición), márcala como 'Reposición de Stock' para que NO se sume otra vez al capital inicial en el Resumen Contable.

Sheet 🏢 Activos Fijos
A1: Código Activo | B1: Nombre del Activo | C1: Categoría | D1: Ubicación | E1: Cantidad | F1: Estado | G1: Valor Est. Unit ($) | H1: Valor Total ($) | I1: Fecha Adquisición | J1: Observaciones | K1: Clasificación
A2: ACT-001 | B2: Barra / Pole Profesional Dorado | C2: Equipamiento Pole | D2: Salón Principal | E2: 2 | F2: Excelente | G2: 2850000 | H2: =IF(OR(E2="",G2=""),"",E2*G2) -> 5700000 | I2: 46274 | J2: Poles de acero inoxidable removibles | K2: Inversión Inicial
A3: ACT-002 | B3: Barra / Pole Profesional Plateado | C3: Equipamiento Pole | D3: Salón Principal | E3: 3 | F3: Excelente | G3: 2000000 | H3: =IF(OR(E3="",G3=""),"",E3*G3) -> 6000000 | I3: 46274 | J3: Poles de bronce removibles | K3: Inversión Inicial
A4: ACT-003 | B4: Poltrona | C4: Mobiliario y Confort | D4: Recepción | E4: 2 | F4: Excelente | G4: 750000 | H4: =IF(OR(E4="",G4=""),"",E4*G4) -> 1500000 | I4: 46280 | J4: Sillas individuales | K4: Inversión Inicial
A5: ACT-004 | B5: Colchoneta profesional para Pole solo espuma | C5: Equipamiento Pole | D5: Salón Principal | E5: 1 | F5: Excelente | G5: 895000 | H5: =IF(OR(E5="",G5=""),"",E5*G5) -> 895000 | I5: 46249 | J5: Espuma alta densidad | K5: Inversión Inicial
A6: ACT-005 | B6: Colchoneta profesional para Pole espuma + casata | C6: Equipamiento Pole | D6: Salón Principal | E6: 1 | F6: Excelente | G6: 1180000 | H6: =IF(OR(E6="",G6=""),"",E6*G6) -> 1180000 | I6: 46249 | J6: Espuma + casata | K6: Inversión Inicial
A7: ACT-006 | B7: Atomizador Negro de 250 ml | C7: Aseo y Limpieza | D7: Salón / Recepción | E7: 1 | F7: Reemplazar | G7: 5048 | H7: =IF(OR(E7="",G7=""),"",E7*G7) -> 5048 | I7: 46249 | J7: Para desinfección de poles | K7: Inversión Inicial
A8: ACT-007 | B8: Atomizador vintage negro 300 ml | C8: Aseo y Limpieza | D8: Salón / Recepción | E8: 1 | F8: Excelente | G8: 6939 | H8: =IF(OR(E8="",G8=""),"",E8*G8) -> 6939 | I8: 46249 | J8: Para desinfección | K8: Inversión Inicial
A9: ACT-008 | B9: Atomizador vintage diamante-gris 400 ml | C9: Aseo y Limpieza | D9: Salón / Recepción | E9: 1 | F9: Excelente | G9: 4950 | H9: =IF(OR(E9="",G9=""),"",E9*G9) -> 4950 | I9: 46249 | J9: Para desinfección | K9: Inversión Inicial
A10: ACT-009 | B10: Canastas de Almacenamiento Objetos | C10: Mobiliario y Confort | D10: Vestier / Salón | E10: 6 | F10: Excelente | G10: 8232 | H10: =IF(OR(E10="",G10=""),"",E10*G10) -> 49392 | I10: 46249 | J10: Canastas organizadoras alumnas | K10: Inversión Inicial
A11: ACT-010 | B11: Bafle AS-800 pro | C11: Equipos y tecnologia | D11: Salón Principal | E11: 1 | F11: Excelente | G11: 590000 | H11: =IF(OR(E11="",G11=""),"",E11*G11) -> 590000 | I11: 46249 | J11: Torre de sonido con micrófono | K11: Inversión Inicial
A12: ACT-011 | B12: Mate negro | C12: Equipamiento Pole | D12: Salón Principal | E12: 4 | F12: Excelente | G12: 13856 | H12: =IF(OR(E12="",G12=""),"",E12*G12) -> 55424 | I12: 46249 | J12: Promediando lo del mismo color | K12: Inversión Inicial
A13: ACT-012 | B13: Mate Gris | C13: Equipamiento Pole | D13: Salón Principal | E13: 1 | F13: Excelente | G13: 13220 | H13: =IF(OR(E13="",G13=""),"",E13*G13) -> 13220 | I13: 46249 | K13: Inversión Inicial
A14: ACT-013 | B14: Bandas de resistencia | C14: Equipamiento Pole | D14: Salón Principal | E14: 10 | F14: Excelente | G14: 1666 | H14: =IF(OR(E14="",G14=""),"",E14*G14) -> 16660 | I14: 46249 | K14: Inversión Inicial
A15: ACT-014 | B15: Bandas para Mate | C15: Mobiliario y Confort | D15: Salón Principal | E15: 2 | F15: Excelente | G15: 1703 | H15: =IF(OR(E15="",G15=""),"",E15*G15) -> 3406 | I15: 46249 | K15: Inversión Inicial
A16: ACT-015 | B16: Toalla de limpieza negra | C16: Aseo y Limpieza | D16: Salón Principal | E16: 6 | F16: Excelente | G16: 1486 | H16: =IF(OR(E16="",G16=""),"",E16*G16) -> 8916 | I16: 46216 | K16: Inversión Inicial
A17: ACT-018 | B17: Estante de pared compacto blanco de 3 niveles | C17: Mobiliario y Confort | D17: Recepción | E17: 1 | F17: Excelente | G17: 17921 | H17: =IF(OR(E17="",G17=""),"",E17*G17) -> 17921 | I17: 46249 | K17: Inversión Inicial
A18: ACT-019 | B18: Aclirico personalizado rectanguar | C18: Decoración | D18: Recepción | E18: 1 | F18: Excelente | G18: 13929 | H18: =IF(OR(E18="",G18=""),"",E18*G18) -> 13929 | I18: 46249 | K18: Inversión Inicial
A19: ACT-020 | B19: Tapete personalizado | C19: Decoración | D19: Recepción | E19: 1 | F19: Excelente | G19: 11662 | H19: =IF(OR(E19="",G19=""),"",E19*G19) -> 11662 | I19: 46249 | K19: Inversión Inicial
A20: ACT-021 | B20: Aclirico personalizado redondo | C20: Decoración | D20: Recepción | E20: 1 | F20: Excelente | G20: 10994 | H20: =IF(OR(E20="",G20=""),"",E20*G20) -> 10994 | I20: 46249 | K20: Inversión Inicial
A21: ACT-022 | B21: Ganchos con revestimiento plastico | C21: Mobiliario y Confort | D21: Recepción | E21: 20 | F21: Excelente | G21: 924 | H21: =IF(OR(E21="",G21=""),"",E21*G21) -> 18480 | I21: 46249 | K21: Inversión Inicial
A22: ACT-023 | B22: Tendedero de ropa plegable blanco | C22: Mobiliario y Confort | D22: Recepción | E22: 1 | F22: Excelente | G22: 17108 | H22: =IF(OR(E22="",G22=""),"",E22*G22) -> 17108 | I22: 46249 | K22: Inversión Inicial
A23: ACT-024 | B23: Mate rosado | C23: Equipamiento Pole | D23: Recepción | E23: 1 | F23: Excelente | G23: 9583 | H23: =IF(OR(E23="",G23=""),"",E23*G23) -> 9583 | I23: 46249 | K23: Inversión Inicial
A24: ACT-025 | B24: Proyector led de planetas | C24: Equipos y tecnologia | D24: Salón Principal | E24: 1 | F24: Excelente | G24: 8842 | H24: =IF(OR(E24="",G24=""),"",E24*G24) -> 8842 | I24: 46259 | K24: Inversión Inicial
... A36: ACT-037 | B36: Toalla de limpieza azul | C36: Aseo y Limpieza | D36: Salón Principal | E36: 22 | F36: Excelente | G36: 541 | H36: =IF(OR(E36="",G36=""),"",E36*G36) -> 11902 | I36: 46277 | K36: Inversión Inicial
A37: ACT-038 | B37: Telas para practica de pole | C37: Equipamiento Pole | D37: Salón Principal | F37: Excelente | G37: 25000 | H37: =IF(OR(E37="",G37=""),"",E37*G37) | I37: 46253 | K37: Inversión Inicial
A38: ACT-039 | B38: Estrutura del techo (travesaño) | C38: Equipamiento Pole | D38: Salón Principal | E38: 1 | F38: Excelente | G38: 1300000 | H38: =IF(OR(E38="",G38=""),"",E38*G38) -> 1300000 | I38: 46260 | K38: Inversión Inicial
A39: ACT-040 | B39: Zapatero | C39: Mobiliario y Confort | D39: Salón Principal | E39: 1 | F39: Excelente | G39: 380000 | H39: =IF(OR(E39="",G39=""),"",E39*G39) -> 380000 | I39: 46260 | K39: Inversión Inicial
A40: ACT-041 | B40: Mueble entrepaños para vestier | C40: Mobiliario y Confort | D40: Vestier | E40: 1 | F40: Excelente | G40: 1030000 | H40: =IF(OR(E40="",G40=""),"",E40*G40) -> 1030000 | I40: 46260 | K40: Inversión Inicial
A41: ACT-042 | B41: Espejos | C41: Equipamiento Pole | D41: Salón Principal | E41: 1 | F41: Excelente | G41: 1550000 | H41: =IF(OR(E41="",G41=""),"",E41*G41) -> 1550000 | I41: 46255 | K41: Inversión Inicial
A42: ACT-043 | B42: Papelera | C42: Aseo y Limpieza | D42: Recepción | E42: 1 | F42: Excelente | G42: 12500 | H42: =IF(OR(E42="",G42=""),"",E42*G42) -> 12500 | I42: 46268 | K42: Inversión Inicial
A43: ACT-044 | B43: Extension electrica | C43: Equipos y tecnologia | D43: Bodega | E43: 1 | F43: Excelente | G43: 10000 | H43: =IF(OR(E43="",G43=""),"",E43*G43) -> 10000 | I43: 46281 | K43: Inversión Inicial
A44: ACT-046 | B44: Bases empotradas | C44: Equipamiento Pole | D44: Salón Principal | E44: 5 | F44: Excelente | G44: 50000 | H44: =IF(OR(E44="",G44=""),"",E44*G44) -> 250000 | I44: 46274 | K44: Inversión Inicial
A47: ACT-039 | H47: =IF(OR(E47="",G47=""),"",E47*G47) | K47: Inversión Inicial
D48: TOTAL VALOR ACTIVOS | E48: =SUM(E2:E47) -> 125 | H48: =SUM(H2:H47) -> 20857007
A50: Nota: se marcaron todos como 'Inversión Inicial' porque se compraron para montar el salón. Si compras algo nuevo más adelante ya abierto, marca esa fila como 'Posterior a Apertura'.

Sheet 🛒 Ventas
A1: Ref Venta (Consecutivo) | B1: Fecha | C1: Código Prenda | D1: Descripción | E1: Talla | F1: Color | G1: Cant. Vendida (-) | H1: Precio Unit. ($) | I1: Total Venta ($) | J1: Método Pago | K1: Registrado Por
A2: V1 | B2: 46263 | D2: =IFERROR(IF(C2="","",VLOOKUP(C2,#REF!, 3, FALSE())), "") | E2: =IFERROR(IF(C2="","",VLOOKUP(C2,#REF!, 4, FALSE())), "") | H2: =IFERROR(IF(C2="","",VLOOKUP(C2,#REF!, 6, FALSE())), 0) | I2: =IF(OR(G2="",H2=""),"",G2*H2) | J2: Nequi | K2: Nicole
A3: V2 | D3: =IFERROR(IF(C3="","",VLOOKUP(C3,#REF!, 3, FALSE())), "") | E3: =IFERROR(IF(C3="","",VLOOKUP(C3,#REF!, 4, FALSE())), "") | H3: =IFERROR(IF(C3="","",VLOOKUP(C3,#REF!, 6, FALSE())), 0) | I3: =IF(OR(G3="",H3=""),"",G3*H3)
A4: V3 | D4: =IFERROR(IF(C4="","",VLOOKUP(C4,#REF!, 3, FALSE())), "") | E4: =IFERROR(IF(C4="","",VLOOKUP(C4,#REF!, 4, FALSE())), "") | H4: =IFERROR(IF(C4="","",VLOOKUP(C4,#REF!, 6, FALSE())), 0) | I4: =IF(OR(G4="",H4=""),"",G4*H4)
A5: V4 | D5: =IFERROR(IF(C5="","",VLOOKUP(C5,#REF!, 3, FALSE())), "") | E5: =IFERROR(IF(C5="","",VLOOKUP(C5,#REF!, 4, FALSE())), "") | H5: =IFERROR(IF(C5="","",VLOOKUP(C5,#REF!, 6, FALSE())), 0) | I5: =IF(OR(G5="",H5=""),"",G5*H5)
A6: V5 | D6: =IFERROR(IF(C6="","",VLOOKUP(C6,#REF!, 3, FALSE())), "") | E6: =IFERROR(IF(C6="","",VLOOKUP(C6,#REF!, 4, FALSE())), "") | H6: =IFERROR(IF(C6="","",VLOOKUP(C6,#REF!, 6, FALSE())), 0) | I6: =IF(OR(G6="",H6=""),"",G6*H6)
A7: V6 | D7: =IFERROR(IF(C7="","",VLOOKUP(C7,#REF!, 3, FALSE())), "") | E7: =IFERROR(IF(C7="","",VLOOKUP(C7,#REF!, 4, FALSE())), "") | H7: =IFERROR(IF(C7="","",VLOOKUP(C7,#REF!, 6, FALSE())), 0) | I7: =IF(OR(G7="",H7=""),"",G7*H7)
A8: V7 | D8: =IFERROR(IF(C8="","",VLOOKUP(C8,#REF!, 3, FALSE())), "") | E8: =IFERROR(IF(C8="","",VLOOKUP(C8,#REF!, 4, FALSE())), "") | H8: =IFERROR(IF(C8="","",VLOOKUP(C8,#REF!, 6, FALSE())), 0) | I8: =IF(OR(G8="",H8=""),"",G8*H8)
A9: V8 | D9: =IFERROR(IF(C9="","",VLOOKUP(C9,#REF!, 3, FALSE())), "") | E9: =IFERROR(IF(C9="","",VLOOKUP(C9,#REF!, 4, FALSE())), "") | H9: =IFERROR(IF(C9="","",VLOOKUP(C9,#REF!, 6, FALSE())), 0) | I9: =IF(OR(G9="",H9=""),"",G9*H9)
A10: V9 | D10: =IFERROR(IF(C10="","",VLOOKUP(C10,#REF!, 3, FALSE())), "") | E10: =IFERROR(IF(C10="","",VLOOKUP(C10,#REF!, 4, FALSE())), "") | H10: =IFERROR(IF(C10="","",VLOOKUP(C10,#REF!, 6, FALSE())), 0) | I10: =IF(OR(G10="",H10=""),"",G10*H10)
A11: V10 | D11: =IFERROR(IF(C11="","",VLOOKUP(C11,#REF!, 3, FALSE())), "") | E11: =IFERROR(IF(C11="","",VLOOKUP(C11,#REF!, 4, FALSE())), "") | H11: =IFERROR(IF(C11="","",VLOOKUP(C11,#REF!, 6, FALSE())), 0) | I11: =IF(OR(G11="",H11=""),"",G11*H11)
A12: V11 | D12: =IFERROR(IF(C12="","",VLOOKUP(C12,#REF!, 3, FALSE())), "") | E12: =IFERROR(IF(C12="","",VLOOKUP(C12,#REF!, 4, FALSE())), "") | H12: =IFERROR(IF(C12="","",VLOOKUP(C12,#REF!, 6, FALSE())), 0) | I12: =IF(OR(G12="",H12=""),"",G12*H12)
A13: V12 | D13: =IFERROR(IF(C13="","",VLOOKUP(C13,#REF!, 3, FALSE())), "") | E13: =IFERROR(IF(C13="","",VLOOKUP(C13,#REF!, 4, FALSE())), "") | H13: =IFERROR(IF(C13="","",VLOOKUP(C13,#REF!, 6, FALSE())), 0) | I13: =IF(OR(G13="",H13=""),"",G13*H13)
A14: V13 | D14: =IFERROR(IF(C14="","",VLOOKUP(C14,#REF!, 3, FALSE())), "") | E14: =IFERROR(IF(C14="","",VLOOKUP(C14,#REF!, 4, FALSE())), "") | H14: =IFERROR(IF(C14="","",VLOOKUP(C14,#REF!, 6, FALSE())), 0) | I14: =IF(OR(G14="",H14=""),"",G14*H14)
... A41: V40 | D41: =IFERROR(IF(C41="","",VLOOKUP(C41,#REF!, 3, FALSE())), "") | E41: =IFERROR(IF(C41="","",VLOOKUP(C41,#REF!, 4, FALSE())), "") | H41: =IFERROR(IF(C41="","",VLOOKUP(C41,#REF!, 6, FALSE())), 0) | I41: =IF(OR(G41="",H41=""),"",G41*H41)

Sheet ⚙️ Configuración
A1: LISTAS DE PARÁMETROS
A2: Estas listas alimentan los menús desplegables de todas las hojas. Para agregar una opción nueva, escríbela al final de la lista correspondiente (no dejes filas vacías en medio).
A3: Tipo | C3: Tallas | E3: Metodos Pago | G3: Estados Activo | I3: Categorias Activos | K3: Categorías Gastos | M3: Color | O3: Unidades Medida | Q3: Codigo | S3: Clasificación Contable | U3: Descripcion | W3: Clasificación Activo | Y3: Clasificación Mercancía | AA3: Concepto
A4: Short | C4: XS | E4: Nequi | G4: Excelente | I4: Equipamiento Pole | K4: Arriendo | M4: Negro | O4: UN | Q4: TM | S4: Operativo | U4: Clase Suelta | W4: Inversión Inicial | Y4: Inversión Inicial | AA4: 4 clases: Sport Fitness Challenge $200.000
A5: Top/Sujetador | C5: S | E5: Daviplata | G5: Bueno | I5: Aseo y Limpieza | K5: Servicios Públicos | M5: Azul | O5: Par | Q5: TS | S5: Preoperativo | U5: Paquete de Clases | W5: Posterior a Apertura | Y5: Reposición de Stock | AA5: 9 clases: Sport Power Team $350.000
A6: Mallas | C6: M | E6: Efectivo | G6: Regular / Mantenimiento | I6: Mobiliario y Confort | K6: Nómina / Personal | M6: Rojo | O6: Pack | Q6: TL | S6: Inversión Inicial | U6: Membresía Mensual | AA6: 12 clases: Sport Intense $420.000
A7: Accesorios | C7: L | E7: Transferencia Bancaria | G7: Reemplazar | I7: Decoración | K7: Insumos y Aseo | M7: Verde | O7: Caja | Q7: TXS | U7: Evento / Taller | AA7: 16 clases : Sport Elite club $480.000
A8: Grip | C8: XL | E8: Tarjeta Débito/Crédito | G8: Aberiado | I8: Equipos y tecnologia | K8: Mantenimiento Equipos | M8: Amarillo | O8: Kit | Q8: TXL | U8: Otro | AA8: 1 Pole: Alquiler $22000
A9: Conjunto | C9: XXL | I9: Otros | K9: Marketing y Publicidad | M9: Blanco | Q9: TXXL | U9: Promo 2x1 | AA9: 1 Clase: Individual $50000
C10: Única | K10: Software / Suscripciones | M10: Combinado | Q10: SS | U10: Alquiler Pole
K11: Mantenimiento Local/Infraestructura | M11: Variado | Q11: SXS
K12: Envíos/Transporte | M12: Gris | Q12: SM
K13: Seguridad/señalizacion | M13: Purpura | Q13: SL
K14: Decoracion/adecuacion | M14: Borgoña | Q14: SXL
K15: Tramites/papeleria | M15: Dorado | Q15: SXXL
K16: Eventos/celebraciones | Q16: RS
K17: Otros | Q17: RM
Q18: RL
Q19: CS
Q20: CM
Q21: CXS
Q22: CL
Q23: CXL
Q24: CXXL
Q25: MU
Q26: A
Q27: SU
Q28: TU
